Workbook

Sheet 00_Metadaten
A1: Herkunftsnachweis
A2: Quelle | B2: file:///tmp/cat.json
A3: Git-Commit (SHA) | B3: n/a — lokale Quelldatei, SHA-256 ist Versionsanker
A4: Commit-Datum | B4: n/a
A5: SHA-256 der Quelldatei | B5: db3a1417d7e904315a0886f450129832e19c57324660358c830357349f552332
A6: Abgerufen am (UTC) | B6: 2026-08-17T14:38:17.443549+00:00
A8: Katalog
A9: Katalog-UUID | B9: bd38cb1f-b4cd-4756-b181-a5568e1d9f45
A10: Katalog-Version | B10: 2026-07-29T06:42:34.226285+00:00
A11: Zuletzt geaendert (BSI) | B11: 2026-07-29T06:42:42.582326619Z
A12: OSCAL-Version | B12: 1.1.3
A13: Anzahl Anforderungen | B13: 1000
A15: Erzeugung
A16: Werkzeug-Version | B16: 0.1.0

Sheet Deckblatt
B1: Einstufung gemäß Vorgaben der Sicherheitskonzeption
B3: Dokumententitel | C3: Praktiken und Grundschutz++-Checks
B4: Layout | C4: BSI-Vorlage A.3.4, Kompendium-Edition 2023
B5: Katalog | C5: Grundschutz++ (OSCAL), Anwenderkatalog des BSI
B6: Katalog-Version | C6: 2026-07-29T06:42:34.226285+00:00
B7: Git-Commit | C7: n/a — lokale Quelldatei, SHA-256 ist Versionsanker
B8: SHA-256 der Quelldatei | C8: db3a1417d7e904315a0886f450129832e19c57324660358c830357349f552332
B9: Erzeugt am (UTC) | C9: 2026-08-17T14:38:17.443549+00:00
B10: Werkzeug | C10: gspp-tool 0.1.0
B12: Anforderungszeilen | C12: 652
B13: Teilanforderungen (bewertbar) | C13: 974
B15: Zuordnung zu IT-Grundschutz 2023
B16: Quelle | C16: Offizielles BSI-Mapping (control_layer/Mappings/IT-GS2023-zu-GSpp)
B17: Abdeckung | C17: Unvollstaendig, laut BSI noch in Pilotierung - nur ca. 30% der GS++-Anforderungen haben aktuell eine Zuordnung. Leere Spalten 'Alte Anforderung' bedeuten 'noch nicht kartiert', nicht 'keine Beziehung'.
B19: Spalten ein-/ausblenden
B20: Bedienung | C20: Alle 25 Spalten sind beim Öffnen sichtbar. Über den Spaltenköpfen stehen kleine +/− Schaltflächen, mit denen sich zwei Blöcke unabhängig einklappen lassen: 'Zuordnung IT-GS 2023' (Spalten N–O) und 'Guidance' (Spalten P–Y: Erläuterung, Zielobjekte, Dokumentation, Ergebnis, Gefährdungen, Aufwand, vier Schutzziele). Keine Makros nötig.
B21: Schwerpunkt (Schutzziel) | C21: Nennt nur Schutzziele mit Wert 2 – also jene, die laut BSI im Zentrum der Anforderung stehen. Leer heißt: kein Schutzziel besonders betont (gilt für rund die Hälfte der Anforderungen). Die Einzelwerte 0/1/2 stehen im Guidance-Block.
B23: Offene fachliche Annahme
B24: Spalte 'Schutz' | C24: GS++ kennt zwei Schutzbedarfsstufen, die 2023er-Vorlage drei Anforderungskategorien. Abgebildet wird: erhöht -> erhöhter Schutzbedarf; normal-SdT + MUSS -> Basis; normal-SdT + SOLLTE/KANN -> Standard. Diese Zuordnung ist nicht vom BSI dokumentiert und fachlich zu bestätigen.

Sheet ARCH
A1: Einstufung gemäß Vorgaben der Sicherheitskonzeption
A3: ARCH | B3: Architektur
A4: Zielobjekte | B4: =IF(Praktiken!D5="","",Praktiken!D5)
A5: Zuständig | B5: =IF(Praktiken!S5="","",Praktiken!S5)
A6: Anforderung | B6: Beschreibung | C6: Teilanforderung | D6: Schutz | E6: Anforderungstext | F6: Umsetzung | G6: Nachweis | H6: Status | I6: Maßnahme | J6: Befragte Person | K6: Prüfende Person | L6: Datum der Prüfung | M6: Schwerpunkt (Schutzziel) | N6: Alte Anforderung (IT-GS 2023) | O6: Beziehung (IT-GS 2023) | P6: Erläuterung | Q6: Zielobjekt-Kategorien | R6: Dokumentation | S6: Ergebnis | T6: Gefährdungen | U6: Aufwand | V6: Vertraulichkeit | W6: Integrität | X6: Verfügbarkeit | Y6: Authentizität
A7: ARCH.1.1 | B7: Verfahren und Regelungen | D7: Basis-Anforderungen | E7: Gesamt: | H7: =IF(OR(COUNTBLANK($H$8:$H$10)>0,COUNTIF($H$8:$H$10,"unbearbeitet")=COUNTA($H$8:$H$10)),"Bitte Teilanforderungen ausfüllen",IF(COUNTIF($H$8:$H$10,"zu klären")>0,"zu klären",IF(COUNTIF($H$8:$H$10,"entbehrlich")=COUNTA($H$8:$H$10),"entbehrlich",IF(COUNTIF($H$8:$H$10,"verwiesen")=COUNTA($H$8:$H$10),"verwiesen",IF(COUNTIF($H$8:$H$10,"nein")+COUNTIF($H$8:$H$10,"entbehrlich")=COUNTA($H$8:$H$10),"nein",IF(COUNTIF($H$8:$H$10,"ja")+COUNTIF($H$8:$H$10,"entbehrlich")+COUNTIF($H$8:$H$10,"verwiesen")=COUNTA($H$8:$H$10),"ja","teilweise")))))) -> Bitte Teilanforderungen ausfüllen | N7: APP.3.6.A1-UA.2; INF.14.A13-UA.2; NET.1.1.A1-UA.1; NET.1.1.A13-UA.1; NET.1.1.A16-UA.1; NET.1.1.A17-UA.1; NET.1.1.A2-UA.4; NET.1.1.A2-UA.5; NET.1.1.A25-UA.1; NET.1.1.A3-UA.1; NET.1.1.A3-UA.3; NET.1.2.A1-UA.1; NET.1.2.A11-UA.1; NET.1.2.A11-UA.9; NET.1.2.A12-UA.1; NET.1.2.A14-UA.2; NET.1.2.A15-UA.1; OPS.1.1.1.A15-UA.3 | O7: subset-of; subset-of; subset-of; subset-of; subset-of; subset-of; subset-of; subset-of; subset-of; subset-of; subset-of; subset-of; subset-of; subset-of; subset-of; subset-of; subset-of; subset-of | P7: Die Netzarchitektur ist der strukturierte Entwurf einer Netzinfrastruktur, einschließlich der IT-Systeme und verbundsbezogenen Schutzmechanismen darin. Hierzu gehören die Segmentierung und Filterung von kabelgebundenen und kabellosen Netzen, Netzmanagement sowie die Redundanz wichtiger Systeme für eine ausreichende Gewährleistung der Verfügbarkeit. Die bei der Festlegung des Verfahrens im Einzelnen zu berücksichtigenden Inhalte ergeben sich aus den Anforderungen dieser Praktik. Empfehlenswert ist ein Design des Netzes nach dem Zero-Trust-Prinzip (siehe BSI Positionspapier Zero-Trust). Dennoch sind Netzgrenzen zur Isolierung durch Filterung oder Zugbrücken bei Angriffen weiterhin sinnvoll. Weitere Informationen zur Absicherung von Netzen sind in ISO/IEC 27033 zu finden. | S7: Verfahren und Regelungen zur Architektur des Netzes und damit verbundener Infrastrukturen | T7: G 0.18 – Fehlplanung oder fehlende Anpassung; G 0.29 – Verstoß gegen Gesetze oder Regelungen; G 0.30 – Unberechtigte Nutzung oder Administration von Geräten und Systemen | U7: 0 | V7: 1 | W7: 1 | X7: 1 | Y7: 1
A8: ARCH.1.1 | B8: Verfahren und Regelungen | C8: ARCH.1.1.1 | D8: Basis-Anforderungen | E8: Architektur MUSS die Verfahren und Regelungen dokumentieren. | H8: unbearbeitet | M8: Vertraulichkeit, Integrität | N8: CON.8.A12-UA.4; INF.12.A10-UA.1; INF.12.A10-UA.2; INF.12.A10-UA.6; INF.12.A10-UA.8; INF.13.A3-UA.4; ISMS.1.A12-UA.6; NET.1.1.A2-UA.1; NET.1.1.A2-UA.3 | O8: subset-of; subset-of; subset-of; subset-of; subset-of; subset-of; subset-of; equivalent-to; subset-of | P8: Ohne eine Dokumentation könnte die Einhaltung der Verfahren und Regelungen von der Tagesform oder dem individuellen Wissen einzelner Mitarbeiter abhängen, was zu inkonsistenten Entscheidungen und Fehlern führen könnte; insbesondere beim Ausscheiden eines langjährigen Administrators könnte wertvolles prozessuales Wissen verloren gehen. Eine klare Dokumentation sichert die Verbindlichkeit und Wiederholbarkeit und dient als unverzichtbare Grundlage für die Einarbeitung neuer Kollegen, für die Durchführung von Audits und zur einheitlichen Anwendung der Regeln in der gesamten Institution. Die Dokumentation kann in einem eigenständigen Dokument als Richtlinie erfolgen, aber auch als Abschnitt in einem bereits bestehenden Dokument oder über die digital strukturierte Erfassung von Maßnahmen zur Umsetzung der Anforderungen, etwa über eine Software zum Management der Informationssicherheit. Sinnvoll ist es, Ort und Struktur der Dokumentation an der jeweiligen Zielgruppe, d.h. den für das Management und die Umsetzung verantwortlichen Personen oder Rollen, auszurichten. | R8: IT-Betriebskonzept | S8: die Verfahren und Regelungen | T8: G 0.18 – Fehlplanung oder fehlende Anpassung; G 0.37 – Abstreiten von Handlungen; G 0.29 – Verstoß gegen Gesetze oder Regelungen | U8: 0 | V8: 2 | W8: 2 | X8: 1 | Y8: 1
A9: ARCH.1.1 | B9: Verfahren und Regelungen | C9: ARCH.1.1.2 | D9: Basis-Anforderungen | E9: Architektur MUSS die mit den Verfahren und Regelungen verbundenen Aufgaben zuständigen Personen oder Rollen zuweisen. | H9: unbearbeitet | N9: ISMS.1.A6-UA.7; OPS.1.1.1.A1-UA.1; OPS.1.1.1.A1-UA.2; OPS.1.1.1.A19-UA.3; ORP.1.A1-UA.1; ORP.1.A2-UA.1; ORP.1.A4-UA.1 | O9: intersects-with; equivalent-to; intersects-with; subset-of; intersects-with; intersects-with; intersects-with | P9: Die Zuweisung von Aufgaben bezeichnet die eindeutige und verbindliche Übertragung von konkreten Tätigkeiten und Verantwortlichkeiten des Änderungsprozesses, wie etwa die Risikobewertung, die technische Umsetzung oder die finale Freigabe, an definierte Stellen in der Institution. Der Sinn dieser Vorschrift ist es, die Verantwortlichkeit ("Accountability") für jeden einzelnen Schritt im Prozess klarzustellen. Ohne eine solche Zuweisung könnten kritische Prüfungen unterbleiben, weil sich niemand explizit zuständig fühlt, was wiederum die Wahrscheinlichkeit fehlgeschlagener Änderungen erhöht. Eine klare Regelung kann sicherstellen, dass keine Aufgaben übersehen werden und jede Tätigkeit von einer dafür qualifizierten und befugten Stelle ausgeführt wird, was die Prozesssicherheit signifikant erhöht. Eine bewährte Methode zur Umsetzung ist die Erstellung einer RACI-Matrix (Responsible, Accountable, Consulted, Informed), die tabellarisch für jeden Prozessschritt darstellt, wer für die Durchführung verantwortlich ist, wer die Gesamtverantwortung trägt, wer zu konsultieren und wer zu informieren ist. Diese Zuständigkeiten können auch direkt in einem Workflow- oder Ticketsystem abgebildet werden, sodass Aufgaben, wie beispielsweise Genehmigungsschritte, automatisch an die richtige Gruppe oder Person weitergeleitet werden. Sinnvoll ist es, die Zuweisung anhand von Rollen (z. B. "Anwendungsverantwortlicher", "Netzwerkadministrator", "Change Manager") vorzunehmen, statt an konkrete Personen. Dieser Ansatz stellt sicher, dass die Prozesse auch bei Personalwechseln stabil weiterlaufen, da die Zuständigkeit an die Funktion und nicht an das Individuum gebunden ist. | R9: Geschäftsverteilungsplan | S9: die mit den Verfahren und Regelungen verbundenen Aufgaben | T9: G 0.18 – Fehlplanung oder fehlende Anpassung; G 0.31 – Fehlerhafte Nutzung oder Administration von Geräten und Systemen | U9: 0 | V9: 1 | W9: 1 | X9: 1 | Y9: 0
A10: ARCH.1.1 | B10: Verfahren und Regelungen | C10: ARCH.1.1.3 | D10: Basis-Anforderungen | E10: Architektur MUSS die zuständigen Personen oder Rollen über die Verfahren und Regelungen informieren. | H10: unbearbeitet | N10: ISMS.1.A8-UA.6; NET.1.2.A11-UA.2; NET.3.2.A1-UA.3; ORP.1.A1-UA.4; ORP.2.A1-UA.2 | O10: subset-of; equivalent-to; subset-of; equivalent-to; equivalent-to | P10: Wenn die Zuständigen die etablierten Verfahren nicht kennen, besteht die Gefahr, dass diese – sei es aus Unwissenheit oder Bequemlichkeit – umgangen werden, was die Schutzwirkung des gesamten Managementsystems untergräbt. So könnte ein neuer Systemadministrator eine weitreichende Konfigurationsänderung vornehmen, ohne den vorgeschriebenen Genehmigungsprozess zu durchlaufen, was zu einem unbemerkten Sicherheitsrisiko führen könnte. Eine gezielte Information kann hingegen die Akzeptanz der Regelungen fördern und sicherstellen, dass alle Beteiligten ihre Rolle im Prozess verstehen und die Abläufe korrekt anwenden. Zur Umsetzung ist es sinnvoll, die Dokumentation im Rahmen eines Onboarding-Prozesses bekanntzugeben und bei allen Änderungen eine automatische Benachrichtigung aller zuständigen Personen oder Rollen anzustoßen. | R10: IT-Betriebskonzept | S10: die zuständigen Personen oder Rollen über die Verfahren und Regelungen | T10: G 0.18 – Fehlplanung oder fehlende Anpassung; G 0.29 – Verstoß gegen Gesetze oder Regelungen | U10: 0 | V10: 1 | W10: 1 | X10: 1 | Y10: 0
A11: ARCH.1.2 | B11: Regelmäßige Überprüfung | D11: Basis-Anforderungen | E11: Gesamt: | H11: =IF(OR(COUNTBLANK($H$12:$H$12)>0,COUNTIF($H$12:$H$12,"unbearbeitet")=COUNTA($H$12:$H$12)),"Bitte Teilanforderungen ausfüllen",IF(COUNTIF($H$12:$H$12,"zu klären")>0,"zu klären",IF(COUNTIF($H$12:$H$12,"entbehrlich")=COUNTA($H$12:$H$12),"entbehrlich",IF(COUNTIF($H$12:$H$12,"verwiesen")=COUNTA($H$12:$H$12),"verwiesen",IF(COUNTIF($H$12:$H$12,"nein")+COUNTIF($H$12:$H$12,"entbehrlich")=COUNTA($H$12:$H$12),"nein",IF(COUNTIF($H$12:$H$12,"ja")+COUNTIF($H$12:$H$12,"entbehrlich")+COUNTIF($H$12:$H$12,"verwiesen")=COUNTA($H$12:$H$12),"ja","teilweise")))))) -> Bitte Teilanforderungen ausfüllen | N11: INF.11.A4-UA.4; INF.13.A4-UA.4; ISMS.1.A11-UA.2; ISMS.1.A7-UA.3; NET.2.2.A1-UA.7; NET.3.2.A1-UA.5; ORP.1.A1-UA.3 | O11: intersects-with; intersects-with; intersects-with; intersects-with; subset-of; subset-of; superset-of | P11: Eine geplante Überprüfung der etablierten Verfahren und Regelungen dient dazu festzustellen, ob diese noch wirksam, effizient und an die aktuellen Gegebenheiten angepasst sind. Eine anlassbezogene Überprüfung wird durch spezifische Ereignisse ausgelöst, wie etwa einen schwerwiegenden Sicherheitsvorfall, eine strategische Neuausrichtung der IT oder neue gesetzliche Anforderungen. Der Zweck dieser Anforderung ist es, die kontinuierliche Verbesserung und Anpassungsfähigkeit des Prozesses sicherzustellen, da veraltete Regelungen neuen technologischen Entwicklungen oder Bedrohungen nicht mehr gerecht werden könnten; ein vor Jahren für monolithische Anwendungen konzipierter Prozess ist beispielsweise für agile Entwicklungsmethoden oder Microservice-Architekturen ungeeignet. Die regelmäßige Überprüfung kann die Effektivität des Sicherheitsmanagements langfristig aufrechterhalten und die Resilienz der Institution stärken. | R11: Übungs- und Prüfplan | S11: die Verfahren und Regelungen | T11: G 0.18 – Fehlplanung oder fehlende Anpassung; G 0.29 – Verstoß gegen Gesetze oder Regelungen; G 0.31 – Fehlerhafte Nutzung oder Administration von Geräten und Systemen | U11: 0 | V11: 1 | W11: 1 | X11: 1 | Y11: 0
A12: ARCH.1.2 | B12: Regelmäßige Überprüfung | C12: ARCH.1.2 | D12: Basis-Anforderungen | E12: Architektur MUSS die Verfahren und Regelungen regelmäßig und anlassbezogen auf Aktualität überprüfen. | H12: unbearbeitet | N12: INF.11.A4-UA.4; INF.13.A4-UA.4; ISMS.1.A11-UA.2; ISMS.1.A7-UA.3; NET.2.2.A1-UA.7; NET.3.2.A1-UA.5; ORP.1.A1-UA.3 | O12: intersects-with; intersects-with; intersects-with; intersects-with; subset-of; subset-of; superset-of | P12: Eine geplante Überprüfung der etablierten Verfahren und Regelungen dient dazu festzustellen, ob diese noch wirksam, effizient und an die aktuellen Gegebenheiten angepasst sind. Eine anlassbezogene Überprüfung wird durch spezifische Ereignisse ausgelöst, wie etwa einen schwerwiegenden Sicherheitsvorfall, eine strategische Neuausrichtung der IT oder neue gesetzliche Anforderungen. Der Zweck dieser Anforderung ist es, die kontinuierliche Verbesserung und Anpassungsfähigkeit des Prozesses sicherzustellen, da veraltete Regelungen neuen technologischen Entwicklungen oder Bedrohungen nicht mehr gerecht werden könnten; ein vor Jahren für monolithische Anwendungen konzipierter Prozess ist beispielsweise für agile Entwicklungsmethoden oder Microservice-Architekturen ungeeignet. Die regelmäßige Überprüfung kann die Effektivität des Sicherheitsmanagements langfristig aufrechterhalten und die Resilienz der Institution stärken. | R12: Übungs- und Prüfplan | S12: die Verfahren und Regelungen | T12: G 0.18 – Fehlplanung oder fehlende Anpassung; G 0.29 – Verstoß gegen Gesetze oder Regelungen; G 0.31 – Fehlerhafte Nutzung oder Administration von Geräten und Systemen | U12: 0 | V12: 1 | W12: 1 | X12: 1 | Y12: 0
A13: ARCH.2.1 | B13: Netzsegmente | D13: Standard-Anforderungen | E13: Gesamt: | H13: =IF(OR(COUNTBLANK($H$14:$H$14)>0,COUNTIF($H$14:$H$14,"unbearbeitet")=COUNTA($H$14:$H$14)),"Bitte Teilanforderungen ausfüllen",IF(COUNTIF($H$14:$H$14,"zu klären")>0,"zu klären",IF(COUNTIF($H$14:$H$14,"entbehrlich")=COUNTA($H$14:$H$14),"entbehrlich",IF(COUNTIF($H$14:$H$14,"verwiesen")=COUNTA($H$14:$H$14),"verwiesen",IF(COUNTIF($H$14:$H$14,"nein")+COUNTIF($H$14:$H$14,"entbehrlich")=COUNTA($H$14:$H$14),"nein",IF(COUNTIF($H$14:$H$14,"ja")+COUNTIF($H$14:$H$14,"entbehrlich")+COUNTIF($H$14:$H$14,"verwiesen")=COUNTA($H$14:$H$14),"ja","teilweise")))))) -> Bitte Teilanforderungen ausfüllen | M13: Vertraulichkeit, Integrität | N13: APP.4.4.A7-UA.1; INF.14.A13-UA.1; INF.14.A6-UA.1; NET.1.1.A19-UA.1; NET.1.1.A22-UA.1; NET.1.1.A23-UA.1; NET.1.1.A23-UA.3; NET.1.1.A31-UA.1; NET.1.1.A33-UA.1; NET.1.1.A34-UA.1; NET.1.1.A4-UA.1; NET.1.1.A5-UA.1; NET.1.1.A5-UA.4; NET.1.1.A6-UA.1; NET.1.2.A33-UA.1; OPS.1.1.1.A15-UA.3; OPS.1.1.2.A16-UA.2; SYS.1.5.A9-UA.3; SYS.1.5.A9-UA.4; SYS.1.5.A9-UA.5; SYS.2.5.A2-UA.3; SYS.2.6.A4-UA.2; SYS.2.6.A4-UA.3 | O13: subset-of; subset-of; subset-of; subset-of; intersects-with; equivalent-to; subset-of; subset-of; subset-of; subset-of; superset-of; subset-of; subset-of; subset-of; superset-of; subset-of; subset-of; equivalent-to; subset-of; subset-of; subset-of; subset-of; subset-of | P13: Die Aufteilung in Netzsegmente (auch Netzdomänen oder Subnetze genannt) ermöglicht es, verschiedene Zonen mit unterschiedlichen Schutzanforderungen – z. B. Büro-IT, Produktionsnetz, Managementnetz – getrennt zu betrachten und gezielt zu schützen. Relevant sind dabei (falls vorhanden) auch WLANs/SSIDs, IoT-Geräte wie vernetzte Kühlschränke, Hausleittechnik, operative Technologien, Industrielle Steuerungssysteme oder Netze zum Zugriff auf Speichersysteme (Storage Area Network, SAN). Die Anforderung gilt auch, wenn die Systeme nur noch als VMs oder Container existieren. Die Segmentierung kann hier in die virtuelle Netzwerk‑Ebene verlagert werden, sodass die Segmentierung weder vom Hypervisor noch von den Workloads umgangen wird. Die Einteilung in Segmente kann anhand einer Klassifizierung von Netzen erfolgen (z.B. nach Schutzbedarf der dort verarbeiteten Daten oder nach Risikoklassen angeschlossener Systeme) erfolgen. Beispiele hierfür sind Internet-Domäne, Endgeräte-Domäne, Domäne für zentrale Serverdienste, Domäne für Systeme hoher Vertraulichkeit. Alternativ können auch organisatorische Domänen verwendet werden, z. B. Personalwesen, Marketing, Finanzverwaltung, Innere Verwaltung. Die Filterkriterien können sich nach den Sicherheitsanforderungen der jeweiligen Netze im Einzelnen oder nach einer vorgenommenen Klassifikation der Netze richten. Hierzu gehören insbesondere die Anforderungen zur Authentifizierung und Autorisierung von Assets. | Q13: Netze | R13: Netzplan | S13: eine Unterteilung des internen Netzes in Netzsegmente | T13: G 0.23 – Unbefugtes Eindringen in IT-Systeme; G 0.19 – Offenlegung schützenswerter Informationen; G 0.30 – Unberechtigte Nutzung oder Administration von Geräten und Systemen; G 0.47 – Schädliche Seiteneffekte IT-gestützter Angriffe | U13: 2 | V13: 2 | W13: 2 | X13: 1 | Y13: 1
A14: ARCH.2.1 | B14: Netzsegmente | C14: ARCH.2.1 | D14: Standard-Anforderungen | E14: Architektur für Netze SOLLTE eine Unterteilung des internen Netzes in Netzsegmente unter Berücksichtigung der Anforderungen der Institution und des Schutzbedarfes verankern. | H14: unbearbeitet | M14: Vertraulichkeit, Integrität | N14: APP.4.4.A7-UA.1; INF.14.A13-UA.1; INF.14.A6-UA.1; NET.1.1.A19-UA.1; NET.1.1.A22-UA.1; NET.1.1.A23-UA.1; NET.1.1.A23-UA.3; NET.1.1.A31-UA.1; NET.1.1.A33-UA.1; NET.1.1.A34-UA.1; NET.1.1.A4-UA.1; NET.1.1.A5-UA.1; NET.1.1.A5-UA.4; NET.1.1.A6-UA.1; NET.1.2.A33-UA.1; OPS.1.1.1.A15-UA.3; OPS.1.1.2.A16-UA.2; SYS.1.5.A9-UA.3; SYS.1.5.A9-UA.4; SYS.1.5.A9-UA.5; SYS.2.5.A2-UA.3; SYS.2.6.A4-UA.2; SYS.2.6.A4-UA.3 | O14: subset-of; subset-of; subset-of; subset-of; intersects-with; equivalent-to; subset-of; subset-of; subset-of; subset-of; superset-of; subset-of; subset-of; subset-of; superset-of; subset-of; subset-of; equivalent-to; subset-of; subset-of; subset-of; subset-of; subset-of | P14: Die Aufteilung in Netzsegmente (auch Netzdomänen oder Subnetze genannt) ermöglicht es, verschiedene Zonen mit unterschiedlichen Schutzanforderungen – z. B. Büro-IT, Produktionsnetz, Managementnetz – getrennt zu betrachten und gezielt zu schützen. Relevant sind dabei (falls vorhanden) auch WLANs/SSIDs, IoT-Geräte wie vernetzte Kühlschränke, Hausleittechnik, operative Technologien, Industrielle Steuerungssysteme oder Netze zum Zugriff auf Speichersysteme (Storage Area Network, SAN). Die Anforderung gilt auch, wenn die Systeme nur noch als VMs oder Container existieren. Die Segmentierung kann hier in die virtuelle Netzwerk‑Ebene verlagert werden, sodass die Segmentierung weder vom Hypervisor noch von den Workloads umgangen wird. Die Einteilung in Segmente kann anhand einer Klassifizierung von Netzen erfolgen (z.B. nach Schutzbedarf der dort verarbeiteten Daten oder nach Risikoklassen angeschlossener Systeme) erfolgen. Beispiele hierfür sind Internet-Domäne, Endgeräte-Domäne, Domäne für zentrale Serverdienste, Domäne für Systeme hoher Vertraulichkeit. Alternativ können auch organisatorische Domänen verwendet werden, z. B. Personalwesen, Marketing, Finanzverwaltung, Innere Verwaltung. Die Filterkriterien können sich nach den Sicherheitsanforderungen der jeweiligen Netze im Einzelnen oder nach einer vorgenommenen Klassifikation der Netze richten. Hierzu gehören insbesondere die Anforderungen zur Authentifizierung und Autorisierung von Assets. | Q14: Netze | R14: Netzplan | S14: eine Unterteilung des internen Netzes in Netzsegmente | T14: G 0.23 – Unbefugtes Eindringen in IT-Systeme; G 0.19 – Offenlegung schützenswerter Informationen; G 0.30 – Unberechtigte Nutzung oder Administration von Geräten und Systemen; G 0.47 – Schädliche Seiteneffekte IT-gestützter Angriffe | U14: 2 | V14: 2 | W14: 2 | X14: 1 | Y14: 1
A15: ARCH.2.2 | B15: Einschränkung von Verbindungen zwischen Segmenten | D15: Standard-Anforderungen | E15: Gesamt: | H15: =IF(OR(COUNTBLANK($H$16:$H$28)>0,COUNTIF($H$16:$H$28,"unbearbeitet")=COUNTA($H$16:$H$28)),"Bitte Teilanforderungen ausfüllen",IF(COUNTIF($H$16:$H$28,"zu klären")>0,"zu klären",IF(COUNTIF($H$16:$H$28,"entbehrlich")=COUNTA($H$16:$H$28),"entbehrlich",IF(COUNTIF($H$16:$H$28,"verwiesen")=COUNTA($H$16:$H$28),"verwiesen",IF(COUNTIF($H$16:$H$28,"nein")+COUNTIF($H$16:$H$28,"entbehrlich")=COUNTA($H$16:$H$28),"nein",IF(COUNTIF($H$16:$H$28,"ja")+COUNTIF($H$16:$H$28,"entbehrlich")+COUNTIF($H$16:$H$28,"verwiesen")=COUNTA($H$16:$H$28),"ja","teilweise")))))) -> Bitte Teilanforderungen ausfüllen | N15: APP.4.4.A18-UA.3; INF.10.A6-UA.1; INF.10.A6-UA.3; INF.10.A6-UA.6; INF.14.A11-UA.3; INF.14.A11-UA.5; INF.14.A13-UA.2; NET.1.1.A10-UA.2; NET.1.1.A22-UA.6; NET.1.1.A23-UA.2; NET.1.1.A24-UA.1; NET.1.1.A4-UA.4; NET.1.1.A5-UA.4; NET.1.2.A11-UA.8; NET.3.2.A2-UA.3; NET.3.4.A14-UA.2; NET.3.4.A9-UA.2; OPS.1.1.7.A17-UA.1; SYS.1.5.A15-UA.2; SYS.1.5.A9-UA.4; SYS.4.1.A11-UA.2; SYS.4.4.A5-UA.4 | O15: subset-of; subset-of; subset-of; subset-of; subset-of; subset-of; subset-of; subset-of; superset-of; intersects-with; subset-of; intersects-with; subset-of; superset-of; equivalent-to; intersects-with; subset-of; intersects-with; subset-of; equivalent-to; intersects-with; subset-of | P15: Dient dem Ziel, die Angriffsfläche innerhalb interner und externer Netze zu reduzieren und die Ausbreitung potenzieller Schadsoftware oder unberechtigter Zugriffe einzudämmen. Ohne solche Begrenzungen könnte ein einzelner kompromittierter Bereich direkten Zugriff auf weitere sensible Segmente erhalten und dadurch Geschäftsprozesse massiv beeinträchtigen. Beispielsweise benötigt ein Endgerät Verbindungen zu internen Servern und Druckern, während Gäste lediglich auf den Internetanschluss Zugriff benötigen. Im Blick auf weitreichende Sicherheitsvorfälle ist hier insbesondere die Trennung interner Netzsegmente vom Internet zu beachten. Diese Regeln können auf Kriterien wie Gerätetyp (z. B. Laptop, IoT-Gerät), Benutzerrolle (z. B. Administrator, Gast), physischem Anschlussort oder Uhrzeit basieren. Eine klare Trennung von Benutzergruppen über VLANs oder dynamische ACLs erhöht die Sicherheit und Transparenz. Für die Einführung in eine bestehende Umgebung kann ein gestuftes Vorgehen gewählt werden: (1) Zunächst wird ein Überwachungsmodus ("Audit-Only") aktiviert, der protokolliert, welche Zugriffe durch eine strengere Richtlinie verweigert würden, ohne sie tatsächlich zu blockieren. (2) Anschließend werden diese Protokolle analysiert, um legitime, für den Geschäftsbetrieb notwendige Zugriffe zu identifizieren und diese gezielt in die jeweiligen Rollen und Berechtigungsgruppen aufzunehmen. (3) Erst wenn keine legitimen Zugriffe mehr in den Protokollen als "verweigert" auftauchen, wird die Richtlinie scharf geschaltet und blockiert aktiv alle nicht explizit erlaubten Zugriffe. | Q15: Netze | R15: Netzplan | S15: Verbindungen zwischen Netzsegmenten | T15: G 0.23 – Unbefugtes Eindringen in IT-Systeme; G 0.47 – Schädliche Seiteneffekte IT-gestützter Angriffe; G 0.40 – Verhinderung von Diensten (Denial of Service) | U15: 2 | V15: 1 | W15: 1 | X15: 1 | Y15: 0
A16: ARCH.2.2 | B16: Einschränkung von Verbindungen zwischen Segmenten | C16: ARCH.2.2 | D16: Standard-Anforderungen | E16: Architektur für Netze SOLLTE Verbindungen zwischen Netzsegmenten anhand von Kriterien einschränken. | H16: unbearbeitet | N16: APP.4.4.A18-UA.3; INF.10.A6-UA.1; INF.10.A6-UA.3; INF.10.A6-UA.6; INF.14.A11-UA.3; INF.14.A11-UA.5; INF.14.A13-UA.2; NET.1.1.A10-UA.2; NET.1.1.A22-UA.6; NET.1.1.A23-UA.2; NET.1.1.A24-UA.1; NET.1.1.A4-UA.4; NET.1.1.A5-UA.4; NET.1.2.A11-UA.8; NET.3.2.A2-UA.3; NET.3.4.A14-UA.2; NET.3.4.A9-UA.2; OPS.1.1.7.A17-UA.1; SYS.1.5.A15-UA.2; SYS.1.5.A9-UA.4; SYS.4.1.A11-UA.2; SYS.4.4.A5-UA.4 | O16: subset-of; subset-of; subset-of; subset-of; subset-of; subset-of; subset-of; subset-of; superset-of; intersects-with; subset-of; intersects-with; subset-of; superset-of; equivalent-to; intersects-with; subset-of; intersects-with; subset-of; equivalent-to; intersects-with; subset-of | P16: Dient dem Ziel, die Angriffsfläche innerhalb interner und externer Netze zu reduzieren und die Ausbreitung potenzieller Schadsoftware oder unberechtigter Zugriffe einzudämmen. Ohne solche Begrenzungen könnte ein einzelner kompromittierter Bereich direkten Zugriff auf weitere sensible Segmente erhalten und dadurch Geschäftsprozesse massiv beeinträchtigen. Beispielsweise benötigt ein Endgerät Verbindungen zu internen Servern und Druckern, während Gäste lediglich auf den Internetanschluss Zugriff benötigen. Im Blick auf weitreichende Sicherheitsvorfälle ist hier insbesondere die Trennung interner Netzsegmente vom Internet zu beachten. Diese Regeln können auf Kriterien wie Gerätetyp (z. B. Laptop, IoT-Gerät), Benutzerrolle (z. B. Administrator, Gast), physischem Anschlussort oder Uhrzeit basieren. Eine klare Trennung von Benutzergruppen über VLANs oder dynamische ACLs erhöht die Sicherheit und Transparenz. Für die Einführung in eine bestehende Umgebung kann ein gestuftes Vorgehen gewählt werden: (1) Zunächst wird ein Überwachungsmodus ("Audit-Only") aktiviert, der protokolliert, welche Zugriffe durch eine strengere Richtlinie verweigert würden, ohne sie tatsächlich zu blockieren. (2) Anschließend werden diese Protokolle analysiert, um legitime, für den Geschäftsbetrieb notwendige Zugriffe zu identifizieren und diese gezielt in die jeweiligen Rollen und Berechtigungsgruppen aufzunehmen. (3) Erst wenn keine legitimen Zugriffe mehr in den Protokollen als "verweigert" auftauchen, wird die Richtlinie scharf geschaltet und blockiert aktiv alle nicht explizit erlaubten Zugriffe. | Q16: Netze | R16: Netzplan | S16: Verbindungen zwischen Netzsegmenten | T16: G 0.23 – Unbefugtes Eindringen in IT-Systeme; G 0.47 – Schädliche Seiteneffekte IT-gestützter Angriffe; G 0.40 – Verhinderung von Diensten (Denial of Service) | U16: 2 | V16: 1 | W16: 1 | X16: 1 | Y16: 0
A17: ARCH.2.2 | B17: Einschränkung von Verbindungen zwischen Segmenten | C17: ARCH.2.2.1 | D17: Standard-Anforderungen | E17: Architektur für Netze SOLLTE Verbindungen über externe Netzanschlüsse einschränken. | H17: unbearbeitet | M17: Vertraulichkeit, Verfügbarkeit | N17: CON.7.A7-UA.1; IND.2.1.A16-UA.1; INF.10.A6-UA.1; INF.10.A6-UA.3; INF.10.A6-UA.4; INF.10.A6-UA.5; INF.10.A6-UA.6; INF.14.A11-UA.1; INF.14.A11-UA.3; INF.14.A28-UA.2; NET.1.1.A18-UA.1; NET.3.1.A18-UA.2; NET.3.2.A19-UA.1; NET.3.2.A2-UA.3; NET.3.3.A11-UA.1; NET.3.4.A14-UA.2; NET.3.4.A9-UA.2; NET.4.2.A4-UA.2; OPS.1.2.5.A8-UA.4; SYS.1.5.A9-UA.4; SYS.3.2.1.A28-UA.2; SYS.4.1.A11-UA.2; SYS.4.4.A5-UA.4 | O17: subset-of; subset-of; subset-of; subset-of; intersects-with; subset-of; subset-of; subset-of; subset-of; subset-of; superset-of; subset-of; subset-of; subset-of; subset-of; superset-of; subset-of; subset-of; subset-of; superset-of; subset-of; intersects-with; subset-of | P17: Dient dazu, die Angriffsfläche zu reduzieren, unerwünschte Ein- und Ausleitungen zu begrenzen und das Risiko von Datenabflüssen zu minimieren. Für mobile Systeme kann dies z. B. über das Erzwingen einer VPN-Verbindung ins gefilterte Netz der Institution oder über die Verwendung eines direkten Internetzugangs erfolgen, welcher über einen Direct-Internet-Access Agenten abgesichert ist. | Q17: Netze | R17: Netzplan | S17: Verbindungen über externe Netzanschlüsse | T17: G 0.14 – Ausspähen von Informationen (Spionage); G 0.23 – Unbefugtes Eindringen in IT-Systeme; G 0.39 – Schadprogramme; G 0.40 – Verhinderung von Diensten (Denial of Service); G 0.9 – Ausfall oder Störung von Kommunikationsnetzen; G 0.47 – Schädliche Seiteneffekte IT-gestützter Angriffe | U17: 2 | V17: 2 | W17: 1 | X17: 2 | Y17: 0
A18: ARCH.2.2 | B18: Einschränkung von Verbindungen zwischen Segmenten | C18: ARCH.2.2.2 | D18: Standard-Anforderungen | E18: Architektur für Netze SOLLTE Verbindungen zwischen Gastnetz und internem Netz einschränken. | H18: unbearbeitet | N18: INF.10.A1-UA.4; INF.10.A6-UA.1; INF.10.A6-UA.3; INF.10.A6-UA.4; INF.10.A6-UA.6; NET.1.1.A22-UA.6; NET.1.1.A5-UA.4; NET.3.2.A2-UA.2; NET.3.4.A14-UA.2; NET.3.4.A9-UA.2 | O18: subset-of; equivalent-to; equal-to; intersects-with; subset-of; superset-of; superset-of; intersects-with; intersects-with; intersects-with | P18: Wenn Gäste der Institution sich mit dem internen Netz verbinden, könnten Schadprogramme in das Netz gelangen oder unbeabsichtigte Datenflüsse über die Verbindung fließen. Daher ist es sinnvoll, einen vom übrigen Netz getrennten Gastzugang einzurichten, z.B. in Besprechungs-, Veranstaltungs- und Schulungsräumen. Wenn die Einschränkungen von Gastnetzen lockerer sind als die interner Netze am gleichen Standort, so zeigt die Erfahrung, dass auch interne Mitarbeitende gerne auf Gastnetze zurückgreifen. Dadurch könnte es zur Umgehung der internen Schutzmaßnahmen kommen. Daher ist es empfehlenswert, für das Gastnetz gleiche oder strengere Einschränkungen zu wählen oder die Nutzung des Gastnetzes durch Mitarbeitende technisch oder organisatorisch zu beschränken. | Q18: Netze | R18: Netzplan | S18: Verbindungen zwischen Gastnetz und internem Netz | T18: G 0.23 – Unbefugtes Eindringen in IT-Systeme | U18: 2 | V18: 1 | W18: 1 | X18: 0 | Y18: 0
A19: ARCH.2.2 | B19: Einschränkung von Verbindungen zwischen Segmenten | C19: ARCH.2.2.3 | D19: Standard-Anforderungen | E19: Architektur für Netze SOLLTE Verbindungen zwischen Hostsystemen und Clients einschränken. | H19: unbearbeitet | N19: NET.1.1.A19-UA.1; NET.1.1.A5-UA.1; NET.1.1.A5-UA.2; NET.1.1.A5-UA.3; NET.3.4.A9-UA.2; SYS.1.5.A9-UA.4; SYS.2.1.A23-UA.1; SYS.2.5.A2-UA.3 | O19: equivalent-to; equivalent-to; equivalent-to; intersects-with; subset-of; equivalent-to; intersects-with; equivalent-to | P19: Die Anforderung gilt auch, wenn die IT-Systeme nur noch als VMs oder Container existieren. Die Segmentierung kann hier in die virtuelle Netzwerk‑Ebene verlagert werden, sodass die Segmentierung weder vom Hypervisor noch von den Workloads umgangen wird. Die Anforderung kann auch physisch durch dedizierte Infrastruktur für VDI/Client‑VMs umgesetzt werden. Um die klare Trennung sicherzustellen, wird empfohlen kein Bridging zwischen Port‑Groups sowie auf dem virtuellen Switch keinen promiscuous Mode zu verwenden. | Q19: Netze | R19: Netzplan | S19: Verbindungen zwischen Hostsystemen und Clients | T19: G 0.23 – Unbefugtes Eindringen in IT-Systeme; G 0.9 – Ausfall oder Störung von Kommunikationsnetzen; G 0.40 – Verhinderung von Diensten (Denial of Service) | U19: 3 | V19: 1 | W19: 1 | X19: 1 | Y19: 0
A20: ARCH.2.2 | B20: Einschränkung von Verbindungen zwischen Segmenten | C20: ARCH.2.2.4 | D20: Anforderungen bei erhöhtem Schutzbedarf | E20: Architektur für Netze KANN Verbindungen zwischen Daten- und VoIP-Systemen einschränken. | H20: unbearbeitet | M20: Verfügbarkeit | N20: INF.10.A6-UA.6; NET.4.2.A1-UA.5; NET.4.2.A16-UA.1; NET.4.2.A16-UA.2; NET.4.2.A16-UA.3; NET.4.2.A4-UA.2; NET.4.2.A4-UA.3 | O20: intersects-with; intersects-with; equal-to; intersects-with; equivalent-to; intersects-with; subset-of | P20: Werden sowohl Telefonie als auch andere Daten über dasselbe Netz geführt, so könnte dies bei einem Netzausfall dazu führen, dass keine Kommunikation mehr möglich ist, auch nicht zur Meldung oder Behebung der Störung. Die Wahrscheinlichkeit kann durch getrennt betriebene Voice- und Datennetze verringert werden. Für weitere Details siehe „Kompendium für organisationsinterne Telekommunikationssysteme mit erhöhtem Schutzbedarf". | Q20: Netze | R20: Netzplan | S20: Verbindungen zwischen Daten- und VoIP-Systemen | T20: G 0.23 – Unbefugtes Eindringen in IT-Systeme; G 0.9 – Ausfall oder Störung von Kommunikationsnetzen; G 0.40 – Verhinderung von Diensten (Denial of Service) | U20: 5 | V20: 1 | W20: 1 | X20: 2 | Y20: 0
A21: ARCH.2.2 | B21: Einschränkung von Verbindungen zwischen Segmenten | C21: ARCH.2.2.5 | D21: Standard-Anforderungen | E21: Architektur für Netze SOLLTE Verbindungen zwischen OT-Systemen und anderen IT-Systemen einschränken. | H21: unbearbeitet | M21: Verfügbarkeit | N21: IND.1.A8-UA.1; IND.2.4.A1-UA.5; IND.3.2.A12-UA.1; IND.3.2.A5-UA.1; IND.3.2.A7-UA.1; IND.3.2.A7-UA.2; IND.3.2.A7-UA.4; IND.3.2.A8-UA.5; INF.14.A18-UA.1 | O21: subset-of; subset-of; intersects-with; intersects-with; subset-of; subset-of; subset-of; intersects-with; intersects-with | P21: IT- und OT-Systeme haben typischerweise sehr unterschiedliche Risikoprofile (IT: Schnelllebig, viele Cybersicherheitsmechanismen, OT: Stabilität, weniger Cybersicherheitsmechanismen, beispielsweise industrielle Steuerungssysteme und Gebäudeautomationstechnik). Insbesondere der Zugriff auf OT-Funktionen (z. B. Öffnung zentraler Schließanlage) ist mit erhöhtem Risiko verbunden und könnte auch versehentlich z.B. durch Portscanner ausgelöst werden. Stattdessen ist es empfehlenswert, den Zugriff zu solchen Netzen nur über dafür vorgesehene Quellen zu ermöglichen (z. B. Sprungserver, bestimmte auslösende OT-Systeme). | Q21: Netze | R21: Netzplan | S21: Verbindungen zwischen OT-Systemen und anderen IT-Systemen | T21: G 0.23 – Unbefugtes Eindringen in IT-Systeme; G 0.9 – Ausfall oder Störung von Kommunikationsnetzen; G 0.40 – Verhinderung von Diensten (Denial of Service) | U21: 3 | V21: 1 | W21: 1 | X21: 2 | Y21: 0
A22: ARCH.2.2 | B22: Einschränkung von Verbindungen zwischen Segmenten | C22: ARCH.2.2.6 | D22: Standard-Anforderungen | E22: Architektur für Netze SOLLTE eine demilitarisierte Zone installieren. | H22: unbearbeitet | M22: Vertraulichkeit, Integrität | N22: APP.3.6.A16-UA.2; IND.1.A16-UA.2; NET.1.1.A10-UA.1; NET.1.1.A10-UA.2; NET.1.1.A10-UA.3; NET.1.1.A4-UA.1 | O22: subset-of; intersects-with; subset-of; subset-of; subset-of; equal-to | P22: Unter einer Demilitarisierten Zone versteht man in diesem Kontext ein logisch oder physisch getrenntes Teilnetz, in dem Systeme mit exponierten Diensten – wie Webserver, Mail-Gateways oder VPN-Endpunkte – betrieben werden. Systeme der Institution, die sowohl aus dem öffentlichen Netz als auch aus dem internen Netz erreichbar sind, werden in einer demilitarisierten Zone (DMZ) so betrieben, dass (1) der Netzverkehr zwischen dem System und dem öffentlichen Netz gefiltert wird und (2) der Netzverkehr zwischen dem System und anderen internen Netzen gefiltert wird. Eine DMZ kann sowohl durch dedizierte Hardware-Firewalls als auch durch virtuelle Netzwerksegmente umgesetzt werden. Ohne eine solche Trennung könnte ein kompromittierter Webserver direkt als Sprungbrett ins interne Netz dienen oder Schadsoftware könnte sich ungehindert auf sensible Systeme ausbreiten. Mit einer DMZ kann eine Institution hingegen erreichen, dass kompromittierte Systeme isoliert bleiben und sicherheitskritische interne Netze weiterhin geschützt sind. | Q22: Netze | R22: Netzplan | S22: eine demilitarisierte Zone | T22: G 0.23 – Unbefugtes Eindringen in IT-Systeme; G 0.47 – Schädliche Seiteneffekte IT-gestützter Angriffe | U22: 3 | V22: 2 | W22: 2 | X22: 1 | Y22: 0
A23: ARCH.2.2 | B23: Einschränkung von Verbindungen zwischen Segmenten | C23: ARCH.2.2.7 | D23: Standard-Anforderungen | E23: Architektur für Netze SOLLTE ein oder mehrere Management-Netze installieren. | H23: unbearbeitet | M23: Vertraulichkeit | N23: NET.1.1.A21-UA.5; NET.1.2.A28-UA.2; NET.1.2.A29-UA.1; NET.1.2.A33-UA.1; NET.3.1.A13-UA.1; NET.3.1.A4-UA.4; NET.3.1.A4-UA.5; NET.3.2.A18-UA.1; NET.3.2.A18-UA.3; OPS.1.1.2.A16-UA.2; SYS.1.5.A11-UA.1; SYS.1.5.A5-UA.1; SYS.1.5.A9-UA.3; SYS.1.6.A5-UA.1 | O23: equivalent-to; intersects-with; subset-of; subset-of; subset-of; subset-of; intersects-with; subset-of; intersects-with; equivalent-to; subset-of; intersects-with; superset-of; subset-of | P23: Ein Management-Netz ist ein physisch oder durch Netzfilter separiertes Netzsegment, das dediziert für die Überwachung, Verwaltung und Wartung von IT-Systemen bestimmt ist. Es ist von anderen Produktions- und Datennetzen getrennt, um den Zugriff auf kritische Verwaltungsfunktionen zu schützen und die Verfügbarkeit dieser Zugänge auch bei Problemen im restlichen Netz zu sichern. Dies gilt auch für virtualisierte Systeme. Im Kontext der Containerisierung empfiehlt es sich, administrative Zugänge auf Applikations-Container immer über die Container-Runtime erfolgen zu lassen. | Q23: Netze | R23: Netzplan | S23: ein oder mehrere Management-Netze | T23: G 0.30 – Unberechtigte Nutzung oder Administration von Geräten und Systemen; G 0.23 – Unbefugtes Eindringen in IT-Systeme; G 0.32 – Missbrauch von Berechtigungen; G 0.19 – Offenlegung schützenswerter Informationen | U23: 3 | V23: 2 | W23: 1 | X23: 1 | Y23: 1
A24: ARCH.2.2 | B24: Einschränkung von Verbindungen zwischen Segmenten | C24: ARCH.2.2.8 | D24: Standard-Anforderungen | E24: Architektur für Netze SOLLTE Verbindungen zwischen Testumgebungen und Betrieb einschränken. | H24: unbearbeitet | M24: Vertraulichkeit, Integrität | N24: CON.8.A7-UA.8; NET.3.4.A9-UA.2; OPS.1.1.3.A9-UA.3; OPS.1.1.6.A13-UA.1; OPS.1.1.6.A13-UA.2; SYS.1.5.A9-UA.4; SYS.1.7.A33-UA.1 | O24: subset-of; intersects-with; subset-of; subset-of; equal-to; superset-of; subset-of | P24: Entwicklungs-, Staging- und Testumgebungen haben oft geringere Sicherheitsvorkehrungen als Produktivsysteme. Eine saubere Trennung zwischen Test- und Produktivumgebung verhindert Übergriffe auf das Produktivsystem und vermeidet Ressourcenkonflikte. | Q24: Netze | R24: Netzplan | S24: Verbindungen zwischen Testumgebungen und Betrieb | T24: G 0.23 – Unbefugtes Eindringen in IT-Systeme; G 0.26 – Fehlfunktion von Geräten oder Systemen; G 0.20 – Informationen oder Produkte aus unzuverlässiger Quelle; G 0.28 – Software-Schwachstellen oder -Fehler | U24: 4 | V24: 2 | W24: 2 | X24: 1 | Y24: 1
A25: ARCH.2.2 | B25: Einschränkung von Verbindungen zwischen Segmenten | C25: ARCH.2.2.9 | D25: Standard-Anforderungen | E25: Architektur für Netze SOLLTE Verbindungen zwischen IPv4 und IPv6 einschränken. | H25: unbearbeitet | M25: Vertraulichkeit, Integrität | N25: NET.1.1.A20-UA.1; NET.3.2.A17-UA.1; NET.3.4.A9-UA.2 | O25: equivalent-to; subset-of; intersects-with | P25: IPv4 und IPv6 sind grundlegende Netzprotokolle, die unterschiedliche Protokollstacks und Sicherheitseigenschaften haben. Eine Trennung von IT-Systemen mit IPv4 und IPv6 erschwert es Angreifern, Schwachstellen der Protokolle auszunutzen oder zu kombinieren und verringert die Wahrscheinlichkeit von Fehlern durch Wechselwirkungen. | Q25: Netze | R25: Netzplan | S25: Verbindungen zwischen IPv4 und IPv6 | T25: G 0.23 – Unbefugtes Eindringen in IT-Systeme; G 0.18 – Fehlplanung oder fehlende Anpassung; G 0.39 – Schadprogramme | U25: 4 | V25: 2 | W25: 2 | X25: 1 | Y25: 0
A26: ARCH.2.2 | B26: Einschränkung von Verbindungen zwischen Segmenten | C26: ARCH.2.2.10 | D26: Standard-Anforderungen | E26: Architektur für Netze SOLLTE Verbindungen zwischen Druckern und anderen Systemen einschränken. | H26: unbearbeitet | N26: NET.3.4.A9-UA.2; SYS.1.5.A9-UA.4; SYS.4.1.A11-UA.1; SYS.4.1.A11-UA.3; SYS.4.1.A18-UA.3; SYS.4.1.A4-UA.1 | O26: intersects-with; superset-of; subset-of; subset-of; subset-of; intersects-with | P26: Drucker können Schwachstellen aufweisen, die Angreifer ausnutzen, z.B. veraltete Firmware oder ungesicherte Netzprotokolle. Durch die Segmentierung wird die Angriffsoberfläche reduziert und die Netzüberwachung erleichtert. Die Umsetzung kann physisch oder durch VLANs erfolgen. | Q26: Netze | R26: Netzplan | S26: Verbindungen zwischen Druckern und anderen Systemen | T26: G 0.30 – Unberechtigte Nutzung oder Administration von Geräten und Systemen; G 0.18 – Fehlplanung oder fehlende Anpassung; G 0.39 – Schadprogramme | U26: 4 | V26: 1 | W26: 1 | X26: 1 | Y26: 1
A27: ARCH.2.2 | B27: Einschränkung von Verbindungen zwischen Segmenten | C27: ARCH.2.2.11 | D27: Anforderungen bei erhöhtem Schutzbedarf | E27: Architektur für Netze KANN den physischen Zugang auf diese einschränken. | H27: unbearbeitet | N27: NET.1.1.A23-UA.4; NET.1.1.A31-UA.1; NET.1.1.A32-UA.1; NET.1.1.A4-UA.1; NET.1.2.A32-UA.1; OPS.1.1.7.A21-UA.1 | O27: intersects-with; subset-of; subset-of; superset-of; subset-of; subset-of | P27: Obwohl sich eine virtuelle Vernetzung immer größerer Beliebtheit erfreut, können Konfigurationsfehler oder Sicherheitslücken dabei leichter zu einer Umgehung der Netztrennung führen, als wenn die Netze bereits auf physischer Ebene voneinander getrennt werden. | Q27: Netze | R27: Netzplan | S27: den physischen Zugang auf diese | T27: G 0.18 – Fehlplanung oder fehlende Anpassung; G 0.29 – Verstoß gegen Gesetze oder Regelungen; G 0.23 – Unbefugtes Eindringen in IT-Systeme; G 0.9 – Ausfall oder Störung von Kommunikationsnetzen | U27: 5 | V27: 1 | W27: 1 | X27: 1 | Y27: 0
A28: ARCH.2.2 | B28: Einschränkung von Verbindungen zwischen Segmenten | C28: ARCH.2.2.12 | D28: Anforderungen bei erhöhtem Schutzbedarf | E28: Architektur KANN Sprungserver installieren. | H28: unbearbeitet | M28: Vertraulichkeit | N28: IND.3.2.A7-UA.4; NET.1.2.A21-UA.3; OPS.1.1.7.A26-UA.1; OPS.1.2.5.A25-UA.3 | O28: superset-of; intersects-with; equivalent-to; equivalent-to | P28: Ein Sprungserver (englisch „jump server“ oder „jump host“) ist ein speziell abgesicherter Server, der als einzig vorgesehener Einstiegspunkt in ein Verwaltungsnetz oder zu administrierten Systemen dient. Alle administrativen Sitzungen laufen über diesen zentralen Knotenpunkt, wodurch die Angriffsfläche reduziert und die Nachvollziehbarkeit erhöht wird. Ohne Sprungserver könnte ein Angreifer beispielsweise über kompromittierte Administrator-Notebooks unbemerkt direkt auf zentrale Systeme zugreifen und dort Manipulationen durchführen. Ein Sprungserver kann hingegen alle Management-Zugriffe zentral kanalisieren, sodass verdächtige Aktivitäten leichter erkannt und im Nachhinein nachvollzogen werden können. Praktische Umsetzungen können sein: (1) der Einsatz eines dedizierten, gehärteten Servers mit restriktiven Firewall-Regeln, (2) die Nutzung von Mehrfaktor-Authentisierung und zentralem Benutzer-Management auf dem Sprungserver, (3) eine verpflichtende Session-Aufzeichnung oder Protokollierung sämtlicher Administrationsvorgänge. | R28: Netzplan | S28: Sprungserver | T28: G 0.23 – Unbefugtes Eindringen in IT-Systeme; G 0.30 – Unberechtigte Nutzung oder Administration von Geräten und Systemen; G 0.15 – Abhören | U28: 5 | V28: 2 | W28: 1 | X28: 1 | Y28: 1
A29: ARCH.2.3 | B29: Mikrosegmentierung | D29: Anforderungen bei erhöhtem Schutzbedarf | E29: Gesamt: | H29: =IF(OR(COUNTBLANK($H$30:$H$30)>0,COUNTIF($H$30:$H$30,"unbearbeitet")=COUNTA($H$30:$H$30)),"Bitte Teilanforderungen ausfüllen",IF(COUNTIF($H$30:$H$30,"zu klären")>0,"zu klären",IF(COUNTIF($H$30:$H$30,"entbehrlich")=COUNTA($H$30:$H$30),"entbehrlich",IF(COUNTIF($H$30:$H$30,"verwiesen")=COUNTA($H$30:$H$30),"verwiesen",IF(COUNTIF($H$30:$H$30,"nein")+COUNTIF($H$30:$H$30,"entbehrlich")=COUNTA($H$30:$H$30),"nein",IF(COUNTIF($H$30:$H$30,"ja")+COUNTIF($H$30:$H$30,"entbehrlich")+COUNTIF($H$30:$H$30,"verwiesen")=COUNTA($H$30:$H$30),"ja","teilweise")))))) -> Bitte Teilanforderungen ausfüllen | M29: Vertraulichkeit | N29: NET.1.1.A4-UA.3; NET.3.4.A9-UA.2; SYS.1.5.A4-UA.2; SYS.1.5.A9-UA.4; SYS.1.6.A5-UA.3 | O29: subset-of; equivalent-to; subset-of; subset-of; equivalent-to | P29: Mikrosegmentierung ist die Unterteilung des Netzes in möglichst kleine Segmente (z.B. pro IT-System oder Server-Anwendung). Für jedes dieser Segmente wird die erlaubte Kommunikation definiert und gefiltert. Mikrosegmentierung sorgt dafür, dass z.B. zwei medizinische Geräte mit gleicher Rolle zwar ins gleiche VLAN dürfen, aber nicht direkt miteinander kommunizieren dürfen. Die Umsetzung kann mit dynamischen VLANs, softwaredefinierten Netzwerken (SDN) oder Netzwerk-Firewalls auf Host-Ebene erfolgen. Die Mikrosegmentierung begrenzt Angriffe, die sich lateral ausbreiten. | Q29: IT-Systeme | R29: Netzplan | S29: Verbindungen zu allen anderen IT-Systemen | T29: G 0.23 – Unbefugtes Eindringen in IT-Systeme; G 0.30 – Unberechtigte Nutzung oder Administration von Geräten und Systemen; G 0.15 – Abhören | U29: 5 | V29: 2 | W29: 1 | X29: 1 | Y29: 1
A30: ARCH.2.3 | B30: Mikrosegmentierung | C30: ARCH.2.3 | D30: Anforderungen bei erhöhtem Schutzbedarf | E30: Architektur für IT-Systeme KANN Verbindungen zu allen anderen IT-Systemen einschränken. | H30: unbearbeitet | M30: Vertraulichkeit | N30: NET.1.1.A4-UA.3; NET.3.4.A9-UA.2; SYS.1.5.A4-UA.2; SYS.1.5.A9-UA.4; SYS.1.6.A5-UA.3 | O30: subset-of; equivalent-to; subset-of; subset-of; equivalent-to | P30: Mikrosegmentierung ist die Unterteilung des Netzes in möglichst kleine Segmente (z.B. pro IT-System oder Server-Anwendung). Für jedes dieser Segmente wird die erlaubte Kommunikation definiert und gefiltert. Mikrosegmentierung sorgt dafür, dass z.B. zwei medizinische Geräte mit gleicher Rolle zwar ins gleiche VLAN dürfen, aber nicht direkt miteinander kommunizieren dürfen. Die Umsetzung kann mit dynamischen VLANs, softwaredefinierten Netzwerken (SDN) oder Netzwerk-Firewalls auf Host-Ebene erfolgen. Die Mikrosegmentierung begrenzt Angriffe, die sich lateral ausbreiten. | Q30: IT-Systeme | R30: Netzplan | S30: Verbindungen zu allen anderen IT-Systemen | T30: G 0.23 – Unbefugtes Eindringen in IT-Systeme; G 0.30 – Unberechtigte Nutzung oder Administration von Geräten und Systemen; G 0.15 – Abhören | U30: 5 | V30: 2 | W30: 1 | X30: 1 | Y30: 1
A31: ARCH.2.4 | B31: Inventar der Netze | D31: Standard-Anforderungen | E31: Gesamt: | H31: =IF(OR(COUNTBLANK($H$32:$H$32)>0,COUNTIF($H$32:$H$32,"unbearbeitet")=COUNTA($H$32:$H$32)),"Bitte Teilanforderungen ausfüllen",IF(COUNTIF($H$32:$H$32,"zu klären")>0,"zu klären",IF(COUNTIF($H$32:$H$32,"entbehrlich")=COUNTA($H$32:$H$32),"entbehrlich",IF(COUNTIF($H$32:$H$32,"verwiesen")=COUNTA($H$32:$H$32),"verwiesen",IF(COUNTIF($H$32:$H$32,"nein")+COUNTIF($H$32:$H$32,"entbehrlich")=COUNTA($H$32:$H$32),"nein",IF(COUNTIF($H$32:$H$32,"ja")+COUNTIF($H$32:$H$32,"entbehrlich")+COUNTIF($H$32:$H$32,"verwiesen")=COUNTA($H$32:$H$32),"ja","teilweise")))))) -> Bitte Teilanforderungen ausfüllen | M31: Vertraulichkeit, Integrität | N31: IND.1.A4-UA.6; INF.12.A10-UA.1; NET.1.1.A16-UA.2; NET.1.1.A17-UA.2; NET.1.1.A2-UA.5; NET.1.1.A22-UA.4; NET.1.1.A25-UA.1; NET.1.2.A12-UA.6; NET.1.2.A13-UA.2 | O31: subset-of; subset-of; superset-of; superset-of; equivalent-to; superset-of; intersects-with; subset-of; intersects-with | P31: Die Erfassung externer Netzanschlüsse – etwa zu Partnernetzen, Cloud-Diensten oder dem Internet – hilft, potenzielle Angriffspunkte zu identifizieren und gezielte Schutzmaßnahmen zu planen. Beispiele für interne Netzsegmente können klassische Trennungen wie IT-Office-Netze, SCADA-/Leittechnik-Netze oder DMZs für externe Zugriffe sein. Dabei sollten auch virtuelle Netze und virtuelle Switches berücksichtigt werden, ebenso wie Container-Infrastrukturen. Als externe Netzanschlüsse kommen etwa VPN-Gateways, dedizierte Providerverbindungen, Fernwartungszugänge oder Cloud-Endpunkte in Frage. Dabei sind nicht nur die auf den ersten Blick relevanten Datennetze, sondern auch andere Telekommunikationsanbindungen wie ISDN-Leitungen, Mobilfunkausweichstrecken oder WLAN-Roaming von Clients relevant. Der Verwendungszweck beschreibt, warum ein Segment oder Anschluss existiert – etwa für Produktivsysteme, Entwicklung, Administration oder Gastzugänge. Der Zweck von Netzsegmenten kann durch einen sprechenden Namen dokumentiert werden, z. B. Management-Netz, OT-Netz, Internetanschluss, Netz der Finanzverwaltung. Dies hilft, Zuständigkeiten und Zugriffsrechte klar zuzuordnen, z. B. anhand von Geschäftsprozessen, Organisationseinheiten oder Zielgruppen (z. B. Gäste, Vertrieb, Leitung). Dabei sind, falls vorhanden, auch WLANs/SSIDs, IoT-Geräte wie vernetzte Kühlschränke, Hausleittechnik, operative Technologien oder Industrielle Steuerungssysteme zu berücksichtigen. Informationen können aus Netzwerkmanagementsystemen, Konfigurationsdateien oder Asset-Management-Tools gewonnen werden. Die Pflege kann als wiederkehrende Aufgabe in Prozesse eingebettet oder im Rahmen von Änderungen (z. B. Change Management) angestoßen werden. Auch eine einfache Pflege in Tabellenform kann sinnvoll sein – entscheidend ist die Klarheit und Aktualität. | R31: Netzplan | S31: ein Inventar der Netze | T31: G 0.18 – Fehlplanung oder fehlende Anpassung; G 0.23 – Unbefugtes Eindringen in IT-Systeme; G 0.30 – Unberechtigte Nutzung oder Administration von Geräten und Systemen | U31: 2 | V31: 2 | W31: 2 | X31: 1 | Y31: 1
A32: ARCH.2.4 | B32: Inventar der Netze | C32: ARCH.2.4 | D32: Standard-Anforderungen | E32: Architektur SOLLTE ein Inventar der Netze einschließlich interner Segmente, externer Netzanschlüsse und deren Verwendungszweck dokumentieren. | H32: unbearbeitet | M32: Vertraulichkeit, Integrität | N32: IND.1.A4-UA.6; INF.12.A10-UA.1; NET.1.1.A16-UA.2; NET.1.1.A17-UA.2; NET.1.1.A2-UA.5; NET.1.1.A22-UA.4; NET.1.1.A25-UA.1; NET.1.2.A12-UA.6; NET.1.2.A13-UA.2 | O32: subset-of; subset-of; superset-of; superset-of; equivalent-to; superset-of; intersects-with; subset-of; intersects-with | P32: Die Erfassung externer Netzanschlüsse – etwa zu Partnernetzen, Cloud-Diensten oder dem Internet – hilft, potenzielle Angriffspunkte zu identifizieren und gezielte Schutzmaßnahmen zu planen. Beispiele für interne Netzsegmente können klassische Trennungen wie IT-Office-Netze, SCADA-/Leittechnik-Netze oder DMZs für externe Zugriffe sein. Dabei sollten auch virtuelle Netze und virtuelle Switches berücksichtigt werden, ebenso wie Container-Infrastrukturen. Als externe Netzanschlüsse kommen etwa VPN-Gateways, dedizierte Providerverbindungen, Fernwartungszugänge oder Cloud-Endpunkte in Frage. Dabei sind nicht nur die auf den ersten Blick relevanten Datennetze, sondern auch andere Telekommunikationsanbindungen wie ISDN-Leitungen, Mobilfunkausweichstrecken oder WLAN-Roaming von Clients relevant. Der Verwendungszweck beschreibt, warum ein Segment oder Anschluss existiert – etwa für Produktivsysteme, Entwicklung, Administration oder Gastzugänge. Der Zweck von Netzsegmenten kann durch einen sprechenden Namen dokumentiert werden, z. B. Management-Netz, OT-Netz, Internetanschluss, Netz der Finanzverwaltung. Dies hilft, Zuständigkeiten und Zugriffsrechte klar zuzuordnen, z. B. anhand von Geschäftsprozessen, Organisationseinheiten oder Zielgruppen (z. B. Gäste, Vertrieb, Leitung). Dabei sind, falls vorhanden, auch WLANs/SSIDs, IoT-Geräte wie vernetzte Kühlschränke, Hausleittechnik, operative Technologien oder Industrielle Steuerungssysteme zu berücksichtigen. Informationen können aus Netzwerkmanagementsystemen, Konfigurationsdateien oder Asset-Management-Tools gewonnen werden. Die Pflege kann als wiederkehrende Aufgabe in Prozesse eingebettet oder im Rahmen von Änderungen (z. B. Change Management) angestoßen werden. Auch eine einfache Pflege in Tabellenform kann sinnvoll sein – entscheidend ist die Klarheit und Aktualität. | R32: Netzplan | S32: ein Inventar der Netze | T32: G 0.18 – Fehlplanung oder fehlende Anpassung; G 0.23 – Unbefugtes Eindringen in IT-Systeme; G 0.30 – Unberechtigte Nutzung oder Administration von Geräten und Systemen | U32: 2 | V32: 2 | W32: 2 | X32: 1 | Y32: 1
A33: ARCH.2.5 | B33: Netzplan | D33: Standard-Anforderungen | E33: Gesamt: | H33: =IF(OR(COUNTBLANK($H$34:$H$34)>0,COUNTIF($H$34:$H$34,"unbearbeitet")=COUNTA($H$34:$H$34)),"Bitte Teilanforderungen ausfüllen",IF(COUNTIF($H$34:$H$34,"zu klären")>0,"zu klären",IF(COUNTIF($H$34:$H$34,"entbehrlich")=COUNTA($H$34:$H$34),"entbehrlich",IF(COUNTIF($H$34:$H$34,"verwiesen")=COUNTA($H$34:$H$34),"verwiesen",IF(COUNTIF($H$34:$H$34,"nein")+COUNTIF($H$34:$H$34,"entbehrlich")=COUNTA($H$34:$H$34),"nein",IF(COUNTIF($H$34:$H$34,"ja")+COUNTIF($H$34:$H$34,"entbehrlich")+COUNTIF($H$34:$H$34,"verwiesen")=COUNTA($H$34:$H$34),"ja","teilweise")))))) -> Bitte Teilanforderungen ausfüllen | M33: Vertraulichkeit, Integrität | N33: IND.1.A4-UA.6; NET.1.1.A13-UA.3; NET.1.1.A2-UA.2; NET.1.1.A2-UA.5; NET.1.1.A25-UA.1 | O33: subset-of; intersects-with; equal-to; subset-of; superset-of | P33: Ein Netzplan (engl. network diagram) stellt eine schematische Darstellung der logischen und physischen Struktur von Kommunikationsnetzen dar und bildet die Grundlage für Transparenz im Betrieb. Er kann einen zentralen Beitrag zur Informationssicherheit leisten, da er Transparenz über die Struktur, Verbindungen und Schutzbedarfe einer Netzwerkumgebung schafft. Ein aktueller Netzplan, aus dem sich gut die Netzstruktur erkennen lässt, ermöglicht es Anschlüssen mit hohem Risiko oder von einzelnen Ausfallstellen (Single Points of Failure) auf einen Blick zu erkennen. Für die Umsetzung ist es nicht erforderlich, jedes Subnetz einzeln in einer Grafik zu visualisieren. Vielmehr kann es hilfreich sein, Netzpläne auf einem abstrahierten Level zu halten, z. B. als logische Übersicht mit Domänen, Segmenten und Übergängen (bereinigter Netzplan). Eine Visualisierung als Layer-Modell (z. B. Infrastruktur-, Kommunikations- und Applikationsebene) kann zusätzliche Einblicke schaffen. Auch eine einfache Pflege als visuelle Skizze kann sinnvoll sein – entscheidend ist die Klarheit und Aktualität. | Q33: Netze | R33: Netzplan | S33: einen Netzplan | T33: G 0.23 – Unbefugtes Eindringen in IT-Systeme; G 0.30 – Unberechtigte Nutzung oder Administration von Geräten und Systemen; G 0.18 – Fehlplanung oder fehlende Anpassung; G 0.37 – Abstreiten von Handlungen | U33: 2 | V33: 2 | W33: 2 | X33: 1 | Y33: 1
A34: ARCH.2.5 | B34: Netzplan | C34: ARCH.2.5 | D34: Standard-Anforderungen | E34: Architektur für Netze SOLLTE einen Netzplan dokumentieren. | H34: unbearbeitet | M34: Vertraulichkeit, Integrität | N34: IND.1.A4-UA.6; NET.1.1.A13-UA.3; NET.1.1.A2-UA.2; NET.1.1.A2-UA.5; NET.1.1.A25-UA.1 | O34: subset-of; intersects-with; equal-to; subset-of; superset-of | P34: Ein Netzplan (engl. network diagram) stellt eine schematische Darstellung der logischen und physischen Struktur von Kommunikationsnetzen dar und bildet die Grundlage für Transparenz im Betrieb. Er kann einen zentralen Beitrag zur Informationssicherheit leisten, da er Transparenz über die Struktur, Verbindungen und Schutzbedarfe einer Netzwerkumgebung schafft. Ein aktueller Netzplan, aus dem sich gut die Netzstruktur erkennen lässt, ermöglicht es Anschlüssen mit hohem Risiko oder von einzelnen Ausfallstellen (Single Points of Failure) auf einen Blick zu erkennen. Für die Umsetzung ist es nicht erforderlich, jedes Subnetz einzeln in einer Grafik zu visualisieren. Vielmehr kann es hilfreich sein, Netzpläne auf einem abstrahierten Level zu halten, z. B. als logische Übersicht mit Domänen, Segmenten und Übergängen (bereinigter Netzplan). Eine Visualisierung als Layer-Modell (z. B. Infrastruktur-, Kommunikations- und Applikationsebene) kann zusätzliche Einblicke schaffen. Auch eine einfache Pflege als visuelle Skizze kann sinnvoll sein – entscheidend ist die Klarheit und Aktualität. | Q34: Netze | R34: Netzplan | S34: einen Netzplan | T34: G 0.23 – Unbefugtes Eindringen in IT-Systeme; G 0.30 – Unberechtigte Nutzung oder Administration von Geräten und Systemen; G 0.18 – Fehlplanung oder fehlende Anpassung; G 0.37 – Abstreiten von Handlungen | U34: 2 | V34: 2 | W34: 2 | X34: 1 | Y34: 1
A35: ARCH.2.6 | B35: Topologieüberwachung | D35: Standard-Anforderungen | E35: Gesamt: | H35: =IF(OR(COUNTBLANK($H$36:$H$36)>0,COUNTIF($H$36:$H$36,"unbearbeitet")=COUNTA($H$36:$H$36)),"Bitte Teilanforderungen ausfüllen",IF(COUNTIF($H$36:$H$36,"zu klären")>0,"zu klären",IF(COUNTIF($H$36:$H$36,"entbehrlich")=COUNTA($H$36:$H$36),"entbehrlich",IF(COUNTIF($H$36:$H$36,"verwiesen")=COUNTA($H$36:$H$36),"verwiesen",IF(COUNTIF($H$36:$H$36,"nein")+COUNTIF($H$36:$H$36,"entbehrlich")=COUNTA($H$36:$H$36),"nein",IF(COUNTIF($H$36:$H$36,"ja")+COUNTIF($H$36:$H$36,"entbehrlich")+COUNTIF($H$36:$H$36,"verwiesen")=COUNTA($H$36:$H$36),"ja","teilweise")))))) -> Bitte Teilanforderungen ausfüllen | N35: NET.1.1.A1-UA.7; NET.1.1.A15-UA.3; NET.1.2.A11-UA.4; NET.2.1.A13-UA.2 | O35: superset-of; equivalent-to; superset-of; subset-of | P35: Unbeabsichtigte Netzverbindungen können z.B. über falsch gesteckte Kabel, WLAN auf Clients oder Modems im öffentlichen Telefonnetz (PSTN) an einer TK-Anlage entstehen. Die Anforderung kann durch Netzscans, Software zur Topologieüberwachung oder Protokollanalyse umgesetzt werden. Hierbei sind auch virtualisierte Systeme auf VM-Hosts zu berücksichtigen. | Q35: Netze | R35: IT-Betriebskonzept | S35: die Einhaltung der Netzarchitektur | T35: G 0.19 – Offenlegung schützenswerter Informationen; G 0.30 – Unberechtigte Nutzung oder Administration von Geräten und Systemen; G 0.22 – Manipulation von Informationen; G 0.41 – Sabotage | U35: 4 | V35: 1 | W35: 1 | X35: 1 | Y35: 1
A36: ARCH.2.6 | B36: Topologieüberwachung | C36: ARCH.2.6 | D36: Standard-Anforderungen | E36: Architektur für Netze SOLLTE die Einhaltung der Netzarchitektur regelmäßig überprüfen. | H36: unbearbeitet | N36: NET.1.1.A1-UA.7; NET.1.1.A15-UA.3; NET.1.2.A11-UA.4; NET.2.1.A13-UA.2 | O36: superset-of; equivalent-to; superset-of; subset-of | P36: Unbeabsichtigte Netzverbindungen können z.B. über falsch gesteckte Kabel, WLAN auf Clients oder Modems im öffentlichen Telefonnetz (PSTN) an einer TK-Anlage entstehen. Die Anforderung kann durch Netzscans, Software zur Topologieüberwachung oder Protokollanalyse umgesetzt werden. Hierbei sind auch virtualisierte Systeme auf VM-Hosts zu berücksichtigen. | Q36: Netze | R36: IT-Betriebskonzept | S36: die Einhaltung der Netzarchitektur | T36: G 0.19 – Offenlegung schützenswerter Informationen; G 0.30 – Unberechtigte Nutzung oder Administration von Geräten und Systemen; G 0.22 – Manipulation von Informationen; G 0.41 – Sabotage | U36: 4 | V36: 1 | W36: 1 | X36: 1 | Y36: 1
A37: ARCH.3.1 | B37: Netzabdeckung | D37: Standard-Anforderungen | E37: Gesamt: | H37: =IF(OR(COUNTBLANK($H$38:$H$38)>0,COUNTIF($H$38:$H$38,"unbearbeitet")=COUNTA($H$38:$H$38)),"Bitte Teilanforderungen ausfüllen",IF(COUNTIF($H$38:$H$38,"zu klären")>0,"zu klären",IF(COUNTIF($H$38:$H$38,"entbehrlich")=COUNTA($H$38:$H$38),"entbehrlich",IF(COUNTIF($H$38:$H$38,"verwiesen")=COUNTA($H$38:$H$38),"verwiesen",IF(COUNTIF($H$38:$H$38,"nein")+COUNTIF($H$38:$H$38,"entbehrlich")=COUNTA($H$38:$H$38),"nein",IF(COUNTIF($H$38:$H$38,"ja")+COUNTIF($H$38:$H$38,"entbehrlich")+COUNTIF($H$38:$H$38,"verwiesen")=COUNTA($H$38:$H$38),"ja","teilweise")))))) -> Bitte Teilanforderungen ausfüllen | M37: Vertraulichkeit, Integrität | N37: NET.2.1.A13-UA.3; NET.2.1.A4-UA.2 | O37: subset-of; superset-of | P37: Drahtlose Netzanbindungen sind schwerer zu schützen als kabelgebundene Netze, da der Perimeter des Netzes schwerer zu erkennen ist. Das erschwert es, die Netzverfügbarkeit zu gewährleisten und gleichzeitig den Zugang zum Netz vor unbefugtem Zugriff oder Störungen zwischen Netzen zu schützen. Zudem können Wände und andere strahlende Geräte wie Mikrowellen-Geräte oder Bluetooth-Sender den Empfang beeinträchtigen. Ein Test des Empfangs an wichtigen Standorten unter realen Bedingungen hilft, die WLAN-Qualität zu gewährleisten. Der Empfang in den verschiedenen Frequenzbändern kann dabei unterschiedlich ausfallen. Für weitere Informationen, siehe Allgemeinzuteilungen von Frequenzen für Mobilfunkanwendungen, DECT, WLAN, CB-Funk und ähnliche Anwendungen der Bundesnetzagentur. Abdeckungsbereich ist der Bereich, in dem das WLAN mit gewöhnlichen Endgeräten genutzt werden kann. Relevant ist dabei auch die Abdeckung aller Orte, an denen sich Gäste aufhalten, sowie an Orte an denen gerade kein Empfang gewünscht ist, z.B. Serverräume oder abhörsichere Räume. | Q37: WLANs | R37: Netzplan | S37: die Netzabdeckung | T37: G 0.18 – Fehlplanung oder fehlende Anpassung; G 0.43 – Einspielen von Nachrichten | U37: 2 | V37: 2 | W37: 2 | X37: 1 | Y37: 1
A38: ARCH.3.1 | B38: Netzabdeckung | C38: ARCH.3.1 | D38: Standard-Anforderungen | E38: Architektur für WLANs SOLLTE die Netzabdeckung testen. | H38: unbearbeitet | M38: Vertraulichkeit, Integrität | N38: NET.2.1.A13-UA.3; NET.2.1.A4-UA.2 | O38: subset-of; superset-of | P38: Drahtlose Netzanbindungen sind schwerer zu schützen als kabelgebundene Netze, da der Perimeter des Netzes schwerer zu erkennen ist. Das erschwert es, die Netzverfügbarkeit zu gewährleisten und gleichzeitig den Zugang zum Netz vor unbefugtem Zugriff oder Störungen zwischen Netzen zu schützen. Zudem können Wände und andere strahlende Geräte wie Mikrowellen-Geräte oder Bluetooth-Sender den Empfang beeinträchtigen. Ein Test des Empfangs an wichtigen Standorten unter realen Bedingungen hilft, die WLAN-Qualität zu gewährleisten. Der Empfang in den verschiedenen Frequenzbändern kann dabei unterschiedlich ausfallen. Für weitere Informationen, siehe Allgemeinzuteilungen von Frequenzen für Mobilfunkanwendungen, DECT, WLAN, CB-Funk und ähnliche Anwendungen der Bundesnetzagentur. Abdeckungsbereich ist der Bereich, in dem das WLAN mit gewöhnlichen Endgeräten genutzt werden kann. Relevant ist dabei auch die Abdeckung aller Orte, an denen sich Gäste aufhalten, sowie an Orte an denen gerade kein Empfang gewünscht ist, z.B. Serverräume oder abhörsichere Räume. | Q38: WLANs | R38: Netzplan | S38: die Netzabdeckung | T38: G 0.18 – Fehlplanung oder fehlende Anpassung; G 0.43 – Einspielen von Nachrichten | U38: 2 | V38: 2 | W38: 2 | X38: 1 | Y38: 1
A39: ARCH.3.2 | B39: Einschränkung in Sicherheitsbereichen | D39: Anforderungen bei erhöhtem Schutzbedarf | E39: Gesamt: | H39: =IF(OR(COUNTBLANK($H$40:$H$40)>0,COUNTIF($H$40:$H$40,"unbearbeitet")=COUNTA($H$40:$H$40)),"Bitte Teilanforderungen ausfüllen",IF(COUNTIF($H$40:$H$40,"zu klären")>0,"zu klären",IF(COUNTIF($H$40:$H$40,"entbehrlich")=COUNTA($H$40:$H$40),"entbehrlich",IF(COUNTIF($H$40:$H$40,"verwiesen")=COUNTA($H$40:$H$40),"verwiesen",IF(COUNTIF($H$40:$H$40,"nein")+COUNTIF($H$40:$H$40,"entbehrlich")=COUNTA($H$40:$H$40),"nein",IF(COUNTIF($H$40:$H$40,"ja")+COUNTIF($H$40:$H$40,"entbehrlich")+COUNTIF($H$40:$H$40,"verwiesen")=COUNTA($H$40:$H$40),"ja","teilweise")))))) -> Bitte Teilanforderungen ausfüllen | M39: Vertraulichkeit, Verfügbarkeit | N39: NET.2.1.A1-UA.3; NET.2.1.A4-UA.3 | O39: equivalent-to; equivalent-to | P39: Hierzu gehören beispielsweise abhörsichere Räume oder Serverräume, von denen aus keine Daten ins Internet gesendet werden sollen. Dies kann z.B. durch die Reduktion der Sendeleistung in benachbarten Räumen oder die Isolierung der Räume erfolgen. | Q39: WLANs | R39: Netzplan | S39: in Sicherheitsbereichen die Ausstrahlung | T39: G 0.18 – Fehlplanung oder fehlende Anpassung; G 0.16 – Diebstahl von Geräten, Datenträgern oder Dokumenten | U39: 4 | V39: 2 | W39: 1 | X39: 2 | Y39: 0
A40: ARCH.3.2 | B40: Einschränkung in Sicherheitsbereichen | C40: ARCH.3.2 | D40: Anforderungen bei erhöhtem Schutzbedarf | E40: Architektur für WLANs KANN in Sicherheitsbereichen die Ausstrahlung einschränken. | H40: unbearbeitet | M40: Vertraulichkeit, Verfügbarkeit | N40: NET.2.1.A1-UA.3; NET.2.1.A4-UA.3 | O40: equivalent-to; equivalent-to | P40: Hierzu gehören beispielsweise abhörsichere Räume oder Serverräume, von denen aus keine Daten ins Internet gesendet werden sollen. Dies kann z.B. durch die Reduktion der Sendeleistung in benachbarten Räumen oder die Isolierung der Räume erfolgen. | Q40: WLANs | R40: Netzplan | S40: in Sicherheitsbereichen die Ausstrahlung | T40: G 0.18 – Fehlplanung oder fehlende Anpassung; G 0.16 – Diebstahl von Geräten, Datenträgern oder Dokumenten | U40: 4 | V40: 2 | W40: 1 | X40: 2 | Y40: 0
A41: ARCH.3.3 | B41: SSIDs | D41: Standard-Anforderungen | E41: Gesamt: | H41: =IF(OR(COUNTBLANK($H$42:$H$42)>0,COUNTIF($H$42:$H$42,"unbearbeitet")=COUNTA($H$42:$H$42)),"Bitte Teilanforderungen ausfüllen",IF(COUNTIF($H$42:$H$42,"zu klären")>0,"zu klären",IF(COUNTIF($H$42:$H$42,"entbehrlich")=COUNTA($H$42:$H$42),"entbehrlich",IF(COUNTIF($H$42:$H$42,"verwiesen")=COUNTA($H$42:$H$42),"verwiesen",IF(COUNTIF($H$42:$H$42,"nein")+COUNTIF($H$42:$H$42,"entbehrlich")=COUNTA($H$42:$H$42),"nein",IF(COUNTIF($H$42:$H$42,"ja")+COUNTIF($H$42:$H$42,"entbehrlich")+COUNTIF($H$42:$H$42,"verwiesen")=COUNTA($H$42:$H$42),"ja","teilweise")))))) -> Bitte Teilanforderungen ausfüllen | M41: Vertraulichkeit, Integrität | N41: NET.2.1.A5-UA.2 | O41: equivalent-to | P41: Viele WLAN-Geräte bringen ab Werk eingestellte Netznamen (Default SSID) mit, aus denen sich häufig Rückschlüsse auf eingesetzte Geräte oder sogar Zugangsdaten ziehen lassen. Eigene SSIDs können Nutzenden die Zuordnung der Netze zur Institution oder deren Unterscheidung erleichtern, wenn hierfür sprechende Namen konfiguriert werden (z.B. "Institutionsname-Gastnetz"). | Q41: WLANs | R41: Netzplan | S41: institutionsspezifische SSIDs | T41: G 0.18 – Fehlplanung oder fehlende Anpassung; G 0.23 – Unbefugtes Eindringen in IT-Systeme | U41: 2 | V41: 2 | W41: 2 | X41: 1 | Y41: 0
A42: ARCH.3.3 | B42: SSIDs | C42: ARCH.3.3 | D42: Standard-Anforderungen | E42: Architektur für WLANs SOLLTE institutionsspezifische SSIDs aktivieren. | H42: unbearbeitet | M42: Vertraulichkeit, Integrität | N42: NET.2.1.A5-UA.2 | O42: equivalent-to | P42: Viele WLAN-Geräte bringen ab Werk eingestellte Netznamen (Default SSID) mit, aus denen sich häufig Rückschlüsse auf eingesetzte Geräte oder sogar Zugangsdaten ziehen lassen. Eigene SSIDs können Nutzenden die Zuordnung der Netze zur Institution oder deren Unterscheidung erleichtern, wenn hierfür sprechende Namen konfiguriert werden (z.B. "Institutionsname-Gastnetz"). | Q42: WLANs | R42: Netzplan | S42: institutionsspezifische SSIDs | T42: G 0.18 – Fehlplanung oder fehlende Anpassung; G 0.23 – Unbefugtes Eindringen in IT-Systeme | U42: 2 | V42: 2 | W42: 2 | X42: 1 | Y42: 0
A43: ARCH.3.4 | B43: Verschlüsselte Netzanbindung | D43: Standard-Anforderungen | E43: Gesamt: | H43: =IF(OR(COUNTBLANK($H$44:$H$44)>0,COUNTIF($H$44:$H$44,"unbearbeitet")=COUNTA($H$44:$H$44)),"Bitte Teilanforderungen ausfüllen",IF(COUNTIF($H$44:$H$44,"zu klären")>0,"zu klären",IF(COUNTIF($H$44:$H$44,"entbehrlich")=COUNTA($H$44:$H$44),"entbehrlich",IF(COUNTIF($H$44:$H$44,"verwiesen")=COUNTA($H$44:$H$44),"verwiesen",IF(COUNTIF($H$44:$H$44,"nein")+COUNTIF($H$44:$H$44,"entbehrlich")=COUNTA($H$44:$H$44),"nein",IF(COUNTIF($H$44:$H$44,"ja")+COUNTIF($H$44:$H$44,"entbehrlich")+COUNTIF($H$44:$H$44,"verwiesen")=COUNTA($H$44:$H$44),"ja","teilweise")))))) -> Bitte Teilanforderungen ausfüllen | M43: Vertraulichkeit | N43: INF.10.A6-UA.4; NET.1.1.A34-UA.3; NET.2.1.A17-UA.1; NET.2.1.A3-UA.1; NET.2.2.A3-UA.3; SYS.2.1.A18-UA.1 | O43: superset-of; superset-of; subset-of; equivalent-to; superset-of; superset-of | P43: Ohne eine sichere Verschlüsselung könnte ein Angreifer durch „Sniffing“ sensible Inhalte wie Passwörter, E-Mails oder Geschäftsdaten abfangen oder sogar schadhaften Datenverkehr in die Kommunikation einschleusen. Ebenso könnte ein schwacher oder veralteter Standard wie WEP einem Angreifer ermöglichen, das WLAN-Passwort innerhalb weniger Minuten zu knacken und damit vollständigen Netzzugang zu erlangen. Eine zeitgemäße und wirksame Verschlüsselung kann dagegen die Vertraulichkeit und Integrität der Kommunikation sicherstellen und bietet Schutz vor Angriffen wie „Man-in-the-Middle“-Manipulationen oder unerwünschtem Zugriff über „Rogue Clients“. Netzanbindung bedeutet hier, dass nicht nur die über das Netz transportierten Daten verschlüsselt werden, sondern auch die Kommunikation selbst, z.B. die Adressen kommunizierender Geräte. Anerkannten Standards meint z.B. WPA3-Enterprise mit 802.1X und EAP-TLS. Für Details siehe IEEE 80211, WPA3. | Q43: WLANs | R43: Konfigurationshistorie | S43: die Netzanbindung | T43: G 0.23 – Unbefugtes Eindringen in IT-Systeme; G 0.15 – Abhören; G 0.43 – Einspielen von Nachrichten | U43: 2 | V43: 2 | W43: 1 | X43: 1 | Y43: 1
A44: ARCH.3.4 | B44: Verschlüsselte Netzanbindung | C44: ARCH.3.4 | D44: Standard-Anforderungen | E44: Architektur für WLANs SOLLTE die Netzanbindung nach einem anerkannten Standard verschlüsseln. | H44: unbearbeitet | M44: Vertraulichkeit | N44: INF.10.A6-UA.4; NET.1.1.A34-UA.3; NET.2.1.A17-UA.1; NET.2.1.A3-UA.1; NET.2.2.A3-UA.3; SYS.2.1.A18-UA.1 | O44: superset-of; superset-of; subset-of; equivalent-to; superset-of; superset-of | P44: Ohne eine sichere Verschlüsselung könnte ein Angreifer durch „Sniffing“ sensible Inhalte wie Passwörter, E-Mails oder Geschäftsdaten abfangen oder sogar schadhaften Datenverkehr in die Kommunikation einschleusen. Ebenso könnte ein schwacher oder veralteter Standard wie WEP einem Angreifer ermöglichen, das WLAN-Passwort innerhalb weniger Minuten zu knacken und damit vollständigen Netzzugang zu erlangen. Eine zeitgemäße und wirksame Verschlüsselung kann dagegen die Vertraulichkeit und Integrität der Kommunikation sicherstellen und bietet Schutz vor Angriffen wie „Man-in-the-Middle“-Manipulationen oder unerwünschtem Zugriff über „Rogue Clients“. Netzanbindung bedeutet hier, dass nicht nur die über das Netz transportierten Daten verschlüsselt werden, sondern auch die Kommunikation selbst, z.B. die Adressen kommunizierender Geräte. Anerkannten Standards meint z.B. WPA3-Enterprise mit 802.1X und EAP-TLS. Für Details siehe IEEE 80211, WPA3. | Q44: WLANs | R44: Konfigurationshistorie | S44: die Netzanbindung | T44: G 0.23 – Unbefugtes Eindringen in IT-Systeme; G 0.15 – Abhören; G 0.43 – Einspielen von Nachrichten | U44: 2 | V44: 2 | W44: 1 | X44: 1 | Y44: 1
A45: ARCH.4.1 | B45: Netzzugangskontrolle | D45: Standard-Anforderungen | E45: Gesamt: | H45: =IF(OR(COUNTBLANK($H$46:$H$48)>0,COUNTIF($H$46:$H$48,"unbearbeitet")=COUNTA($H$46:$H$48)),"Bitte Teilanforderungen ausfüllen",IF(COUNTIF($H$46:$H$48,"zu klären")>0,"zu klären",IF(COUNTIF($H$46:$H$48,"entbehrlich")=COUNTA($H$46:$H$48),"entbehrlich",IF(COUNTIF($H$46:$H$48,"verwiesen")=COUNTA($H$46:$H$48),"verwiesen",IF(COUNTIF($H$46:$H$48,"nein")+COUNTIF($H$46:$H$48,"entbehrlich")=COUNTA($H$46:$H$48),"nein",IF(COUNTIF($H$46:$H$48,"ja")+COUNTIF($H$46:$H$48,"entbehrlich")+COUNTIF($H$46:$H$48,"verwiesen")=COUNTA($H$46:$H$48),"ja","teilweise")))))) -> Bitte Teilanforderungen ausfüllen | M45: Vertraulichkeit, Integrität | N45: INF.10.A6-UA.2; INF.14.A11-UA.4; NET.3.4.A14-UA.2; NET.3.4.A23-UA.4; NET.3.4.A7-UA.2; NET.3.4.A9-UA.2 | O45: equivalent-to; subset-of; intersects-with; intersects-with; equal-to; superset-of | P45: Unautorisierte Systeme könnten Ausgangspunkt von Angriffen sein oder zu unbeabsichtigten Störungen im Netz führen. Netzwerkzugangskontrolle (Network Access Control, NAC) bietet eine wirksame Möglichkeit, den Zugriff auf Netzwerke kontrolliert zu steuern, insbesondere in schützenswerten Bereichen wie Management-Netzen, Produktionssystemen oder Forschungsumgebungen. Die Auswahl der Netzbereiche für die Netzzugangskontrolle richtet sich nach dem Schutzbedarf oder Risikoprofil. Dabei empfiehlt sich zu dokumentieren, welche Zonen mit NAC abgesichert werden und warum andere bewusst nicht berücksichtigt werden (z.B. aufgrund technischer Einschränkungen oder fehlender Relevanz). Die Umsetzung kann (1) auf Zertifikaten basieren (X.509, EAP‑TLS or mTLS), (2) auf Zugangskonten basieren (IEEE 802.1X, RADIUS), (3) auf dynamischen Prüfungen basieren (z.B. Sicherheitspatches). Eine Authentifizierung, die nur auf MAC-Adressen basiert, gilt dagegen nicht mehr als zeitgemäß, da MAC-Adressen sehr leicht ausgelesen und auf Systemen eingestellt werden könnten und so unberechtigte IT-Systeme zu leicht auch Zugang erhalten. Wenn Systeme die Netzzugangskontrolle nicht oder nur unzureichend unterstützen, ist für solche Systeme anstelle einer Netzzugangskontrolle die Nutzung eines eigenen Netzsegmentes empfehlenswert. Für die Verbindung zwischen RADIUS-Servern, Switches und Verzeichnisdiensten kommen Protokolle wie RadSec, IPsec oder LDAPS in Betracht. Die Verwendung nur einer einzigen Serverkonfigurationen (z.B. ein gemeinsamer RADIUS-Server für NAC und VPN) führt zu Komplexität und Angriffspunkten. Daher werden getrennte Systeme empfohlen. Dies gilt insbesondere bei unterschiedlichen Schutzklassen im LAN/WLAN oder Büro-/Produktionsnetz. Bei WLANs kann die Umsetzung in größeren Umgebungen mittels 802.1X (WPA3-Enterprise) und an kleineren Zugangspunkten oder Gastnetzen durch SAE (WPA3-Personal) erfolgen. Da es sich um eine automatisierte Sicherheitsrichtlinie handelt, ist hier auch die Anforderung zur Überwachung solcher Richtlinien anwendbar. Überwachungskriterien sind hier z.B. die Erreichbarkeit des RADIUS-Servers, die Antwortzeiten, die Last auf Access-Switches und andere Metriken. Für die Überwachung der Integrität ist insbesondere die Authentifizierung oder deren Fehlschlag relevant, z.B. viele abgelehnte Authentisierungen, plötzliche Deaktivierung eines Supplicants. Durch synthetische Anfragen an Testkonten kann die gesamte Authentisierungskette regelmäßig geprüft werden. Die Formulierung "im Einklang mit den Festlegungen des Identitäts- und Berechtigungsmanagements" bedeutet, dass die Authentifizierung so erfolgt, wie in der Praktik IDM festgelegt. Hierzu gehört insbesondere die Verwendung aktueller kryptographischer Verfahren, wie sie im Thema Kryptographie zu finden ist. | Q45: Interne Netzsegmente | R45: Konfigurationshistorie | S45: den Zugriff von IT-Systemen auf das Netzsegment | T45: G 0.18 – Fehlplanung oder fehlende Anpassung; G 0.23 – Unbefugtes Eindringen in IT-Systeme | U45: 3 | V45: 2 | W45: 2 | X45: 1 | Y45: 0
A46: ARCH.4.1 | B46: Netzzugangskontrolle | C46: ARCH.4.1 | D46: Standard-Anforderungen | E46: Architektur für Interne Netzsegmente SOLLTE den Zugriff von IT-Systemen auf das Netzsegment im Einklang mit den zugehörigen Anforderungen des Identitäts- und Berechtigungsmanagements authentifizieren. | H46: unbearbeitet | M46: Vertraulichkeit, Integrität | N46: INF.10.A6-UA.2; INF.14.A11-UA.4; NET.3.4.A14-UA.2; NET.3.4.A23-UA.4; NET.3.4.A7-UA.2; NET.3.4.A9-UA.2 | O46: equivalent-to; subset-of; intersects-with; intersects-with; equal-to; superset-of | P46: Unautorisierte Systeme könnten Ausgangspunkt von Angriffen sein oder zu unbeabsichtigten Störungen im Netz führen. Netzwerkzugangskontrolle (Network Access Control, NAC) bietet eine wirksame Möglichkeit, den Zugriff auf Netzwerke kontrolliert zu steuern, insbesondere in schützenswerten Bereichen wie Management-Netzen, Produktionssystemen oder Forschungsumgebungen. Die Auswahl der Netzbereiche für die Netzzugangskontrolle richtet sich nach dem Schutzbedarf oder Risikoprofil. Dabei empfiehlt sich zu dokumentieren, welche Zonen mit NAC abgesichert werden und warum andere bewusst nicht berücksichtigt werden (z.B. aufgrund technischer Einschränkungen oder fehlender Relevanz). Die Umsetzung kann (1) auf Zertifikaten basieren (X.509, EAP‑TLS or mTLS), (2) auf Zugangskonten basieren (IEEE 802.1X, RADIUS), (3) auf dynamischen Prüfungen basieren (z.B. Sicherheitspatches). Eine Authentifizierung, die nur auf MAC-Adressen basiert, gilt dagegen nicht mehr als zeitgemäß, da MAC-Adressen sehr leicht ausgelesen und auf Systemen eingestellt werden könnten und so unberechtigte IT-Systeme zu leicht auch Zugang erhalten. Wenn Systeme die Netzzugangskontrolle nicht oder nur unzureichend unterstützen, ist für solche Systeme anstelle einer Netzzugangskontrolle die Nutzung eines eigenen Netzsegmentes empfehlenswert. Für die Verbindung zwischen RADIUS-Servern, Switches und Verzeichnisdiensten kommen Protokolle wie RadSec, IPsec oder LDAPS in Betracht. Die Verwendung nur einer einzigen Serverkonfigurationen (z.B. ein gemeinsamer RADIUS-Server für NAC und VPN) führt zu Komplexität und Angriffspunkten. Daher werden getrennte Systeme empfohlen. Dies gilt insbesondere bei unterschiedlichen Schutzklassen im LAN/WLAN oder Büro-/Produktionsnetz. Bei WLANs kann die Umsetzung in größeren Umgebungen mittels 802.1X (WPA3-Enterprise) und an kleineren Zugangspunkten oder Gastnetzen durch SAE (WPA3-Personal) erfolgen. Da es sich um eine automatisierte Sicherheitsrichtlinie handelt, ist hier auch die Anforderung zur Überwachung solcher Richtlinien anwendbar. Überwachungskriterien sind hier z.B. die Erreichbarkeit des RADIUS-Servers, die Antwortzeiten, die Last auf Access-Switches und andere Metriken. Für die Überwachung der Integrität ist insbesondere die Authentifizierung oder deren Fehlschlag relevant, z.B. viele abgelehnte Authentisierungen, plötzliche Deaktivierung eines Supplicants. Durch synthetische Anfragen an Testkonten kann die gesamte Authentisierungskette regelmäßig geprüft werden. Die Formulierung "im Einklang mit den Festlegungen des Identitäts- und Berechtigungsmanagements" bedeutet, dass die Authentifizierung so erfolgt, wie in der Praktik IDM festgelegt. Hierzu gehört insbesondere die Verwendung aktueller kryptographischer Verfahren, wie sie im Thema Kryptographie zu finden ist. | Q46: Interne Netzsegmente | R46: Konfigurationshistorie | S46: den Zugriff von IT-Systemen auf das Netzsegment | T46: G 0.18 – Fehlplanung oder fehlende Anpassung; G 0.23 – Unbefugtes Eindringen in IT-Systeme | U46: 3 | V46: 2 | W46: 2 | X46: 1 | Y46: 0
A47: ARCH.4.1 | B47: Netzzugangskontrolle | C47: ARCH.4.1.1 | D47: Standard-Anforderungen | E47: Architektur für Interne Netzsegmente SOLLTE den Zugriff von IT-Systemen auf das Netzsegment anhand dynamischer Kriterien im Einklang mit den zugehörigen Anforderungen des Identitäts- und Berechtigungsmanagements authentifizieren. | H47: unbearbeitet | N47: NET.3.1.A21-UA.1; NET.3.4.A19-UA.1; NET.3.4.A9-UA.3; NET.3.4.A9-UA.4 | O47: subset-of; subset-of; subset-of; subset-of | P47: Bei der dynamischen Netzzugangskontrolle (Posturing oder Dynamic NAC) wird vor dem Netzzugang auch der Zustand des IT-Systems geprüft, z.B. der aktuelle Patchlevel des Systems oder von Erkennungssignaturen. Hierzu gehört auch die softwaredefinierte Netzzugangskontrolle, die dynamisch auf Aktivitäten des Systems oder aktuelle Threat Intelligence reagieren kann. Empfehlenswert ist es hierbei, die Konfiguration der Systeme automatisiert vorzunehmen, z.B. über eine automatische Supplicant-Konfiguration beim Rollout und die Zuweisung von Zertifikaten über Enrollment-Dienste. Die Formulierung "im Einklang mit den Festlegungen des Identitäts- und Berechtigungsmanagements" bedeutet, dass die Authentifizierung so erfolgt, wie in der Praktik IDM festgelegt. Hierzu gehört insbesondere die Verwendung aktueller kryptographischer Verfahren, wie sie im Thema Kryptographie zu finden ist. | Q47: Interne Netzsegmente | R47: Konfigurationshistorie | S47: den Zugriff von IT-Systemen auf das Netzsegment | T47: G 0.18 – Fehlplanung oder fehlende Anpassung; G 0.36 – Identitätsdiebstahl | U47: 4 | V47: 1 | W47: 1 | X47: 1 | Y47: 0
A48: ARCH.4.1 | B48: Netzzugangskontrolle | C48: ARCH.4.1.2 | D48: Anforderungen bei erhöhtem Schutzbedarf | E48: Architektur für Interne Netzsegmente KANN ein Quarantänenetz für nicht authentifizierte IT-Systeme installieren. | H48: unbearbeitet | N48: NET.1.1.A4-UA.4 | O48: superset-of | P48: Wenn Systeme aufgrund bestimmter Voraussetzungen sich nicht authentifizieren (z.B. installierte Sicherheitsupdates oder weil sie keine 802.1X-Anmeldung unterstützen), kann ein vollständiges blockieren aller Netzverbindungen die Verfügbarkeit erforderlicher Geschäftsprozesse unmöglich machen. Um IT-Systemen einen eingeschränkten Zugang zu Netzressourcen zu ermöglichen – etwa damit diese die Voraussetzungen durch den Download von Updates erfüllen können – kann ein Quarantänenetz eingerichtet werden, das z.B. Zugang zu bestimmten Downloadservern oder eine Meldung des Problems ermöglicht. | Q48: Interne Netzsegmente | R48: Konfigurationshistorie | S48: ein Quarantänenetz | T48: G 0.18 – Fehlplanung oder fehlende Anpassung | U48: 5 | V48: 1 | W48: 1 | X48: 1 | Y48: 0
A49: ARCH.4.2 | B49: Autorisiertes Routing | D49: Standard-Anforderungen | E49: Gesamt: | H49: =IF(OR(COUNTBLANK($H$50:$H$50)>0,COUNTIF($H$50:$H$50,"unbearbeitet")=COUNTA($H$50:$H$50)),"Bitte Teilanforderungen ausfüllen",IF(COUNTIF($H$50:$H$50,"zu klären")>0,"zu klären",IF(COUNTIF($H$50:$H$50,"entbehrlich")=COUNTA($H$50:$H$50),"entbehrlich",IF(COUNTIF($H$50:$H$50,"verwiesen")=COUNTA($H$50:$H$50),"verwiesen",IF(COUNTIF($H$50:$H$50,"nein")+COUNTIF($H$50:$H$50,"entbehrlich")=COUNTA($H$50:$H$50),"nein",IF(COUNTIF($H$50:$H$50,"ja")+COUNTIF($H$50:$H$50,"entbehrlich")+COUNTIF($H$50:$H$50,"verwiesen")=COUNTA($H$50:$H$50),"ja","teilweise")))))) -> Bitte Teilanforderungen ausfüllen | M49: Integrität | N49: APP.5.4.A13-UA.1; NET.3.1.A1-UA.2; NET.3.1.A10-UA.2 | O49: subset-of; intersects-with; intersects-with | P49: Dient der Kontrolle von Netzarchitekturen, um unbeabsichtigte oder böswillige Änderungen zu verhindern. Ohne eine solche Freigabe könnte ein Angreifer durch unbemerkte Manipulation von Routing-Einträgen den Datenverkehr umleiten, abhören oder blockieren; auch ein ungeschulter Administrator könnte versehentlich falsche Routen konfigurieren, wodurch kritische Dienste ausfallen könnten. Die Autorisierung kann sicherstellen, dass jede Änderung nachvollziehbar geprüft, dokumentiert und nur nach sachgerechter Bewertung umgesetzt wird, wodurch die Integrität und Verfügbarkeit der Netze erhöht werden kann. Im konkreten Kontext bedeutet „Routing-Verbindungen“ die Konfiguration von Pfaden, über die Datenpakete zwischen Netzsegmenten oder über Gateways weitergeleitet werden. „Autorisieren“ bedeutet hier die formale Freigabe nach einer sachlichen und fachlichen Prüfung, typischerweise durch Rollen wie (1) Netzwerkarchitekt, (2) IT-Sicherheitsbeauftragter oder (3) Leiter IT-Betrieb. Eine Institution kann dies umsetzen, indem sie (1) eine dokumentierte Freigabeprozedur für alle Routing-Änderungen etabliert, (2) Änderungen technisch über ein Ticket- oder Change-Management-System prüfen und protokollieren lässt, (3) rollenbasierte Zugriffsrechte in Routern und Firewalls so einschränken kann, dass nur autorisierte Personen Konfigurationsänderungen durchführen, und (4) automatisierte Plausibilitätsprüfungen oder Peer-Reviews nutzen kann, um fehlerhafte oder unsichere Routen frühzeitig zu erkennen. Die Autorisierung kann entweder einzelne Routen (z.B. für Netz A zwischen Router B und C), als auch bestimmte Routing-Regeln (z.B. Default-Routing über die zentrale Firewall) autorisieren. Sinnvoll ist es dabei das Prinzip "so allgemein wie für den Betrieb nötig, so spezifisch wie für die Sicherheit möglich" als Faustregel anzuwenden. Bei der Verwendung dynamischer Routing-Algorithmen kann die Anforderung umgesetzt werden, indem eingeschränkte Bereiche freigegeben werden, z.B. "dynamisches Routing im Bereich 10.x.x.x)". | Q49: Netze | R49: Konfigurationshistorie | S49: Routing-Verbindungen | T49: G 0.18 – Fehlplanung oder fehlende Anpassung; G 0.22 – Manipulation von Informationen | U49: 3 | V49: 1 | W49: 2 | X49: 1 | Y49: 1
A50: ARCH.4.2 | B50: Autorisiertes Routing | C50: ARCH.4.2 | D50: Standard-Anforderungen | E50: Architektur für Netze SOLLTE Routing-Verbindungen durch eine zuständige Person oder Rolle autorisieren. | H50: unbearbeitet | M50: Integrität | N50: APP.5.4.A13-UA.1; NET.3.1.A1-UA.2; NET.3.1.A10-UA.2 | O50: subset-of; intersects-with; intersects-with | P50: Dient der Kontrolle von Netzarchitekturen, um unbeabsichtigte oder böswillige Änderungen zu verhindern. Ohne eine solche Freigabe könnte ein Angreifer durch unbemerkte Manipulation von Routing-Einträgen den Datenverkehr umleiten, abhören oder blockieren; auch ein ungeschulter Administrator könnte versehentlich falsche Routen konfigurieren, wodurch kritische Dienste ausfallen könnten. Die Autorisierung kann sicherstellen, dass jede Änderung nachvollziehbar geprüft, dokumentiert und nur nach sachgerechter Bewertung umgesetzt wird, wodurch die Integrität und Verfügbarkeit der Netze erhöht werden kann. Im konkreten Kontext bedeutet „Routing-Verbindungen“ die Konfiguration von Pfaden, über die Datenpakete zwischen Netzsegmenten oder über Gateways weitergeleitet werden. „Autorisieren“ bedeutet hier die formale Freigabe nach einer sachlichen und fachlichen Prüfung, typischerweise durch Rollen wie (1) Netzwerkarchitekt, (2) IT-Sicherheitsbeauftragter oder (3) Leiter IT-Betrieb. Eine Institution kann dies umsetzen, indem sie (1) eine dokumentierte Freigabeprozedur für alle Routing-Änderungen etabliert, (2) Änderungen technisch über ein Ticket- oder Change-Management-System prüfen und protokollieren lässt, (3) rollenbasierte Zugriffsrechte in Routern und Firewalls so einschränken kann, dass nur autorisierte Personen Konfigurationsänderungen durchführen, und (4) automatisierte Plausibilitätsprüfungen oder Peer-Reviews nutzen kann, um fehlerhafte oder unsichere Routen frühzeitig zu erkennen. Die Autorisierung kann entweder einzelne Routen (z.B. für Netz A zwischen Router B und C), als auch bestimmte Routing-Regeln (z.B. Default-Routing über die zentrale Firewall) autorisieren. Sinnvoll ist es dabei das Prinzip "so allgemein wie für den Betrieb nötig, so spezifisch wie für die Sicherheit möglich" als Faustregel anzuwenden. Bei der Verwendung dynamischer Routing-Algorithmen kann die Anforderung umgesetzt werden, indem eingeschränkte Bereiche freigegeben werden, z.B. "dynamisches Routing im Bereich 10.x.x.x)". | Q50: Netze | R50: Konfigurationshistorie | S50: Routing-Verbindungen | T50: G 0.18 – Fehlplanung oder fehlende Anpassung; G 0.22 – Manipulation von Informationen | U50: 3 | V50: 1 | W50: 2 | X50: 1 | Y50: 1
A51: ARCH.4.3 | B51: Authentifizierung von Routingprotokollen | D51: Standard-Anforderungen | E51: Gesamt: | H51: =IF(OR(COUNTBLANK($H$52:$H$52)>0,COUNTIF($H$52:$H$52,"unbearbeitet")=COUNTA($H$52:$H$52)),"Bitte Teilanforderungen ausfüllen",IF(COUNTIF($H$52:$H$52,"zu klären")>0,"zu klären",IF(COUNTIF($H$52:$H$52,"entbehrlich")=COUNTA($H$52:$H$52),"entbehrlich",IF(COUNTIF($H$52:$H$52,"verwiesen")=COUNTA($H$52:$H$52),"verwiesen",IF(COUNTIF($H$52:$H$52,"nein")+COUNTIF($H$52:$H$52,"entbehrlich")=COUNTA($H$52:$H$52),"nein",IF(COUNTIF($H$52:$H$52,"ja")+COUNTIF($H$52:$H$52,"entbehrlich")+COUNTIF($H$52:$H$52,"verwiesen")=COUNTA($H$52:$H$52),"ja","teilweise")))))) -> Bitte Teilanforderungen ausfüllen | M51: Vertraulichkeit, Integrität | N51: NET.3.1.A20-UA.1 | O51: equal-to | P51: Hierzu zählt z.B. die Authentifizierung von BGP/OSPF-Sitzungen zur Verhinderung von Route Hijacking, BGP origin validation with RPKI oder OSPF/ISIS/BGP MD5 or TTL+hMAC authentication. Die Formulierung "im Einklang mit den Festlegungen des Identitäts- und Berechtigungsmanagements" bedeutet, dass die Authentifizierung so erfolgt, wie in der Praktik IDM festgelegt. Hierzu gehört insbesondere die Verwendung aktueller kryptographischer Verfahren, wie sie im Thema Kryptographie zu finden ist. | Q51: Netze | R51: Konfigurationshistorie | S51: Änderungen an Routing-Tabellen | T51: G 0.18 – Fehlplanung oder fehlende Anpassung; G 0.23 – Unbefugtes Eindringen in IT-Systeme | U51: 3 | V51: 2 | W51: 2 | X51: 1 | Y51: 0
A52: ARCH.4.3 | B52: Authentifizierung von Routingprotokollen | C52: ARCH.4.3 | D52: Standard-Anforderungen | E52: Architektur für Netze SOLLTE Änderungen an Routing-Tabellen im Einklang mit den zugehörigen Anforderungen des Identitäts- und Berechtigungsmanagements authentifizieren. | H52: unbearbeitet | M52: Vertraulichkeit, Integrität | N52: NET.3.1.A20-UA.1 | O52: equal-to | P52: Hierzu zählt z.B. die Authentifizierung von BGP/OSPF-Sitzungen zur Verhinderung von Route Hijacking, BGP origin validation with RPKI oder OSPF/ISIS/BGP MD5 or TTL+hMAC authentication. Die Formulierung "im Einklang mit den Festlegungen des Identitäts- und Berechtigungsmanagements" bedeutet, dass die Authentifizierung so erfolgt, wie in der Praktik IDM festgelegt. Hierzu gehört insbesondere die Verwendung aktueller kryptographischer Verfahren, wie sie im Thema Kryptographie zu finden ist. | Q52: Netze | R52: Konfigurationshistorie | S52: Änderungen an Routing-Tabellen | T52: G 0.18 – Fehlplanung oder fehlende Anpassung; G 0.23 – Unbefugtes Eindringen in IT-Systeme | U52: 3 | V52: 2 | W52: 2 | X52: 1 | Y52: 0
A53: ARCH.5.1 | B53: Einschränkung und Inspektion von Verbindungen | D53: Standard-Anforderungen | E53: Gesamt: | H53: =IF(OR(COUNTBLANK($H$54:$H$70)>0,COUNTIF($H$54:$H$70,"unbearbeitet")=COUNTA($H$54:$H$70)),"Bitte Teilanforderungen ausfüllen",IF(COUNTIF($H$54:$H$70,"zu klären")>0,"zu klären",IF(COUNTIF($H$54:$H$70,"entbehrlich")=COUNTA($H$54:$H$70),"entbehrlich",IF(COUNTIF($H$54:$H$70,"verwiesen")=COUNTA($H$54:$H$70),"verwiesen",IF(COUNTIF($H$54:$H$70,"nein")+COUNTIF($H$54:$H$70,"entbehrlich")=COUNTA($H$54:$H$70),"nein",IF(COUNTIF($H$54:$H$70,"ja")+COUNTIF($H$54:$H$70,"entbehrlich")+COUNTIF($H$54:$H$70,"verwiesen")=COUNTA($H$54:$H$70),"ja","teilweise")))))) -> Bitte Teilanforderungen ausfüllen | M53: Vertraulichkeit | N53: IND.1.A8-UA.2; IND.2.4.A1-UA.5; INF.10.A6-UA.1; INF.10.A6-UA.6; INF.14.A11-UA.1; NET.1.1.A19-UA.2; NET.3.2.A2-UA.2; NET.3.2.A2-UA.3; NET.3.4.A9-UA.2; OPS.1.1.7.A17-UA.1; SYS.1.5.A4-UA.2 | O53: subset-of; subset-of; subset-of; subset-of; subset-of; subset-of; subset-of; subset-of; subset-of; subset-of; subset-of | P53: Über Netverbindungen können unbeabsichtigte Verbindungen aufgebaut werden oder netzbasierte Angriffe über das Internet gegen die Institution erfolgen. Unerwünschter Datenverkehr nach außen können z.B. private IP-Adressen (RFC 1918 leakage), Multicasting, TCP/UDP Ports für veraltete, angreifbare Protokolle oder ICMP-Verkehr sein. Die Beschränkung der Verbindung zwischen IT-Systemen kann sowohl durch zustandsbehaftete Paketfilter, als auch mit Application Layer Gateways umgesetzt werden. Empfehlenswert ist eine Kombination aus Allowlisting, IP-Reputationslisten, Deep Packet Inspection und Durchsatzratenbegrenzung. Hierbei können Verbindungen auch nach Kategorien autorisiert werden (z.B. anhand von IP-Subnetzen oder Voraussetzungen wie per Zertifikat authentifzierten IT-Systemen). Damit dabei keine unnötigen Verbindungen zugelassen werden, ist es wichtig, die Kategorisierung möglich genau zu wählen (z.B. möglichst einzelne Subnetze statt des ganzen Netzes oder nur bestimmte Ports oder Anwendungen zuzulassen). | Q53: Netze | R53: Firewallregeln | S53: Verbindungen zwischen IT-Systemen | T53: G 0.23 – Unbefugtes Eindringen in IT-Systeme; G 0.14 – Ausspähen von Informationen (Spionage); G 0.30 – Unberechtigte Nutzung oder Administration von Geräten und Systemen | U53: 2 | V53: 2 | W53: 1 | X53: 1 | Y53: 1
A54: ARCH.5.1 | B54: Einschränkung und Inspektion von Verbindungen | C54: ARCH.5.1 | D54: Standard-Anforderungen | E54: Architektur für Netze SOLLTE Verbindungen zwischen IT-Systemen einschränken. | H54: unbearbeitet | M54: Vertraulichkeit | N54: IND.1.A8-UA.2; IND.2.4.A1-UA.5; INF.10.A6-UA.1; INF.10.A6-UA.6; INF.14.A11-UA.1; NET.1.1.A19-UA.2; NET.3.2.A2-UA.2; NET.3.2.A2-UA.3; NET.3.4.A9-UA.2; OPS.1.1.7.A17-UA.1; SYS.1.5.A4-UA.2 | O54: subset-of; subset-of; subset-of; subset-of; subset-of; subset-of; subset-of; subset-of; subset-of; subset-of; subset-of | P54: Über Netverbindungen können unbeabsichtigte Verbindungen aufgebaut werden oder netzbasierte Angriffe über das Internet gegen die Institution erfolgen. Unerwünschter Datenverkehr nach außen können z.B. private IP-Adressen (RFC 1918 leakage), Multicasting, TCP/UDP Ports für veraltete, angreifbare Protokolle oder ICMP-Verkehr sein. Die Beschränkung der Verbindung zwischen IT-Systemen kann sowohl durch zustandsbehaftete Paketfilter, als auch mit Application Layer Gateways umgesetzt werden. Empfehlenswert ist eine Kombination aus Allowlisting, IP-Reputationslisten, Deep Packet Inspection und Durchsatzratenbegrenzung. Hierbei können Verbindungen auch nach Kategorien autorisiert werden (z.B. anhand von IP-Subnetzen oder Voraussetzungen wie per Zertifikat authentifzierten IT-Systemen). Damit dabei keine unnötigen Verbindungen zugelassen werden, ist es wichtig, die Kategorisierung möglich genau zu wählen (z.B. möglichst einzelne Subnetze statt des ganzen Netzes oder nur bestimmte Ports oder Anwendungen zuzulassen). | Q54: Netze | R54: Firewallregeln | S54: Verbindungen zwischen IT-Systemen | T54: G 0.23 – Unbefugtes Eindringen in IT-Systeme; G 0.14 – Ausspähen von Informationen (Spionage); G 0.30 – Unberechtigte Nutzung oder Administration von Geräten und Systemen | U54: 2 | V54: 2 | W54: 1 | X54: 1 | Y54: 1
A55: ARCH.5.1 | B55: Einschränkung und Inspektion von Verbindungen | C55: ARCH.5.1.1 | D55: Standard-Anforderungen | E55: Architektur für Netze SOLLTE anfällige Netzwerkprotokolle blockieren. | H55: unbearbeitet | M55: Vertraulichkeit, Integrität | N55: NET.3.4.A24-UA.1; OPS.1.2.5.A8-UA.1; SYS.1.9.A17-UA.2; SYS.2.2.3.A9-UA.2 | O55: equivalent-to; equal-to; equivalent-to; equivalent-to | P55: Anfällig sind Netzprotokolle, wenn sie veraltete oder gar keine Algorithmen zur Verschlüsselung oder Integritätsprüfung verwenden. Hierzu gehören Protokolle wie Telnet, SMB v1, SNMP v1/v2c. Für aktuelle Verschlüsselungsalgorithmen siehe BSI TR 02102. | Q55: Netze | R55: Firewallregeln | S55: anfällige Netzwerkprotokolle | T55: G 0.23 – Unbefugtes Eindringen in IT-Systeme | U55: 3 | V55: 2 | W55: 2 | X55: 1 | Y55: 0
A56: ARCH.5.1 | B56: Einschränkung und Inspektion von Verbindungen | C56: ARCH.5.1.2 | D56: Standard-Anforderungen | E56: Architektur für Netze SOLLTE bekannte netzbasierte Angriffsmethoden blockieren. | H56: unbearbeitet | N56: NET.1.1.A8-UA.2; NET.3.1.A15-UA.1; NET.3.1.A16-UA.1; NET.3.1.A19-UA.1; NET.3.1.A5-UA.1; NET.3.2.A10-UA.1; NET.3.2.A19-UA.1 | O56: subset-of; subset-of; subset-of; subset-of; subset-of; subset-of; subset-of | P56: Netzbasierte Angriffe verwenden Netzwerktechnologien (typischerweise auf OSI Layer 2-3), z.B. Fragmentierungsangriffe. Beispiele für mögliche Maßnahmen sind DHCP snooping, ARP/Dynamic ARP Inspection, IP-source guard, BPDU guard, root guard, port-security (sticky MAC). | Q56: Netze | R56: Firewallregeln | S56: bekannte netzbasierte Angriffsmethoden | T56: G 0.23 – Unbefugtes Eindringen in IT-Systeme; G 0.40 – Verhinderung von Diensten (Denial of Service) | U56: 4 | V56: 1 | W56: 1 | X56: 1 | Y56: 0
A57: ARCH.5.1 | B57: Einschränkung und Inspektion von Verbindungen | C57: ARCH.5.1.3 | D57: Standard-Anforderungen | E57: Architektur für Netze SOLLTE bekannte TCP-basierte Angriffsmethoden blockieren. | H57: unbearbeitet | N57: APP.3.2.A18-UA.2; NET.3.1.A17-UA.1; NET.3.2.A19-UA.1; NET.3.2.A19-UA.3; NET.3.2.A3-UA.2; OPS.1.2.5.A20-UA.2 | O57: superset-of; subset-of; subset-of; subset-of; subset-of; subset-of | P57: TCP ist das am meisten verwendete Protokoll für die zuverlässige Datenübertragung. Durch TCP-basierte Angriffe können IT-Systeme gehackt oder Daten unbemerkt ausgeleitet werden. Beispiele sind TCP Session Hijacking (ACK-number guessing), Overlapping-Segment Attacks, TCP Reset (RST) Injection, Xmas-tree Scanning. Die Anforderung kann durch Blockieren solcher Verbindungen oder nur bestimmter Mechanismen umgesetzt werden. | Q57: Netze | R57: Firewallregeln | S57: bekannte TCP-basierte Angriffsmethoden | T57: G 0.23 – Unbefugtes Eindringen in IT-Systeme; G 0.40 – Verhinderung von Diensten (Denial of Service) | U57: 4 | V57: 1 | W57: 1 | X57: 1 | Y57: 0
A58: ARCH.5.1 | B58: Einschränkung und Inspektion von Verbindungen | C58: ARCH.5.1.4 | D58: Standard-Anforderungen | E58: Architektur für Netze SOLLTE bekannte UDP-basierte Angriffsmethoden blockieren. | H58: unbearbeitet | N58: APP.3.2.A18-UA.2; NET.1.1.A8-UA.2; NET.3.1.A17-UA.1; NET.3.2.A19-UA.1; NET.3.2.A19-UA.2; NET.3.2.A3-UA.4 | O58: intersects-with; superset-of; intersects-with; subset-of; subset-of; equivalent-to | P58: UDP-basierte Angriffsmethoden (englisch: known UDP-based attack vectors) sind hierbei Techniken zu verstehen, die das User Datagram Protocol (UDP) ausnutzen. UDP ist das am meisten verwendete Protokoll für die Übertragung von Datenstreams. Aufgrund seiner verbindungslosen Eigenschaft ermöglicht UDP eine sehr schnelle Datenübertragung und wird daher oft für zeitkritische Anwendungen wie Videostreaming, VoIP oder DNS-Anfragen verwendet. Genau diese Eigenschaft macht es jedoch anfällig für Missbrauch, da die Absenderadresse leicht gefälscht werden kann (IP-Spoofing). Beispiele für Angriffe sind Sequence Number Guessing, DHCP Starvation und UDP Hole-Punching Abuse. Die Anforderung kann durch Blockieren solcher Verbindungen oder nur bestimmter Mechanismen umgesetzt werden. | Q58: Netze | R58: Firewallregeln | S58: bekannte UDP-basierte Angriffsmethoden | T58: G 0.23 – Unbefugtes Eindringen in IT-Systeme; G 0.40 – Verhinderung von Diensten (Denial of Service) | U58: 4 | V58: 1 | W58: 1 | X58: 1 | Y58: 0
A59: ARCH.5.1 | B59: Einschränkung und Inspektion von Verbindungen | C59: ARCH.5.1.5 | D59: Standard-Anforderungen | E59: Architektur für Externe Netzanschlüsse SOLLTE Split Tunneling blockieren. | H59: unbearbeitet | M59: Vertraulichkeit | N59: INF.10.A6-UA.6; NET.3.3.A10-UA.1; NET.3.3.A11-UA.1 | O59: subset-of; intersects-with; intersects-with | P59: Um eine durchgehende Kontrolle und Absicherung des Netzverkehrs zu gewährleisten, muss verhindert werden, dass IT-Clients während einer aktiven Verbindung zum internen Netz gleichzeitig ungeschützten Zugriff auf das öffentliche Internet oder andere Netzwerke haben. Dies schließt sogenannte „Split Tunneling“-Konfigurationen aus, bei denen nur ausgewählter Datenverkehr über das VPN geleitet wird, während anderer Datenverkehr (z. B. Webzugriffe) über das lokale Netzwerk oder die Internetverbindung des Clients erfolgt. | Q59: Externe Netzanschlüsse | R59: Firewallregeln | S59: Split Tunneling | T59: G 0.23 – Unbefugtes Eindringen in IT-Systeme; G 0.14 – Ausspähen von Informationen (Spionage) | U59: 3 | V59: 2 | W59: 1 | X59: 1 | Y59: 0
A60: ARCH.5.1 | B60: Einschränkung und Inspektion von Verbindungen | C60: ARCH.5.1.6 | D60: Standard-Anforderungen | E60: Architektur für Externe Netzanschlüsse SOLLTE Verbindungen zu Management-Schnittstellen blockieren. | H60: unbearbeitet | N60: NET.1.1.A11-UA.6; NET.1.1.A21-UA.4; NET.1.2.A21-UA.1; NET.3.1.A13-UA.2; NET.3.1.A4-UA.1; NET.3.1.A4-UA.2; NET.3.1.A4-UA.5; NET.3.2.A18-UA.2; NET.3.2.A2-UA.2; NET.3.2.A6-UA.1; OPS.1.1.2.A16-UA.1; OPS.1.2.5.A25-UA.1; SYS.1.5.A5-UA.1 | O60: superset-of; superset-of; subset-of; subset-of; superset-of; equivalent-to; superset-of; subset-of; superset-of; superset-of; intersects-with; subset-of; equivalent-to | P60: Zum Internet offene Management-Schnittstellen werden von Angreifern durch Scans leicht gefunden und sind häufig Ziel von Angriffen. Deshalb ist es sinnvoll, alle eingehenden Verbindungen zu Management-Schnittstellen aus externen Netzen zu blockieren, einschließlich der Verwaltung von VPN- und Firewallsystemen selbst. Wenn eine Administration dieser Systeme aus der Ferne erforderlich ist, so kann dieser Zugriff stattdessen über ein VPN in das interne Netz hergestellt werden, wobei auch hiermit ein erhöhten Risiko für Angriffe einhergeht. | Q60: Externe Netzanschlüsse | R60: Firewallregeln | S60: Verbindungen zu Management-Schnittstellen | T60: G 0.23 – Unbefugtes Eindringen in IT-Systeme; G 0.40 – Verhinderung von Diensten (Denial of Service) | U60: 3 | V60: 1 | W60: 1 | X60: 1 | Y60: 0
A61: ARCH.5.1 | B61: Einschränkung und Inspektion von Verbindungen | C61: ARCH.5.1.7 | D61: Standard-Anforderungen | E61: Architektur für Externe Netzanschlüsse SOLLTE dynamische Routingprotokolle blockieren. | H61: unbearbeitet | M61: Vertraulichkeit, Integrität | N61: NET.3.1.A20-UA.3; NET.3.1.A20-UA.5; NET.3.2.A2-UA.2; NET.3.2.A2-UA.3; NET.3.2.A8-UA.1 | O61: intersects-with; subset-of; intersects-with; intersects-with; subset-of | P61: Dynamische Routingprotokolle könnten versehentlich oder durch Angriffe unerwünschte Verbindungen ermöglichen. An den Übergangen zu externen Netzen sind statische Default-Routen deshalb die bessere Alternative. | Q61: Externe Netzanschlüsse | R61: Firewallregeln | S61: dynamische Routingprotokolle | T61: G 0.23 – Unbefugtes Eindringen in IT-Systeme; G 0.30 – Unberechtigte Nutzung oder Administration von Geräten und Systemen; G 0.43 – Einspielen von Nachrichten | U61: 3 | V61: 2 | W61: 2 | X61: 1 | Y61: 1
A62: ARCH.5.1 | B62: Einschränkung und Inspektion von Verbindungen | C62: ARCH.5.1.8 | D62: Standard-Anforderungen | E62: Architektur für Externe Netzanschlüsse SOLLTE den Inhalt unverschlüsselter und verschlüsselter Verbindungen basierend auf der Art des Inhalts einschränken. | H62: unbearbeitet | M62: Vertraulichkeit, Integrität | N62: DER.1.A10-UA.1; NET.1.1.A12-UA.1; NET.3.2.A16-UA.3; NET.3.2.A16-UA.4; NET.3.2.A20-UA.1; NET.3.2.A21-UA.1; NET.3.2.A28-UA.2; NET.3.2.A28-UA.3; OPS.1.1.7.A17-UA.1; SYS.1.7.A6-UA.5; SYS.3.2.1.A28-UA.3 | O62: subset-of; intersects-with; subset-of; subset-of; subset-of; subset-of; subset-of; intersects-with; intersects-with; intersects-with; intersects-with | P62: Verschlüsselte Verbindungen wie VoIP über TLS oder HTTPS-Anfragen können über Sicherheitsproxies oder die Inspektion auf den Endstellen der Verbindungen inspiziert werden. Ein Proxy bzw. Proxy-Server ist ein Vermittler im Netz, der zwischen dem Client und einer Netzressource, wie einer Webseite, fungiert. Er dient als Brücke zwischen dem Client und dem Server, wobei Anfragen und Antworten stellvertretend abgewickelt werden. Proxys können Datenverkehr filtern, blockieren, oder auch speichern, um die Netzwerkleistung zu optimieren. Systeme zur Filterung von Webinhalten gehören zu den häufigsten Arten von Proxyservern, die zur Vermittlung des Internetzugangs eingesetzt werden. Diese Server können TCP-Sitzungen protokollieren und die Zugriffskontrolle durch Blockieren bestimmter URLs, IP-Adressen oder Domänennamen erzwingen. Institutionen können Web-Proxys mit benutzerdefinierten Erlaubnis- und Sperrlisten konfigurieren, um den Zugriff auf der Grundlage von Richtlinien zu regeln. Es ist jedoch zu beachten, dass Proxyserver die Nutzung virtueller privater Netzwerke (VPN) beeinträchtigen und je nach Implementierung Risiken wie Man-in-the-Middle-Angriffe (MitM) mit sich bringen können. Beispiel-Implementierungen sind Squid, Nginx, Privoxy. | Q62: Externe Netzanschlüsse | R62: Firewallregeln | S62: den Inhalt unverschlüsselter und verschlüsselter Verbindungen | T62: G 0.23 – Unbefugtes Eindringen in IT-Systeme; G 0.39 – Schadprogramme; G 0.30 – Unberechtigte Nutzung oder Administration von Geräten und Systemen | U62: 4 | V62: 2 | W62: 2 | X62: 1 | Y62: 1
A63: ARCH.5.1 | B63: Einschränkung und Inspektion von Verbindungen | C63: ARCH.5.1.9 | D63: Standard-Anforderungen | E63: Architektur für Externe Netzanschlüsse SOLLTE unerwünschte Inhalte in DNS-Verbindungen einschränken. | H63: unbearbeitet | M63: Vertraulichkeit | N63: APP.1.2.A11-UA.3; NET.3.2.A2-UA.3; NET.3.2.A2-UA.5; NET.3.2.A28-UA.3 | O63: intersects-with; intersects-with; intersects-with; intersects-with | P63: Unerwünschte Inhalte sind DNS-Anfragen oder -Antworten, die für Geschäftsprozesse unnötige oder sogar schädliche Daten enthalten, z.B. Verbindungen zu bekannten Malware-Domains oder zu Werbe- oder Telemetriediensten. Dies kann entweder nach dem Allowlist- oder Denylist-Ansatz erfolgen. Listen bekannter schädlicher Domains können über Threat Intelligence-Feeds oder spezielle DNS-Lösungen wie Pihole bezogen werden. | Q63: Externe Netzanschlüsse | R63: Firewallregeln | S63: unerwünschte Inhalte in DNS-Verbindungen | T63: G 0.23 – Unbefugtes Eindringen in IT-Systeme; G 0.14 – Ausspähen von Informationen (Spionage); G 0.39 – Schadprogramme | U63: 3 | V63: 2 | W63: 1 | X63: 1 | Y63: 0
A64: ARCH.5.1 | B64: Einschränkung und Inspektion von Verbindungen | C64: ARCH.5.1.10 | D64: Standard-Anforderungen | E64: Architektur für Externe Netzanschlüsse SOLLTE den Zugriff auf Webinhalte anhand von Kriterien einschränken. | H64: unbearbeitet | M64: Vertraulichkeit | N64: APP.1.2.A7-UA.1; NET.3.2.A28-UA.1; NET.3.2.A28-UA.3; SYS.3.2.1.A28-UA.1; SYS.3.2.1.A28-UA.3 | O64: intersects-with; subset-of; subset-of; subset-of; subset-of | P64: Das World Wide Web ist für zahlreiche Geschäftsprozesse essenziell. Andererseits wird das Web von Angreifern auch für die Verbreitung von illegalen Inhalten, Schadprogrammen oder Phishing verwendet. Durch unkontrollierten Webzugriff könnten etwa Schadcode, Phishing oder Datenabfluss in die Institution gelangen. Kriterien meint hier die festgelegten Maßstäbe, nach denen externe Verbindungen zu Webinhalten gefiltert oder eingeschränkt werden. Im Fachjargon spricht man von filtering criteria oder access control policies. Solche Kriterien können beispielsweise Inhaltskategorien (z. B. Glücksspiel, soziale Netzwerke, Streaming), Reputationsbewertungen von Domains (z. B. „malicious“ oder „suspicious“ laut Threat-Intelligence-Feeds), oder technische Eigenschaften (z. B. bekannte IP-Ranges, Länderzugehörigkeit, verwendete Protokolle/Ports, Signaturen) sein. Sinnvoll ist eine Kombination verschiedener Kriterien. Die Anforderung kann über Filterung im Browser, auf Systemen oder an Netzgrenzen umgesetzt werden (z.B. durch Firewalls, Sicherheitsproxies oder VPN-Gateways). | Q64: Externe Netzanschlüsse | R64: Firewallregeln | S64: den Zugriff auf Webinhalte | T64: G 0.39 – Schadprogramme; G 0.28 – Software-Schwachstellen oder -Fehler; G 0.14 – Ausspähen von Informationen (Spionage); G 0.23 – Unbefugtes Eindringen in IT-Systeme | U64: 2 | V64: 2 | W64: 1 | X64: 1 | Y64: 0
A65: ARCH.5.1 | B65: Einschränkung und Inspektion von Verbindungen | C65: ARCH.5.1.10.1 | D65: Standard-Anforderungen | E65: Architektur für Externe Netzanschlüsse SOLLTE bekannte schädliche Inhalte einschränken. | H65: unbearbeitet | M65: Vertraulichkeit | N65: APP.1.2.A11-UA.1; APP.1.2.A11-UA.3; IND.2.1.A16-UA.1; NET.3.2.A28-UA.3; NET.3.4.A15-UA.3 | O65: subset-of; equal-to; superset-of; subset-of; intersects-with | P65: Hierzu gehören beispielsweise Schadprogramme, Phishing, Malware Command & Control Server. Zur Einschränkung kann auf öffentlich verfügbare Sperrlisten für solche Webseiten, auf Filtersysteme spezialisierter Hersteller von Firewalls und ähnlichen Systemen oder auf Daten aus der Threat Intelligence zurückgegriffen werden. | Q65: Externe Netzanschlüsse | R65: Firewallregeln | S65: bekannte schädliche Inhalte | T65: G 0.39 – Schadprogramme; G 0.28 – Software-Schwachstellen oder -Fehler; G 0.14 – Ausspähen von Informationen (Spionage); G 0.23 – Unbefugtes Eindringen in IT-Systeme | U65: 2 | V65: 2 | W65: 1 | X65: 1 | Y65: 0
A66: ARCH.5.1 | B66: Einschränkung und Inspektion von Verbindungen | C66: ARCH.5.1.10.2 | D66: Standard-Anforderungen | E66: Architektur für Externe Netzanschlüsse SOLLTE bekannte illegale Inhalte einschränken. | H66: unbearbeitet | M66: Vertraulichkeit | N66: APP.1.2.A11-UA.1; APP.1.2.A11-UA.3; NET.3.2.A28-UA.3 | O66: intersects-with; superset-of; intersects-with | P66: Gerade bei größeren Webdiensten kann es vorkommen, dass hierüber immer wieder vereinzelt illegale Inhalte verbreitet werden, obwohl der Dienst selbst von einer legitimen Institution betrieben wird. In solchen Fällen empfiehlt es sich, die Filterung möglich passgenau vorzunehmen (also soweit möglich nur bestimmte Seiten, Seitenbereiche oder Subdomains zu filtern) und den Anbieter über die illegalen Inhalte zu informieren. | Q66: Externe Netzanschlüsse | R66: Firewallregeln | S66: bekannte illegale Inhalte | T66: G 0.39 – Schadprogramme; G 0.28 – Software-Schwachstellen oder -Fehler; G 0.14 – Ausspähen von Informationen (Spionage); G 0.23 – Unbefugtes Eindringen in IT-Systeme | U66: 2 | V66: 2 | W66: 1 | X66: 1 | Y66: 0
A67: ARCH.5.1 | B67: Einschränkung und Inspektion von Verbindungen | C67: ARCH.5.1.10.3 | D67: Standard-Anforderungen | E67: Architektur für Externe Netzanschlüsse SOLLTE Speicherdienste einschränken. | H67: unbearbeitet | M67: Vertraulichkeit | N67: NET.3.4.A14-UA.2; SYS.2.1.A24-UA.1 | O67: intersects-with; superset-of | P67: Ausnahmen können sinnvoll sein, wenn es nach den Geschäftsprozessen erforderlich ist, die Daten öffentlich zur Verfügung zu stellen oder diese mit anderen Institutionen über den Speicherdienst auszutauschen. | Q67: Externe Netzanschlüsse | R67: Firewallregeln | S67: Speicherdienste | T67: G 0.39 – Schadprogramme; G 0.28 – Software-Schwachstellen oder -Fehler; G 0.14 – Ausspähen von Informationen (Spionage); G 0.23 – Unbefugtes Eindringen in IT-Systeme | U67: 3 | V67: 2 | W67: 1 | X67: 1 | Y67: 0
A68: ARCH.5.1 | B68: Einschränkung und Inspektion von Verbindungen | C68: ARCH.5.1.11 | D68: Standard-Anforderungen | E68: Architektur für Externe Netzanschlüsse SOLLTE eine P-A-P-Struktur für eingehende und ausgehende Verbindungen installieren. | H68: unbearbeitet | M68: Vertraulichkeit, Verfügbarkeit | N68: APP.3.6.A16-UA.1; NET.1.1.A18-UA.1; NET.1.1.A18-UA.10; NET.1.1.A18-UA.2; NET.1.1.A4-UA.7; NET.3.2.A16-UA.1; NET.3.2.A16-UA.3; NET.3.2.A16-UA.4 | O68: subset-of; superset-of; subset-of; subset-of; superset-of; equal-to; subset-of; subset-of | P68: Die P-A-P-Struktur besteht aus 2 Paketfiltern (P) und einem Filter auf Anwendungsebene (A), die durch Hardware getrennt sind und alle Verbindungen auf Anwendungsebene filtern. In Hardware getrennte Systeme sind hier solche, die jeweils über eigene Rechenkomponenten (CPU, RAM, etc.) verfügen und nur über Netzverbindungen zusammenhängen. Dies minimiert die Angriffsfläche für übergreifende Angriffe wie Covert Channel oder Side Channel. | Q68: Externe Netzanschlüsse | R68: IT-Betriebskonzept | S68: eine P-A-P-Struktur | T68: G 0.19 – Offenlegung schützenswerter Informationen; G 0.30 – Unberechtigte Nutzung oder Administration von Geräten und Systemen; G 0.40 – Verhinderung von Diensten (Denial of Service) | U68: 4 | V68: 2 | W68: 1 | X68: 2 | Y68: 1
A69: ARCH.5.1 | B69: Einschränkung und Inspektion von Verbindungen | C69: ARCH.5.1.12 | D69: Anforderungen bei erhöhtem Schutzbedarf | E69: Architektur für Netze KANN Verbindungen zwischen IT-Systemen anhand dynamischer Kriterien einschränken. | H69: unbearbeitet | M69: Vertraulichkeit | N69: NET.3.2.A2-UA.4; NET.3.4.A9-UA.2 | O69: intersects-with; subset-of | P69: Software-definierte Verbindungen sind logisch kontrollierte Netzwerkpfade, deren Zugriffsbedingungen nicht statisch hinterlegt, sondern anhand aktueller Merkmale bewertet werden; dynamische Kriterien meint dabei festgelegte Filterregeln, deren Werte situativ ermittelt werden, etwa über „context attributes“ oder „dynamic policies“. Solche Merkmale können als contextual signals wie momentane Auslastung, Gerätezustand („device posture“) oder zeitliche Rahmenbedingungen interpretiert werden, während die zugrunde liegenden Regeln unverändert bleiben und nur ihre Bewertung variiert. Dies kann helfen, laterale Bewegungen einzudämmen und kann gleichzeitig unerwartete Zugriffe in veränderten Betriebszuständen abblocken; ein Angriff, der unentdeckt Systeme durchqueren könnte, oder ein kompromittierter Client, der außerhalb definierter Parameter agiert, könnte dadurch abgewehrt werden. Praktisch kann dies über segmentierende „Software-Defined Networking“-Mechanismen, kontextabhängige Firewall-Policies oder adaptive Access-Control-Engines erfolgen. Eine angemessene Absicherung ist hier zu verstehen als ein Bündel verlässlicher Signale, die den Zustand eines Endpunkts oder Dienstes authentisch widerspiegeln. Als Varianten kommen etwa kontextabhängige SDN-Flows, regelbasierte Mikrosegmentierung über Identity-Tags oder der Einsatz von Policy-Engines infrage, die ihre Entscheidungen anhand dynamisch erfasster Werte wie Geräteintegrität, Standort oder Risikobewertung fällen. | Q69: Netze | R69: IT-Betriebskonzept | S69: Verbindungen zwischen IT-Systemen | T69: G 0.19 – Offenlegung schützenswerter Informationen; G 0.30 – Unberechtigte Nutzung oder Administration von Geräten und Systemen | U69: 5 | V69: 2 | W69: 1 | X69: 1 | Y69: 1
A70: ARCH.5.1 | B70: Einschränkung und Inspektion von Verbindungen | C70: ARCH.5.1.13 | D70: Anforderungen bei erhöhtem Schutzbedarf | E70: Architektur für Externe Netzanschlüsse KANN für die Filterung diverse Produkte unterschiedlicher Hersteller für eingehende und ausgehende Verbindungen installieren. | H70: unbearbeitet | M70: Vertraulichkeit | N70: NET.3.2.A27-UA.1 | O70: equivalent-to | P70: Wenn nur gleichartige Filtersysteme verwendet werden, könnten Angreifer eine Schwachstelle zweimal hintereinander ausnutzen, um Netzzugang zu erhalten. Der Einsatz verschiedener, voneinander unabhängiger Hersteller hintereinander verringert die Wahrscheinlichkeit, dass beide Systeme gleichzeitig anfällig sind. | Q70: Externe Netzanschlüsse | R70: IT-Betriebskonzept | S70: für die Filterung diverse Produkte unterschiedlicher Hersteller | T70: G 0.19 – Offenlegung schützenswerter Informationen; G 0.30 – Unberechtigte Nutzung oder Administration von Geräten und Systemen | U70: 5 | V70: 2 | W70: 1 | X70: 1 | Y70: 1
A71: ARCH.5.2 | B71: Blockieren direkter öffentlicher Verbindungen | D71: Standard-Anforderungen | E71: Gesamt: | H71: =IF(OR(COUNTBLANK($H$72:$H$72)>0,COUNTIF($H$72:$H$72,"unbearbeitet")=COUNTA($H$72:$H$72)),"Bitte Teilanforderungen ausfüllen",IF(COUNTIF($H$72:$H$72,"zu klären")>0,"zu klären",IF(COUNTIF($H$72:$H$72,"entbehrlich")=COUNTA($H$72:$H$72),"entbehrlich",IF(COUNTIF($H$72:$H$72,"verwiesen")=COUNTA($H$72:$H$72),"verwiesen",IF(COUNTIF($H$72:$H$72,"nein")+COUNTIF($H$72:$H$72,"entbehrlich")=COUNTA($H$72:$H$72),"nein",IF(COUNTIF($H$72:$H$72,"ja")+COUNTIF($H$72:$H$72,"entbehrlich")+COUNTIF($H$72:$H$72,"verwiesen")=COUNTA($H$72:$H$72),"ja","teilweise")))))) -> Bitte Teilanforderungen ausfüllen | M71: Vertraulichkeit | N71: CON.11.1.A16-UA.6; INF.10.A6-UA.6; NET.1.1.A8-UA.2; NET.3.2.A2-UA.2; NET.3.2.A2-UA.3; NET.3.2.A2-UA.5; SYS.2.1.A31-UA.2 | O71: subset-of; intersects-with; equivalent-to; intersects-with; equal-to; equivalent-to; equivalent-to | P71: Direkte Verbindungen sind hier alle Verbindungen, die nicht von der Filterung erfasst werden. Die Anforderung ist für Firewallsysteme umgesetzt, wenn deren eingehende Verbindungen ebenfalls vollständig gefiltert werden, bevor sie Daten an Systemschnittstellen senden können. | Q71: IT-Systeme | R71: Firewallregeln | S71: direkte Verbindungen von diesen ins öffentliche Netz | T71: G 0.23 – Unbefugtes Eindringen in IT-Systeme; G 0.14 – Ausspähen von Informationen (Spionage) | U71: 4 | V71: 2 | W71: 1 | X71: 1 | Y71: 0
A72: ARCH.5.2 | B72: Blockieren direkter öffentlicher Verbindungen | C72: ARCH.5.2 | D72: Standard-Anforderungen | E72: Architektur für IT-Systeme SOLLTE direkte Verbindungen von diesen ins öffentliche Netz blockieren. | H72: unbearbeitet | M72: Vertraulichkeit | N72: CON.11.1.A16-UA.6; INF.10.A6-UA.6; NET.1.1.A8-UA.2; NET.3.2.A2-UA.2; NET.3.2.A2-UA.3; NET.3.2.A2-UA.5; SYS.2.1.A31-UA.2 | O72: subset-of; intersects-with; equivalent-to; intersects-with; equal-to; equivalent-to; equivalent-to | P72: Direkte Verbindungen sind hier alle Verbindungen, die nicht von der Filterung erfasst werden. Die Anforderung ist für Firewallsysteme umgesetzt, wenn deren eingehende Verbindungen ebenfalls vollständig gefiltert werden, bevor sie Daten an Systemschnittstellen senden können. | Q72: IT-Systeme | R72: Firewallregeln | S72: direkte Verbindungen von diesen ins öffentliche Netz | T72: G 0.23 – Unbefugtes Eindringen in IT-Systeme; G 0.14 – Ausspähen von Informationen (Spionage) | U72: 4 | V72: 2 | W72: 1 | X72: 1 | Y72: 0
A73: ARCH.6.1 | B73: Kontrollierte Verbindungsführung | D73: Anforderungen bei erhöhtem Schutzbedarf | E73: Gesamt: | H73: =IF(OR(COUNTBLANK($H$74:$H$74)>0,COUNTIF($H$74:$H$74,"unbearbeitet")=COUNTA($H$74:$H$74)),"Bitte Teilanforderungen ausfüllen",IF(COUNTIF($H$74:$H$74,"zu klären")>0,"zu klären",IF(COUNTIF($H$74:$H$74,"entbehrlich")=COUNTA($H$74:$H$74),"entbehrlich",IF(COUNTIF($H$74:$H$74,"verwiesen")=COUNTA($H$74:$H$74),"verwiesen",IF(COUNTIF($H$74:$H$74,"nein")+COUNTIF($H$74:$H$74,"entbehrlich")=COUNTA($H$74:$H$74),"nein",IF(COUNTIF($H$74:$H$74,"ja")+COUNTIF($H$74:$H$74,"entbehrlich")+COUNTIF($H$74:$H$74,"verwiesen")=COUNTA($H$74:$H$74),"ja","teilweise")))))) -> Bitte Teilanforderungen ausfüllen | M73: Vertraulichkeit | N73: INF.14.A28-UA.2; NET.3.1.A4-UA.5; NET.3.2.A2-UA.2; NET.3.2.A2-UA.3; NET.3.3.A11-UA.1 | O73: subset-of; subset-of; subset-of; subset-of; subset-of | P73: Unter einer physisch kontrollierten Verbindungsführung kann in diesem Kontext die Verwendung dedizierter Leitungswege (Dark Fiber), sowie Hardware-Komponenten wie Router, Firewalls oder Trennstellen verstanden werden, die den Zugriff auf Leitungen oder Ports unmittelbar begrenzen. Eine logisch kontrollierte Verbindungsführung kann durch softwarebasierte Mechanismen wie VLANs, VPN-Tunnel oder Routing-Regeln erfolgen, die den Datenverkehr unabhängig von der physischen Leitung steuern. Ohne eine kontrollierte Verbindungsführung könnte ein Angreifer über eine ungeschützte oder direkt angebundene Leitung in interne Systeme eindringen und dort Schadsoftware platzieren, Daten manipulieren oder vertrauliche Informationen abziehen. Ebenso könnte durch eine unzureichend kontrollierte Verbindung ein Ausfall der Netzstabilität eintreten, etwa wenn über eine falsch konfigurierte Schnittstelle großflächiger Datenverkehr einbricht und produktive Systeme beeinträchtigt. Eine kontrollierte Architektur kann dagegen Angriffsflächen reduzieren, Datenströme nachvollziehbar machen und die Sicherheit der Informationsflüsse zwischen Institution und externen Partnern oder Netzanbietern erhöhen. Die Umsetzung kann beispielsweise durch klar definierte Übergabepunkte zum externen Netz erfolgen, an denen sämtliche eingehenden und ausgehenden Verbindungen zentral zusammenlaufen und durch Filter- oder Segmentierungsmechanismen geprüft werden. | Q73: Externe Netzanschlüsse | R73: IT-Betriebskonzept | S73: eine {{physisch oder logisch}} kontrollierte Verbindungsführung | T73: G 0.23 – Unbefugtes Eindringen in IT-Systeme; G 0.14 – Ausspähen von Informationen (Spionage) | U73: 5 | V73: 2 | W73: 1 | X73: 1 | Y73: 0
A74: ARCH.6.1 | B74: Kontrollierte Verbindungsführung | C74: ARCH.6.1 | D74: Anforderungen bei erhöhtem Schutzbedarf | E74: Architektur für Externe Netzanschlüsse KANN eine physisch oder logisch kontrollierte Verbindungsführung für Weitverkehrsverbindungen aktivieren. | H74: unbearbeitet | M74: Vertraulichkeit | N74: INF.14.A28-UA.2; NET.3.1.A4-UA.5; NET.3.2.A2-UA.2; NET.3.2.A2-UA.3; NET.3.3.A11-UA.1 | O74: subset-of; subset-of; subset-of; subset-of; subset-of | P74: Unter einer physisch kontrollierten Verbindungsführung kann in diesem Kontext die Verwendung dedizierter Leitungswege (Dark Fiber), sowie Hardware-Komponenten wie Router, Firewalls oder Trennstellen verstanden werden, die den Zugriff auf Leitungen oder Ports unmittelbar begrenzen. Eine logisch kontrollierte Verbindungsführung kann durch softwarebasierte Mechanismen wie VLANs, VPN-Tunnel oder Routing-Regeln erfolgen, die den Datenverkehr unabhängig von der physischen Leitung steuern. Ohne eine kontrollierte Verbindungsführung könnte ein Angreifer über eine ungeschützte oder direkt angebundene Leitung in interne Systeme eindringen und dort Schadsoftware platzieren, Daten manipulieren oder vertrauliche Informationen abziehen. Ebenso könnte durch eine unzureichend kontrollierte Verbindung ein Ausfall der Netzstabilität eintreten, etwa wenn über eine falsch konfigurierte Schnittstelle großflächiger Datenverkehr einbricht und produktive Systeme beeinträchtigt. Eine kontrollierte Architektur kann dagegen Angriffsflächen reduzieren, Datenströme nachvollziehbar machen und die Sicherheit der Informationsflüsse zwischen Institution und externen Partnern oder Netzanbietern erhöhen. Die Umsetzung kann beispielsweise durch klar definierte Übergabepunkte zum externen Netz erfolgen, an denen sämtliche eingehenden und ausgehenden Verbindungen zentral zusammenlaufen und durch Filter- oder Segmentierungsmechanismen geprüft werden. | Q74: Externe Netzanschlüsse | R74: IT-Betriebskonzept | S74: eine {{physisch oder logisch}} kontrollierte Verbindungsführung | T74: G 0.23 – Unbefugtes Eindringen in IT-Systeme; G 0.14 – Ausspähen von Informationen (Spionage) | U74: 5 | V74: 2 | W74: 1 | X74: 1 | Y74: 0
A75: ARCH.6.2 | B75: Verschlüsselung von Weiterverkehrsverbindungen | D75: Standard-Anforderungen | E75: Gesamt: | H75: =IF(OR(COUNTBLANK($H$76:$H$76)>0,COUNTIF($H$76:$H$76,"unbearbeitet")=COUNTA($H$76:$H$76)),"Bitte Teilanforderungen ausfüllen",IF(COUNTIF($H$76:$H$76,"zu klären")>0,"zu klären",IF(COUNTIF($H$76:$H$76,"entbehrlich")=COUNTA($H$76:$H$76),"entbehrlich",IF(COUNTIF($H$76:$H$76,"verwiesen")=COUNTA($H$76:$H$76),"verwiesen",IF(COUNTIF($H$76:$H$76,"nein")+COUNTIF($H$76:$H$76,"entbehrlich")=COUNTA($H$76:$H$76),"nein",IF(COUNTIF($H$76:$H$76,"ja")+COUNTIF($H$76:$H$76,"entbehrlich")+COUNTIF($H$76:$H$76,"verwiesen")=COUNTA($H$76:$H$76),"ja","teilweise")))))) -> Bitte Teilanforderungen ausfüllen | M75: Vertraulichkeit | N75: APP.3.1.A11-UA.2; APP.3.2.A11-UA.1; NET.1.1.A34-UA.3; OPS.1.2.5.A3-UA.4; OPS.1.2.5.A3-UA.5; OPS.1.2.5.A8-UA.4 | O75: equivalent-to; superset-of; superset-of; subset-of; subset-of; subset-of | P75: Ohne ein etabliertes Verschlüsselungsverfahren könnte sensible Kommunikation im Klartext übertragen werden, was Angreifern ein einfaches Mitlesen ermöglichen könnte – etwa durch Abhören in einem öffentlichen WLAN, durch kompromittierte Router eines Providers oder durch staatliche Massenüberwachung. Auch die unbemerkte Manipulation von Datenpaketen auf dem Weg zwischen Institution und Gegenstelle könnte die Integrität der übermittelten Inhalte gefährden und beispielsweise zu manipulierten Geschäftsdaten oder Schadcode-Einschleusungen führen. Der Einsatz von anerkannten Standards zur Verschlüsselung kann Vertraulichkeit und Integrität wahren, indem die Inhalte für Unbefugte unlesbar bleiben und Kommunikationspartner einander zuverlässig identifizieren können. So kann beispielsweise sichergestellt werden, dass eine entfernte Niederlassung tatsächlich mit der Zentrale verbunden ist und nicht mit einem Angreifer, der den Datenverkehr umleitet. Im Kontext externer Netzanschlüsse bezeichnet „Weitverkehrsnetz“ typischerweise öffentliche Netze wie das Internet oder auch gemietete WAN-Verbindungen über Telekommunikationsanbieter, die institutionsextern betrieben und potenziell unsicher sind. Anerkannte Standards sind z.B. TLS, IPsec oder WireGuard, die regelmäßig überprüft und weit verbreitet eingesetzt werden. Eine Institution kann diese Anforderung durch konkrete Maßnahmen umsetzen, z. B. indem sie Site-to-Site-VPNs zwischen Standorten einrichtet, Remote-Zugriffe von Mitarbeitenden ausschließlich über VPN-Gateways mit Zwei-Faktor-Authentisierung ermöglicht und auch Cloud-Dienste konsequent über gesicherte Verbindungen anbindet. | Q75: Externe Netzanschlüsse | R75: Konfigurationshistorie | S75: Verbindungen ins Weitverkehrsnetz | T75: G 0.15 – Abhören; G 0.14 – Ausspähen von Informationen (Spionage); G 0.18 – Fehlplanung oder fehlende Anpassung | U75: 3 | V75: 2 | W75: 1 | X75: 1 | Y75: 0
A76: ARCH.6.2 | B76: Verschlüsselung von Weiterverkehrsverbindungen | C76: ARCH.6.2 | D76: Standard-Anforderungen | E76: Architektur für Externe Netzanschlüsse SOLLTE Verbindungen ins Weitverkehrsnetz nach einem anerkannten Standard verschlüsseln. | H76: unbearbeitet | M76: Vertraulichkeit | N76: APP.3.1.A11-UA.2; APP.3.2.A11-UA.1; NET.1.1.A34-UA.3; OPS.1.2.5.A3-UA.4; OPS.1.2.5.A3-UA.5; OPS.1.2.5.A8-UA.4 | O76: equivalent-to; superset-of; superset-of; subset-of; subset-of; subset-of | P76: Ohne ein etabliertes Verschlüsselungsverfahren könnte sensible Kommunikation im Klartext übertragen werden, was Angreifern ein einfaches Mitlesen ermöglichen könnte – etwa durch Abhören in einem öffentlichen WLAN, durch kompromittierte Router eines Providers oder durch staatliche Massenüberwachung. Auch die unbemerkte Manipulation von Datenpaketen auf dem Weg zwischen Institution und Gegenstelle könnte die Integrität der übermittelten Inhalte gefährden und beispielsweise zu manipulierten Geschäftsdaten oder Schadcode-Einschleusungen führen. Der Einsatz von anerkannten Standards zur Verschlüsselung kann Vertraulichkeit und Integrität wahren, indem die Inhalte für Unbefugte unlesbar bleiben und Kommunikationspartner einander zuverlässig identifizieren können. So kann beispielsweise sichergestellt werden, dass eine entfernte Niederlassung tatsächlich mit der Zentrale verbunden ist und nicht mit einem Angreifer, der den Datenverkehr umleitet. Im Kontext externer Netzanschlüsse bezeichnet „Weitverkehrsnetz“ typischerweise öffentliche Netze wie das Internet oder auch gemietete WAN-Verbindungen über Telekommunikationsanbieter, die institutionsextern betrieben und potenziell unsicher sind. Anerkannte Standards sind z.B. TLS, IPsec oder WireGuard, die regelmäßig überprüft und weit verbreitet eingesetzt werden. Eine Institution kann diese Anforderung durch konkrete Maßnahmen umsetzen, z. B. indem sie Site-to-Site-VPNs zwischen Standorten einrichtet, Remote-Zugriffe von Mitarbeitenden ausschließlich über VPN-Gateways mit Zwei-Faktor-Authentisierung ermöglicht und auch Cloud-Dienste konsequent über gesicherte Verbindungen anbindet. | Q76: Externe Netzanschlüsse | R76: Konfigurationshistorie | S76: Verbindungen ins Weitverkehrsnetz | T76: G 0.15 – Abhören; G 0.14 – Ausspähen von Informationen (Spionage); G 0.18 – Fehlplanung oder fehlende Anpassung | U76: 3 | V76: 2 | W76: 1 | X76: 1 | Y76: 0
A77: ARCH.7.1 | B77: Dedizierte Hostsysteme für Server | D77: Standard-Anforderungen | E77: Gesamt: | H77: =IF(OR(COUNTBLANK($H$78:$H$78)>0,COUNTIF($H$78:$H$78,"unbearbeitet")=COUNTA($H$78:$H$78)),"Bitte Teilanforderungen ausfüllen",IF(COUNTIF($H$78:$H$78,"zu klären")>0,"zu klären",IF(COUNTIF($H$78:$H$78,"entbehrlich")=COUNTA($H$78:$H$78),"entbehrlich",IF(COUNTIF($H$78:$H$78,"verwiesen")=COUNTA($H$78:$H$78),"verwiesen",IF(COUNTIF($H$78:$H$78,"nein")+COUNTIF($H$78:$H$78,"entbehrlich")=COUNTA($H$78:$H$78),"nein",IF(COUNTIF($H$78:$H$78,"ja")+COUNTIF($H$78:$H$78,"entbehrlich")+COUNTIF($H$78:$H$78,"verwiesen")=COUNTA($H$78:$H$78),"ja","teilweise")))))) -> Bitte Teilanforderungen ausfüllen | M77: Vertraulichkeit | N77: APP.3.2.A1-UA.4; APP.3.6.A11-UA.2; APP.4.4.A15-UA.1; NET.3.4.A23-UA.3; SYS.1.1.A16-UA.3; SYS.1.1.A30-UA.1; SYS.1.6.A11-UA.1; SYS.2.1.A23-UA.1 | O77: equivalent-to; subset-of; subset-of; subset-of; subset-of; subset-of; subset-of; intersects-with | P77: „Serverdienste“ bezeichnen hier die logisch oder physisch abgegrenzten IT-Services (engl. server services), die bestimmte Funktionalitäten einer Anwendung bereitstellen, etwa Datenbankinstanzen, Webserver-Komponenten oder API-Endpunkte. Ein „dediziertes Hostsystem“ (engl. dedicated host system) ist dabei ein physischer oder virtueller Server, der ausschließlich für eine einzelne Anwendung und deren zugehörige Serverdienste betrieben wird, ohne dass darauf weitere fachfremde oder von der Anwendung unabhängige Dienste ausgeführt werden. Mögliche Bereitstellungsformen können virtualisierte Maschinen, Container-fähige Hypervisor-Instanzen, Bare-Metal-Server oder Appliances sein. Diese Abgrenzung dient der klaren Trennung von Verantwortlichkeiten, Konfigurationen und Ressourcen und reduziert die Komplexität innerhalb der Systemlandschaft. Sie schafft eine saubere Zuordnung zwischen Anwendung und ihrer technischen Plattform, was die Nachvollziehbarkeit, Wartbarkeit und Sicherheit der jeweiligen Lösung deutlich erhöht. Ziel ist, dass nicht mehrere Server-Anwendungen auf einem Betriebssystem (oder sogar auf Endgeräten) laufen, um systemische Risiken zu minimieren, die aus Mehrfachnutzung oder unklarer Ressourcenteilung entstehen könnten. Sonst könnte es etwa durch unerwartete Wechselwirkungen zwischen Diensten, fehlerhafte Berechtigungszuweisungen, unbeabsichtigte Seitenkanäle, unkontrollierte Ressourcenkonflikte oder Abhängigkeiten bei Systemupdates zu Betriebsproblemen oder lateralen Bewegungen von Angreifenden kommen. Die Anforderung kann auch durch die Verwendung von virtuellen Maschinen oder Containern realisiert werden. | Q77: Anwendungen | R77: Konfigurationshistorie | S77: Serverdienste ausschließlich auf für die Anwendung dedizierten {{virtuellen oder physischen}} Hostsystemen | T77: G 0.25 – Ausfall von Geräten oder Systemen; G 0.28 – Software-Schwachstellen oder -Fehler; G 0.23 – Unbefugtes Eindringen in IT-Systeme | U77: 3 | V77: 2 | W77: 1 | X77: 1 | Y77: 0
A78: ARCH.7.1 | B78: Dedizierte Hostsysteme für Server | C78: ARCH.7.1 | D78: Standard-Anforderungen | E78: Architektur für Anwendungen SOLLTE Serverdienste ausschließlich auf für die Anwendung dedizierten virtuellen oder physischen Hostsystemen platzieren. | H78: unbearbeitet | M78: Vertraulichkeit | N78: APP.3.2.A1-UA.4; APP.3.6.A11-UA.2; APP.4.4.A15-UA.1; NET.3.4.A23-UA.3; SYS.1.1.A16-UA.3; SYS.1.1.A30-UA.1; SYS.1.6.A11-UA.1; SYS.2.1.A23-UA.1 | O78: equivalent-to; subset-of; subset-of; subset-of; subset-of; subset-of; subset-of; intersects-with | P78: „Serverdienste“ bezeichnen hier die logisch oder physisch abgegrenzten IT-Services (engl. server services), die bestimmte Funktionalitäten einer Anwendung bereitstellen, etwa Datenbankinstanzen, Webserver-Komponenten oder API-Endpunkte. Ein „dediziertes Hostsystem“ (engl. dedicated host system) ist dabei ein physischer oder virtueller Server, der ausschließlich für eine einzelne Anwendung und deren zugehörige Serverdienste betrieben wird, ohne dass darauf weitere fachfremde oder von der Anwendung unabhängige Dienste ausgeführt werden. Mögliche Bereitstellungsformen können virtualisierte Maschinen, Container-fähige Hypervisor-Instanzen, Bare-Metal-Server oder Appliances sein. Diese Abgrenzung dient der klaren Trennung von Verantwortlichkeiten, Konfigurationen und Ressourcen und reduziert die Komplexität innerhalb der Systemlandschaft. Sie schafft eine saubere Zuordnung zwischen Anwendung und ihrer technischen Plattform, was die Nachvollziehbarkeit, Wartbarkeit und Sicherheit der jeweiligen Lösung deutlich erhöht. Ziel ist, dass nicht mehrere Server-Anwendungen auf einem Betriebssystem (oder sogar auf Endgeräten) laufen, um systemische Risiken zu minimieren, die aus Mehrfachnutzung oder unklarer Ressourcenteilung entstehen könnten. Sonst könnte es etwa durch unerwartete Wechselwirkungen zwischen Diensten, fehlerhafte Berechtigungszuweisungen, unbeabsichtigte Seitenkanäle, unkontrollierte Ressourcenkonflikte oder Abhängigkeiten bei Systemupdates zu Betriebsproblemen oder lateralen Bewegungen von Angreifenden kommen. Die Anforderung kann auch durch die Verwendung von virtuellen Maschinen oder Containern realisiert werden. | Q78: Anwendungen | R78: Konfigurationshistorie | S78: Serverdienste ausschließlich auf für die Anwendung dedizierten {{virtuellen oder physischen}} Hostsystemen | T78: G 0.25 – Ausfall von Geräten oder Systemen; G 0.28 – Software-Schwachstellen oder -Fehler; G 0.23 – Unbefugtes Eindringen in IT-Systeme | U78: 3 | V78: 2 | W78: 1 | X78: 1 | Y78: 0
A79: ARCH.7.2 | B79: Dedizierte Hardware | D79: Anforderungen bei erhöhtem Schutzbedarf | E79: Gesamt: | H79: =IF(OR(COUNTBLANK($H$80:$H$80)>0,COUNTIF($H$80:$H$80,"unbearbeitet")=COUNTA($H$80:$H$80)),"Bitte Teilanforderungen ausfüllen",IF(COUNTIF($H$80:$H$80,"zu klären")>0,"zu klären",IF(COUNTIF($H$80:$H$80,"entbehrlich")=COUNTA($H$80:$H$80),"entbehrlich",IF(COUNTIF($H$80:$H$80,"verwiesen")=COUNTA($H$80:$H$80),"verwiesen",IF(COUNTIF($H$80:$H$80,"nein")+COUNTIF($H$80:$H$80,"entbehrlich")=COUNTA($H$80:$H$80),"nein",IF(COUNTIF($H$80:$H$80,"ja")+COUNTIF($H$80:$H$80,"entbehrlich")+COUNTIF($H$80:$H$80,"verwiesen")=COUNTA($H$80:$H$80),"ja","teilweise")))))) -> Bitte Teilanforderungen ausfüllen | M79: Verfügbarkeit | N79: APP.3.6.A11-UA.2; SYS.2.5.A4-UA.2 | O79: subset-of; subset-of | P79: Um die Verfügbarkeit ausreichender Ressourcen sicherzustellen und zyklische Abhängigkeiten zu vermeiden (z.B. einen VM-Host, dessen Domain Controller auf ihm selbst virtualisiert wird). | Q79: Hostsysteme | R79: Konfigurationshistorie | S79: diese auf dedizierter Hardware | T79: G 0.27 – Ressourcenmangel; G 0.18 – Fehlplanung oder fehlende Anpassung | U79: 5 | V79: 1 | W79: 1 | X79: 2 | Y79: 0
A80: ARCH.7.2 | B80: Dedizierte Hardware | C80: ARCH.7.2 | D80: Anforderungen bei erhöhtem Schutzbedarf | E80: Architektur für Hostsysteme KANN diese auf dedizierter Hardware platzieren. | H80: unbearbeitet | M80: Verfügbarkeit | N80: APP.3.6.A11-UA.2; SYS.2.5.A4-UA.2 | O80: subset-of; subset-of | P80: Um die Verfügbarkeit ausreichender Ressourcen sicherzustellen und zyklische Abhängigkeiten zu vermeiden (z.B. einen VM-Host, dessen Domain Controller auf ihm selbst virtualisiert wird). | Q80: Hostsysteme | R80: Konfigurationshistorie | S80: diese auf dedizierter Hardware | T80: G 0.27 – Ressourcenmangel; G 0.18 – Fehlplanung oder fehlende Anpassung | U80: 5 | V80: 1 | W80: 1 | X80: 2 | Y80: 0
A81: ARCH.7.3 | B81: Entwicklungs- und Testumgebungen | D81: Standard-Anforderungen | E81: Gesamt: | H81: =IF(OR(COUNTBLANK($H$82:$H$82)>0,COUNTIF($H$82:$H$82,"unbearbeitet")=COUNTA($H$82:$H$82)),"Bitte Teilanforderungen ausfüllen",IF(COUNTIF($H$82:$H$82,"zu klären")>0,"zu klären",IF(COUNTIF($H$82:$H$82,"entbehrlich")=COUNTA($H$82:$H$82),"entbehrlich",IF(COUNTIF($H$82:$H$82,"verwiesen")=COUNTA($H$82:$H$82),"verwiesen",IF(COUNTIF($H$82:$H$82,"nein")+COUNTIF($H$82:$H$82,"entbehrlich")=COUNTA($H$82:$H$82),"nein",IF(COUNTIF($H$82:$H$82,"ja")+COUNTIF($H$82:$H$82,"entbehrlich")+COUNTIF($H$82:$H$82,"verwiesen")=COUNTA($H$82:$H$82),"ja","teilweise")))))) -> Bitte Teilanforderungen ausfüllen | M81: Vertraulichkeit, Verfügbarkeit | N81: APP.4.4.A1-UA.1; CON.8.A7-UA.8; OPS.1.1.6.A13-UA.1; OPS.1.1.6.A13-UA.2; SYS.1.5.A10-UA.4; SYS.1.7.A33-UA.1 | O81: intersects-with; subset-of; equivalent-to; equivalent-to; equal-to; subset-of | P81: Entwicklungs- und Testumgebungen sind dabei Umgebungen, in denen Software noch nicht ausgereift ist, sondern aktiv entwickelt, angepasst oder erprobt wird. Der Sinn der Vorgabe liegt darin, dass instabile oder absichtlich manipulierbare Testsysteme nicht auf denselben Hostsystemen betrieben werden sollten, auf denen produktive Anwendungen laufen. Andernfalls könnte ein Fehler in experimenteller Software dazu führen, dass der Hypervisor oder das Host-Betriebssystem beeinträchtigt wird und produktive Daten oder Dienste in Mitleidenschaft gezogen werden. Ebenso könnte Schadcode, der in einer Testumgebung eingebracht wird, unerwartet in produktive Netze durchgreifen. Durch die Trennung kann sichergestellt werden, dass ein Ausfall oder eine Kompromittierung in Entwicklungsumgebungen nicht die Stabilität und Vertraulichkeit produktiver Systeme gefährdet. Zur praktischen Umsetzung kann eine Institution Entwicklungs- und Testumgebungen auf dedizierte Virtualisierungshosts auslagern, die physisch oder logisch getrennt von den produktiven Hosts betrieben werden. Zusätzlich kann eine Institution Richtlinien zur Lifecycle-Kennzeichnung von VMs einführen (z. B. „dev“, „test“, „prod“ im Namen oder Tagging), um die klare Trennung auch in größeren Umgebungen praktikabel zu machen. | Q81: Virtualisierungslösungen | R81: Konfigurationshistorie | S81: Entwicklungs- und Testumgebungen nicht auf produktiven Hostsystemen | T81: G 0.18 – Fehlplanung oder fehlende Anpassung; G 0.46 – Integritätsverlust schützenswerter Informationen; G 0.19 – Offenlegung schützenswerter Informationen | U81: 4 | V81: 2 | W81: 1 | X81: 2 | Y81: 0
A82: ARCH.7.3 | B82: Entwicklungs- und Testumgebungen | C82: ARCH.7.3 | D82: Standard-Anforderungen | E82: Architektur für Virtualisierungslösungen SOLLTE Entwicklungs- und Testumgebungen nicht auf produktiven Hostsystemen platzieren. | H82: unbearbeitet | M82: Vertraulichkeit, Verfügbarkeit | N82: APP.4.4.A1-UA.1; CON.8.A7-UA.8; OPS.1.1.6.A13-UA.1; OPS.1.1.6.A13-UA.2; SYS.1.5.A10-UA.4; SYS.1.7.A33-UA.1 | O82: intersects-with; subset-of; equivalent-to; equivalent-to; equal-to; subset-of | P82: Entwicklungs- und Testumgebungen sind dabei Umgebungen, in denen Software noch nicht ausgereift ist, sondern aktiv entwickelt, angepasst oder erprobt wird. Der Sinn der Vorgabe liegt darin, dass instabile oder absichtlich manipulierbare Testsysteme nicht auf denselben Hostsystemen betrieben werden sollten, auf denen produktive Anwendungen laufen. Andernfalls könnte ein Fehler in experimenteller Software dazu führen, dass der Hypervisor oder das Host-Betriebssystem beeinträchtigt wird und produktive Daten oder Dienste in Mitleidenschaft gezogen werden. Ebenso könnte Schadcode, der in einer Testumgebung eingebracht wird, unerwartet in produktive Netze durchgreifen. Durch die Trennung kann sichergestellt werden, dass ein Ausfall oder eine Kompromittierung in Entwicklungsumgebungen nicht die Stabilität und Vertraulichkeit produktiver Systeme gefährdet. Zur praktischen Umsetzung kann eine Institution Entwicklungs- und Testumgebungen auf dedizierte Virtualisierungshosts auslagern, die physisch oder logisch getrennt von den produktiven Hosts betrieben werden. Zusätzlich kann eine Institution Richtlinien zur Lifecycle-Kennzeichnung von VMs einführen (z. B. „dev“, „test“, „prod“ im Namen oder Tagging), um die klare Trennung auch in größeren Umgebungen praktikabel zu machen. | Q82: Virtualisierungslösungen | R82: Konfigurationshistorie | S82: Entwicklungs- und Testumgebungen nicht auf produktiven Hostsystemen | T82: G 0.18 – Fehlplanung oder fehlende Anpassung; G 0.46 – Integritätsverlust schützenswerter Informationen; G 0.19 – Offenlegung schützenswerter Informationen | U82: 4 | V82: 2 | W82: 1 | X82: 2 | Y82: 0
A83: ARCH.8.1 | B83: Redundanz im Kernnetz | D83: Standard-Anforderungen | E83: Gesamt: | H83: =IF(OR(COUNTBLANK($H$84:$H$84)>0,COUNTIF($H$84:$H$84,"unbearbeitet")=COUNTA($H$84:$H$84)),"Bitte Teilanforderungen ausfüllen",IF(COUNTIF($H$84:$H$84,"zu klären")>0,"zu klären",IF(COUNTIF($H$84:$H$84,"entbehrlich")=COUNTA($H$84:$H$84),"entbehrlich",IF(COUNTIF($H$84:$H$84,"verwiesen")=COUNTA($H$84:$H$84),"verwiesen",IF(COUNTIF($H$84:$H$84,"nein")+COUNTIF($H$84:$H$84,"entbehrlich")=COUNTA($H$84:$H$84),"nein",IF(COUNTIF($H$84:$H$84,"ja")+COUNTIF($H$84:$H$84,"entbehrlich")+COUNTIF($H$84:$H$84,"verwiesen")=COUNTA($H$84:$H$84),"ja","teilweise")))))) -> Bitte Teilanforderungen ausfüllen | N83: NET.1.1.A16-UA.2; NET.1.1.A17-UA.2; NET.1.1.A29-UA.1; NET.1.1.A29-UA.3; NET.3.1.A26-UA.2; SYS.1.1.A28-UA.3 | O83: superset-of; superset-of; equivalent-to; superset-of; equal-to; superset-of | P83: Ziel hierbei ist es, dass beim Ausfall eines Systems oder einer Systemkomponente die Netzanbindung stets weiterhin funktionsfähig bleibt (Single-Point-of-Failure). | Q83: Netze | R83: Konfigurationshistorie | S83: für das Kernnetz redundante Netzkomponenten | T83: G 0.25 – Ausfall von Geräten oder Systemen; G 0.11 – Ausfall oder Störung von Dienstleistern; G 0.9 – Ausfall oder Störung von Kommunikationsnetzen; G 0.18 – Fehlplanung oder fehlende Anpassung | U83: 4 | V83: 1 | W83: 1 | X83: 1 | Y83: 0
A84: ARCH.8.1 | B84: Redundanz im Kernnetz | C84: ARCH.8.1 | D84: Standard-Anforderungen | E84: Architektur für Netze SOLLTE für das Kernnetz redundante Netzkomponenten installieren. | H84: unbearbeitet | N84: NET.1.1.A16-UA.2; NET.1.1.A17-UA.2; NET.1.1.A29-UA.1; NET.1.1.A29-UA.3; NET.3.1.A26-UA.2; SYS.1.1.A28-UA.3 | O84: superset-of; superset-of; equivalent-to; superset-of; equal-to; superset-of | P84: Ziel hierbei ist es, dass beim Ausfall eines Systems oder einer Systemkomponente die Netzanbindung stets weiterhin funktionsfähig bleibt (Single-Point-of-Failure). | Q84: Netze | R84: Konfigurationshistorie | S84: für das Kernnetz redundante Netzkomponenten | T84: G 0.25 – Ausfall von Geräten oder Systemen; G 0.11 – Ausfall oder Störung von Dienstleistern; G 0.9 – Ausfall oder Störung von Kommunikationsnetzen; G 0.18 – Fehlplanung oder fehlende Anpassung | U84: 4 | V84: 1 | W84: 1 | X84: 1 | Y84: 0
A85: ARCH.8.2 | B85: Redundante TK-Anbindung | D85: Anforderungen bei erhöhtem Schutzbedarf | E85: Gesamt: | H85: =IF(OR(COUNTBLANK($H$86:$H$86)>0,COUNTIF($H$86:$H$86,"unbearbeitet")=COUNTA($H$86:$H$86)),"Bitte Teilanforderungen ausfüllen",IF(COUNTIF($H$86:$H$86,"zu klären")>0,"zu klären",IF(COUNTIF($H$86:$H$86,"entbehrlich")=COUNTA($H$86:$H$86),"entbehrlich",IF(COUNTIF($H$86:$H$86,"verwiesen")=COUNTA($H$86:$H$86),"verwiesen",IF(COUNTIF($H$86:$H$86,"nein")+COUNTIF($H$86:$H$86,"entbehrlich")=COUNTA($H$86:$H$86),"nein",IF(COUNTIF($H$86:$H$86,"ja")+COUNTIF($H$86:$H$86,"entbehrlich")+COUNTIF($H$86:$H$86,"verwiesen")=COUNTA($H$86:$H$86),"ja","teilweise")))))) -> Bitte Teilanforderungen ausfüllen | M85: Verfügbarkeit | N85: APP.5.4.A11-UA.3; NET.1.1.A29-UA.1; NET.4.1.A19-UA.1; NET.4.1.A19-UA.2 | O85: superset-of; superset-of; equal-to; intersects-with | P85: Telekommunikationsanbindungen sind z.B. SIP-Trunks zum öffentlichen Telefonnetz (PSTN). Für weitere Details siehe „Kompendium für organisationsinterne Telekommunikationssysteme mit erhöhtem Schutzbedarf". | Q85: Externe Netzanschlüsse | R85: Konfigurationshistorie | S85: redundante TK-Anbindungen | T85: G 0.9 – Ausfall oder Störung von Kommunikationsnetzen; G 0.27 – Ressourcenmangel; G 0.25 – Ausfall von Geräten oder Systemen; G 0.11 – Ausfall oder Störung von Dienstleistern | U85: 4 | V85: 1 | W85: 1 | X85: 2 | Y85: 0
A86: ARCH.8.2 | B86: Redundante TK-Anbindung | C86: ARCH.8.2 | D86: Anforderungen bei erhöhtem Schutzbedarf | E86: Architektur für Externe Netzanschlüsse KANN redundante TK-Anbindungen für eingehende und ausgehende Verbindungen installieren. | H86: unbearbeitet | M86: Verfügbarkeit | N86: APP.5.4.A11-UA.3; NET.1.1.A29-UA.1; NET.4.1.A19-UA.1; NET.4.1.A19-UA.2 | O86: superset-of; superset-of; equal-to; intersects-with | P86: Telekommunikationsanbindungen sind z.B. SIP-Trunks zum öffentlichen Telefonnetz (PSTN). Für weitere Details siehe „Kompendium für organisationsinterne Telekommunikationssysteme mit erhöhtem Schutzbedarf". | Q86: Externe Netzanschlüsse | R86: Konfigurationshistorie | S86: redundante TK-Anbindungen | T86: G 0.9 – Ausfall oder Störung von Kommunikationsnetzen; G 0.27 – Ressourcenmangel; G 0.25 – Ausfall von Geräten oder Systemen; G 0.11 – Ausfall oder Störung von Dienstleistern | U86: 4 | V86: 1 | W86: 1 | X86: 2 | Y86: 0
A87: ARCH.8.3 | B87: Redundante Server | D87: Anforderungen bei erhöhtem Schutzbedarf | E87: Gesamt: | H87: =IF(OR(COUNTBLANK($H$88:$H$88)>0,COUNTIF($H$88:$H$88,"unbearbeitet")=COUNTA($H$88:$H$88)),"Bitte Teilanforderungen ausfüllen",IF(COUNTIF($H$88:$H$88,"zu klären")>0,"zu klären",IF(COUNTIF($H$88:$H$88,"entbehrlich")=COUNTA($H$88:$H$88),"entbehrlich",IF(COUNTIF($H$88:$H$88,"verwiesen")=COUNTA($H$88:$H$88),"verwiesen",IF(COUNTIF($H$88:$H$88,"nein")+COUNTIF($H$88:$H$88,"entbehrlich")=COUNTA($H$88:$H$88),"nein",IF(COUNTIF($H$88:$H$88,"ja")+COUNTIF($H$88:$H$88,"entbehrlich")+COUNTIF($H$88:$H$88,"verwiesen")=COUNTA($H$88:$H$88),"ja","teilweise")))))) -> Bitte Teilanforderungen ausfüllen | M87: Verfügbarkeit | N87: APP.3.2.A15-UA.1; APP.3.2.A15-UA.2; APP.3.6.A2-UA.1; APP.3.6.A2-UA.2; APP.5.3.A11-UA.1; NET.1.1.A28-UA.2; NET.1.1.A29-UA.1; NET.1.2.A30-UA.2; OPS.1.1.7.A20-UA.2; SYS.1.1.A15-UA.1; SYS.1.1.A25-UA.3; SYS.1.1.A28-UA.1; SYS.1.1.A28-UA.3; SYS.1.9.A21-UA.2; SYS.2.5.A18-UA.3; SYS.2.6.A15-UA.1 | O87: subset-of; subset-of; subset-of; subset-of; subset-of; superset-of; subset-of; subset-of; subset-of; intersects-with; subset-of; intersects-with; intersects-with; subset-of; subset-of; superset-of | P87: Redundanz ist gegeben, wenn sowohl das System als auch seine Netzanbindung redundant vorhanden sind. Das System selbst ist nur redundant, wenn auch seine Datenspeicher und Stromversorgung redundant ausgelegt sind. Automatische Umschaltung meint das Failover. Die Anforderung kann durch netzbasierte Load Balancer oder serverseitige automatisch Umschaltung umgesetzt werden (z.B. durch Hello-Pakete). | Q87: Anwendungen | R87: Konfigurationshistorie | S87: für die Funktionsfähigkeit der Anwendung erforderliche Hostsysteme redundant | T87: G 0.25 – Ausfall von Geräten oder Systemen; G 0.9 – Ausfall oder Störung von Kommunikationsnetzen; G 0.40 – Verhinderung von Diensten (Denial of Service); G 0.27 – Ressourcenmangel | U87: 5 | V87: 1 | W87: 1 | X87: 2 | Y87: 0
A88: ARCH.8.3 | B88: Redundante Server | C88: ARCH.8.3 | D88: Anforderungen bei erhöhtem Schutzbedarf | E88: Architektur für Anwendungen KANN für die Funktionsfähigkeit der Anwendung erforderliche Hostsysteme redundant installieren. | H88: unbearbeitet | M88: Verfügbarkeit | N88: APP.3.2.A15-UA.1; APP.3.2.A15-UA.2; APP.3.6.A2-UA.1; APP.3.6.A2-UA.2; APP.5.3.A11-UA.1; NET.1.1.A28-UA.2; NET.1.1.A29-UA.1; NET.1.2.A30-UA.2; OPS.1.1.7.A20-UA.2; SYS.1.1.A15-UA.1; SYS.1.1.A25-UA.3; SYS.1.1.A28-UA.1; SYS.1.1.A28-UA.3; SYS.1.9.A21-UA.2; SYS.2.5.A18-UA.3; SYS.2.6.A15-UA.1 | O88: subset-of; subset-of; subset-of; subset-of; subset-of; superset-of; subset-of; subset-of; subset-of; intersects-with; subset-of; intersects-with; intersects-with; subset-of; subset-of; superset-of | P88: Redundanz ist gegeben, wenn sowohl das System als auch seine Netzanbindung redundant vorhanden sind. Das System selbst ist nur redundant, wenn auch seine Datenspeicher und Stromversorgung redundant ausgelegt sind. Automatische Umschaltung meint das Failover. Die Anforderung kann durch netzbasierte Load Balancer oder serverseitige automatisch Umschaltung umgesetzt werden (z.B. durch Hello-Pakete). | Q88: Anwendungen | R88: Konfigurationshistorie | S88: für die Funktionsfähigkeit der Anwendung erforderliche Hostsysteme redundant | T88: G 0.25 – Ausfall von Geräten oder Systemen; G 0.9 – Ausfall oder Störung von Kommunikationsnetzen; G 0.40 – Verhinderung von Diensten (Denial of Service); G 0.27 – Ressourcenmangel | U88: 5 | V88: 1 | W88: 1 | X88: 2 | Y88: 0
A89: ARCH.9.1 | B89: Dimensionierung der Netzanbindung | D89: Standard-Anforderungen | E89: Gesamt: | H89: =IF(OR(COUNTBLANK($H$90:$H$90)>0,COUNTIF($H$90:$H$90,"unbearbeitet")=COUNTA($H$90:$H$90)),"Bitte Teilanforderungen ausfüllen",IF(COUNTIF($H$90:$H$90,"zu klären")>0,"zu klären",IF(COUNTIF($H$90:$H$90,"entbehrlich")=COUNTA($H$90:$H$90),"entbehrlich",IF(COUNTIF($H$90:$H$90,"verwiesen")=COUNTA($H$90:$H$90),"verwiesen",IF(COUNTIF($H$90:$H$90,"nein")+COUNTIF($H$90:$H$90,"entbehrlich")=COUNTA($H$90:$H$90),"nein",IF(COUNTIF($H$90:$H$90,"ja")+COUNTIF($H$90:$H$90,"entbehrlich")+COUNTIF($H$90:$H$90,"verwiesen")=COUNTA($H$90:$H$90),"ja","teilweise")))))) -> Bitte Teilanforderungen ausfüllen | M89: Verfügbarkeit | N89: INF.12.A17-UA.3; INF.12.A5-UA.1; NET.4.2.A1-UA.6; SYS.1.9.A6-UA.2; SYS.2.5.A2-UA.1 | O89: superset-of; superset-of; equivalent-to; subset-of; subset-of | P89: Für die Verfügbarkeit und Leistungsfähigkeit kritischer Geschäfts‑ und Fachverfahren ist eine bedarfsgerechte Netzanbindung erforderlich. Durch das strukturierte Erfassen des Bedarfes kann eine Institution frühzeitig Engpässe erkennen, Ausfallrisiken minimieren und eine wirtschaftliche Auslegung ihrer Anschlüsse erreichen. Gleichzeitig lässt sich so eine belastbare Grundlage für Kapazitäts‑, Notfall‑ und Budget‑Planungen schaffen, ohne sich allein auf starre Hersteller‑ oder Provider‑Vorgaben zu verlassen. Relevant ist hierbei die gesamte Netzstrecke zwischen Servern und IT-Clients, zumindest bis zum Internet-Anschluss der Institution. Beispiele für den Anwendungsbereich können sehr unterschiedlich ausfallen: In einem Call‑Center kann sich der Bedarf aus der Anzahl zeitgleich aktiver Soft‑Phones ableiten, deren Codec‑Bandbreite sowie der gewünschten Gesprächsqualität (Latenz < Antwortzeit in ms). In einem Forschungslabor kann die Anbindung darauf basieren, dass täglich große Datensätze mit einer bestimmten maximalen Bandbreite in Gbit/s zu Kooperationspartnern repliziert werden. Auch eine E‑Learning‑Plattform kann berücksichtigen, dass zu Semesterbeginn Studierende gleichzeitig parallele Video‑Streams in HD abrufen, während administrative Dienste weiterhin innerhalb einer bestimmten Antwortzeit in ms reagieren sollen. Dabei ist es sinnvoll, die Netzanbindung an realistische Belastungsszenarien anzupassen. | Q89: Netze | R89: IT-Betriebskonzept | S89: eine bedarfsgerechte Netzanbindung | T89: G 0.18 – Fehlplanung oder fehlende Anpassung; G 0.27 – Ressourcenmangel | U89: 3 | V89: 1 | W89: 1 | X89: 2 | Y89: 0
A90: ARCH.9.1 | B90: Dimensionierung der Netzanbindung | C90: ARCH.9.1 | D90: Standard-Anforderungen | E90: Architektur für Netze SOLLTE eine bedarfsgerechte Netzanbindung installieren. | H90: unbearbeitet | M90: Verfügbarkeit | N90: INF.12.A17-UA.3; INF.12.A5-UA.1; NET.4.2.A1-UA.6; SYS.1.9.A6-UA.2; SYS.2.5.A2-UA.1 | O90: superset-of; superset-of; equivalent-to; subset-of; subset-of | P90: Für die Verfügbarkeit und Leistungsfähigkeit kritischer Geschäfts‑ und Fachverfahren ist eine bedarfsgerechte Netzanbindung erforderlich. Durch das strukturierte Erfassen des Bedarfes kann eine Institution frühzeitig Engpässe erkennen, Ausfallrisiken minimieren und eine wirtschaftliche Auslegung ihrer Anschlüsse erreichen. Gleichzeitig lässt sich so eine belastbare Grundlage für Kapazitäts‑, Notfall‑ und Budget‑Planungen schaffen, ohne sich allein auf starre Hersteller‑ oder Provider‑Vorgaben zu verlassen. Relevant ist hierbei die gesamte Netzstrecke zwischen Servern und IT-Clients, zumindest bis zum Internet-Anschluss der Institution. Beispiele für den Anwendungsbereich können sehr unterschiedlich ausfallen: In einem Call‑Center kann sich der Bedarf aus der Anzahl zeitgleich aktiver Soft‑Phones ableiten, deren Codec‑Bandbreite sowie der gewünschten Gesprächsqualität (Latenz < Antwortzeit in ms). In einem Forschungslabor kann die Anbindung darauf basieren, dass täglich große Datensätze mit einer bestimmten maximalen Bandbreite in Gbit/s zu Kooperationspartnern repliziert werden. Auch eine E‑Learning‑Plattform kann berücksichtigen, dass zu Semesterbeginn Studierende gleichzeitig parallele Video‑Streams in HD abrufen, während administrative Dienste weiterhin innerhalb einer bestimmten Antwortzeit in ms reagieren sollen. Dabei ist es sinnvoll, die Netzanbindung an realistische Belastungsszenarien anzupassen. | Q90: Netze | R90: IT-Betriebskonzept | S90: eine bedarfsgerechte Netzanbindung | T90: G 0.18 – Fehlplanung oder fehlende Anpassung; G 0.27 – Ressourcenmangel | U90: 3 | V90: 1 | W90: 1 | X90: 2 | Y90: 0
A91: ARCH.9.2 | B91: Lastverteilung | D91: Anforderungen bei erhöhtem Schutzbedarf | E91: Gesamt: | H91: =IF(OR(COUNTBLANK($H$92:$H$92)>0,COUNTIF($H$92:$H$92,"unbearbeitet")=COUNTA($H$92:$H$92)),"Bitte Teilanforderungen ausfüllen",IF(COUNTIF($H$92:$H$92,"zu klären")>0,"zu klären",IF(COUNTIF($H$92:$H$92,"entbehrlich")=COUNTA($H$92:$H$92),"entbehrlich",IF(COUNTIF($H$92:$H$92,"verwiesen")=COUNTA($H$92:$H$92),"verwiesen",IF(COUNTIF($H$92:$H$92,"nein")+COUNTIF($H$92:$H$92,"entbehrlich")=COUNTA($H$92:$H$92),"nein",IF(COUNTIF($H$92:$H$92,"ja")+COUNTIF($H$92:$H$92,"entbehrlich")+COUNTIF($H$92:$H$92,"verwiesen")=COUNTA($H$92:$H$92),"ja","teilweise")))))) -> Bitte Teilanforderungen ausfüllen | M91: Verfügbarkeit | N91: SYS.1.1.A28-UA.1; SYS.2.6.A12-UA.2 | O91: superset-of; subset-of | P91: Netzbasierte Lastverteilung bedeutet hier, dass ein dedizierter Netzwerkdienst – z. B. über Load-Balancer oder Layer-4/Layer-7-Komponenten – den eingehenden Datenverkehr dynamisch auf mehrere Server oder Dienste verteilt. Serverbasierte Lastverteilung bedeutet dagegen, dass die beteiligten Systeme selbst Mechanismen bereitstellen, um Anfragen untereinander weiterzugeben oder zu koordinieren, etwa durch eingebaute Proxy- oder Cluster-Funktionalitäten. Der Zweck einer solchen Verteilung liegt in der Absicherung der Verfügbarkeit: Ein plötzlicher Anstieg von Benutzeranfragen könnte ansonsten einzelne Systeme überlasten und zu Ausfällen führen; ebenso könnte ein Defekt in einem Knoten die Gesamtleistung stark beeinträchtigen. Mit geeigneter Lastverteilung kann die Stabilität der Anwendung verbessert und ein unterbrechungsfreier Betrieb unterstützt werden. Zur Umsetzung kann die Institution netzbasierte Verfahren einsetzen, etwa (1) hardware- oder softwaregestützte Load-Balancer, die eingehende Verbindungen nach konfigurierbaren Regeln verteilen, (2) DNS-basierte Verfahren, bei denen Abfragen gezielt auf unterschiedliche Zielsysteme geleitet werden, oder (3) virtuelle Appliances in virtualisierten oder Cloud-nahen Umgebungen. Serverbasierte Verfahren können etwa durch den Einsatz von Cluster-Software, eingebaute Reverse-Proxy-Funktionen in Webservern oder den Einsatz von Message-Queues realisiert werden. Dabei kann eine Institution darauf achten, dass Monitoring-Funktionen integriert sind, um Engpässe frühzeitig zu erkennen, und dass Konfigurationen für Failover-Szenarien getestet werden. Auch ein gestuftes Testen der Lastverteilung unter realitätsnahen Bedingungen kann helfen, die Wirksamkeit sicherzustellen. | Q91: Anwendungen | R91: Konfigurationshistorie | S91: eine {{netzbasierte oder serverbasierte}} automatische Lastverteilung | T91: G 0.18 – Fehlplanung oder fehlende Anpassung; G 0.27 – Ressourcenmangel | U91: 5 | V91: 1 | W91: 1 | X91: 2 | Y91: 0
A92: ARCH.9.2 | B92: Lastverteilung | C92: ARCH.9.2 | D92: Anforderungen bei erhöhtem Schutzbedarf | E92: Architektur für Anwendungen KANN eine netzbasierte oder serverbasierte automatische Lastverteilung aktivieren. | H92: unbearbeitet | M92: Verfügbarkeit | N92: SYS.1.1.A28-UA.1; SYS.2.6.A12-UA.2 | O92: superset-of; subset-of | P92: Netzbasierte Lastverteilung bedeutet hier, dass ein dedizierter Netzwerkdienst – z. B. über Load-Balancer oder Layer-4/Layer-7-Komponenten – den eingehenden Datenverkehr dynamisch auf mehrere Server oder Dienste verteilt. Serverbasierte Lastverteilung bedeutet dagegen, dass die beteiligten Systeme selbst Mechanismen bereitstellen, um Anfragen untereinander weiterzugeben oder zu koordinieren, etwa durch eingebaute Proxy- oder Cluster-Funktionalitäten. Der Zweck einer solchen Verteilung liegt in der Absicherung der Verfügbarkeit: Ein plötzlicher Anstieg von Benutzeranfragen könnte ansonsten einzelne Systeme überlasten und zu Ausfällen führen; ebenso könnte ein Defekt in einem Knoten die Gesamtleistung stark beeinträchtigen. Mit geeigneter Lastverteilung kann die Stabilität der Anwendung verbessert und ein unterbrechungsfreier Betrieb unterstützt werden. Zur Umsetzung kann die Institution netzbasierte Verfahren einsetzen, etwa (1) hardware- oder softwaregestützte Load-Balancer, die eingehende Verbindungen nach konfigurierbaren Regeln verteilen, (2) DNS-basierte Verfahren, bei denen Abfragen gezielt auf unterschiedliche Zielsysteme geleitet werden, oder (3) virtuelle Appliances in virtualisierten oder Cloud-nahen Umgebungen. Serverbasierte Verfahren können etwa durch den Einsatz von Cluster-Software, eingebaute Reverse-Proxy-Funktionen in Webservern oder den Einsatz von Message-Queues realisiert werden. Dabei kann eine Institution darauf achten, dass Monitoring-Funktionen integriert sind, um Engpässe frühzeitig zu erkennen, und dass Konfigurationen für Failover-Szenarien getestet werden. Auch ein gestuftes Testen der Lastverteilung unter realitätsnahen Bedingungen kann helfen, die Wirksamkeit sicherzustellen. | Q92: Anwendungen | R92: Konfigurationshistorie | S92: eine {{netzbasierte oder serverbasierte}} automatische Lastverteilung | T92: G 0.18 – Fehlplanung oder fehlende Anpassung; G 0.27 – Ressourcenmangel | U92: 5 | V92: 1 | W92: 1 | X92: 2 | Y92: 0
A93: ARCH.9.3 | B93: Automatische Skalierung | D93: Anforderungen bei erhöhtem Schutzbedarf | E93: Gesamt: | H93: =IF(OR(COUNTBLANK($H$94:$H$94)>0,COUNTIF($H$94:$H$94,"unbearbeitet")=COUNTA($H$94:$H$94)),"Bitte Teilanforderungen ausfüllen",IF(COUNTIF($H$94:$H$94,"zu klären")>0,"zu klären",IF(COUNTIF($H$94:$H$94,"entbehrlich")=COUNTA($H$94:$H$94),"entbehrlich",IF(COUNTIF($H$94:$H$94,"verwiesen")=COUNTA($H$94:$H$94),"verwiesen",IF(COUNTIF($H$94:$H$94,"nein")+COUNTIF($H$94:$H$94,"entbehrlich")=COUNTA($H$94:$H$94),"nein",IF(COUNTIF($H$94:$H$94,"ja")+COUNTIF($H$94:$H$94,"entbehrlich")+COUNTIF($H$94:$H$94,"verwiesen")=COUNTA($H$94:$H$94),"ja","teilweise")))))) -> Bitte Teilanforderungen ausfüllen | N93: APP.4.3.A11-UA.4 | O93: intersects-with | P93: Automatische Skalierung ist die Fähigkeit einer Anwendungsarchitektur, die Anzahl der von einer Anwendung genutzten Serverinstanzen dynamisch und automatisiert zu erhöhen oder zu verringern. Grundlage für diese Anpassungen sind definierte Schwellwerte, die beispielsweise auf Metriken wie CPU-Auslastung, Speichernutzung oder Antwortzeiten beruhen können. Damit wird festgelegt, bei welchen messbaren Bedingungen zusätzliche Server gestartet oder wieder abgeschaltet werden. Typische Werte für Schwellwerte können etwa „80 % durchschnittliche CPU-Auslastung über 5 Minuten“, „weniger als 500 MB freier Arbeitsspeicher“ oder „Antwortzeit über 2 Sekunden bei mehr als 100 gleichzeitigen Anfragen“ sein. Ohne Auto-Scaling könnte es vorkommen, dass Anwendungen unter hoher Last nicht mehr reagieren, Datenverlust entsteht oder ganze Dienste für Nutzer unerreichbar werden. Umgekehrt kann Auto-Scaling helfen, Kosten und Ressourcen zu optimieren, indem ungenutzte Server wieder abgeschaltet werden. Eine sinnvolle Umsetzung kann beispielsweise durch den Einsatz von cloudbasierten Skalierungsgruppen erfolgen, die auf klar definierte Metriken reagieren, oder durch Virtualisierungsplattformen, die zusätzliche Instanzen automatisch bereitstellen. Praktische Tipps sind etwa (1) die Definition realistischer und getesteter Schwellwerte auf Basis historischer Lastprofile, (2) die Einrichtung von Stresstests, um das Verhalten bei Erreichen der Schwellwerte zu validieren, und (3) die Einführung von Alarmierungen, die Administratoren über ungewöhnlich häufiges Hoch- oder Runterskalieren informieren können. So kann die Institution sicherstellen, dass Auto-Scaling verlässlich funktioniert und gleichzeitig eine ökonomische Ressourcennutzung gewährleistet bleibt. | Q93: Anwendungen | R93: Konfigurationshistorie | S93: eine automatische Skalierung der von der Anwendung verwendeten Computerinstanzen | T93: G 0.27 – Ressourcenmangel | U93: 5 | V93: 0 | W93: 0 | X93: 1 | Y93: 0
A94: ARCH.9.3 | B94: Automatische Skalierung | C94: ARCH.9.3 | D94: Anforderungen bei erhöhtem Schutzbedarf | E94: Architektur für Anwendungen KANN eine automatische Skalierung der von der Anwendung verwendeten Computerinstanzen anhand von Schwellwerten aktivieren. | H94: unbearbeitet | N94: APP.4.3.A11-UA.4 | O94: intersects-with | P94: Automatische Skalierung ist die Fähigkeit einer Anwendungsarchitektur, die Anzahl der von einer Anwendung genutzten Serverinstanzen dynamisch und automatisiert zu erhöhen oder zu verringern. Grundlage für diese Anpassungen sind definierte Schwellwerte, die beispielsweise auf Metriken wie CPU-Auslastung, Speichernutzung oder Antwortzeiten beruhen können. Damit wird festgelegt, bei welchen messbaren Bedingungen zusätzliche Server gestartet oder wieder abgeschaltet werden. Typische Werte für Schwellwerte können etwa „80 % durchschnittliche CPU-Auslastung über 5 Minuten“, „weniger als 500 MB freier Arbeitsspeicher“ oder „Antwortzeit über 2 Sekunden bei mehr als 100 gleichzeitigen Anfragen“ sein. Ohne Auto-Scaling könnte es vorkommen, dass Anwendungen unter hoher Last nicht mehr reagieren, Datenverlust entsteht oder ganze Dienste für Nutzer unerreichbar werden. Umgekehrt kann Auto-Scaling helfen, Kosten und Ressourcen zu optimieren, indem ungenutzte Server wieder abgeschaltet werden. Eine sinnvolle Umsetzung kann beispielsweise durch den Einsatz von cloudbasierten Skalierungsgruppen erfolgen, die auf klar definierte Metriken reagieren, oder durch Virtualisierungsplattformen, die zusätzliche Instanzen automatisch bereitstellen. Praktische Tipps sind etwa (1) die Definition realistischer und getesteter Schwellwerte auf Basis historischer Lastprofile, (2) die Einrichtung von Stresstests, um das Verhalten bei Erreichen der Schwellwerte zu validieren, und (3) die Einführung von Alarmierungen, die Administratoren über ungewöhnlich häufiges Hoch- oder Runterskalieren informieren können. So kann die Institution sicherstellen, dass Auto-Scaling verlässlich funktioniert und gleichzeitig eine ökonomische Ressourcennutzung gewährleistet bleibt. | Q94: Anwendungen | R94: Konfigurationshistorie | S94: eine automatische Skalierung der von der Anwendung verwendeten Computerinstanzen | T94: G 0.27 – Ressourcenmangel | U94: 5 | V94: 0 | W94: 0 | X94: 1 | Y94: 0
A95: ARCH.9.4 | B95: Content Delivery Network | D95: Anforderungen bei erhöhtem Schutzbedarf | E95: Gesamt: | H95: =IF(OR(COUNTBLANK($H$96:$H$96)>0,COUNTIF($H$96:$H$96,"unbearbeitet")=COUNTA($H$96:$H$96)),"Bitte Teilanforderungen ausfüllen",IF(COUNTIF($H$96:$H$96,"zu klären")>0,"zu klären",IF(COUNTIF($H$96:$H$96,"entbehrlich")=COUNTA($H$96:$H$96),"entbehrlich",IF(COUNTIF($H$96:$H$96,"verwiesen")=COUNTA($H$96:$H$96),"verwiesen",IF(COUNTIF($H$96:$H$96,"nein")+COUNTIF($H$96:$H$96,"entbehrlich")=COUNTA($H$96:$H$96),"nein",IF(COUNTIF($H$96:$H$96,"ja")+COUNTIF($H$96:$H$96,"entbehrlich")+COUNTIF($H$96:$H$96,"verwiesen")=COUNTA($H$96:$H$96),"ja","teilweise")))))) -> Bitte Teilanforderungen ausfüllen | N95: NET.3.1.A17-UA.1; SYS.1.1.A25-UA.3; SYS.1.1.A28-UA.1 | O95: intersects-with; superset-of; superset-of | P95: Ein Content Delivery Network (CDN) ist ein Netz geographisch verteilter Server, welches Inhalte wie Webseiten und große Mediendateien auch bei hoher Last skaliert zur Verfügung stellt. CDNs sind sinnvoll für weltweit hochverfügbare Server-Anwendungen, da so Lastspitzen und DDoS-Angriffe abgemildert werden. Ein CDN kann selbst umgesetzt oder durch einen entsprechenden Dienstleister übernommen werden. | Q95: Anwendungen | R95: Konfigurationshistorie | S95: ein Content Delivery Network | T95: G 0.18 – Fehlplanung oder fehlende Anpassung; G 0.27 – Ressourcenmangel; G 0.25 – Ausfall von Geräten oder Systemen | U95: 5 | V95: 1 | W95: 1 | X95: 1 | Y95: 0
A96: ARCH.9.4 | B96: Content Delivery Network | C96: ARCH.9.4 | D96: Anforderungen bei erhöhtem Schutzbedarf | E96: Architektur für Anwendungen KANN ein Content Delivery Network installieren. | H96: unbearbeitet | N96: NET.3.1.A17-UA.1; SYS.1.1.A25-UA.3; SYS.1.1.A28-UA.1 | O96: intersects-with; superset-of; superset-of | P96: Ein Content Delivery Network (CDN) ist ein Netz geographisch verteilter Server, welches Inhalte wie Webseiten und große Mediendateien auch bei hoher Last skaliert zur Verfügung stellt. CDNs sind sinnvoll für weltweit hochverfügbare Server-Anwendungen, da so Lastspitzen und DDoS-Angriffe abgemildert werden. Ein CDN kann selbst umgesetzt oder durch einen entsprechenden Dienstleister übernommen werden. | Q96: Anwendungen | R96: Konfigurationshistorie | S96: ein Content Delivery Network | T96: G 0.18 – Fehlplanung oder fehlende Anpassung; G 0.27 – Ressourcenmangel; G 0.25 – Ausfall von Geräten oder Systemen | U96: 5 | V96: 1 | W96: 1 | X96: 1 | Y96: 0
A97: ARCH.9.5 | B97: Schutz gegen volumetrische DoS-Angriffe | D97: Anforderungen bei erhöhtem Schutzbedarf | E97: Gesamt: | H97: =IF(OR(COUNTBLANK($H$98:$H$98)>0,COUNTIF($H$98:$H$98,"unbearbeitet")=COUNTA($H$98:$H$98)),"Bitte Teilanforderungen ausfüllen",IF(COUNTIF($H$98:$H$98,"zu klären")>0,"zu klären",IF(COUNTIF($H$98:$H$98,"entbehrlich")=COUNTA($H$98:$H$98),"entbehrlich",IF(COUNTIF($H$98:$H$98,"verwiesen")=COUNTA($H$98:$H$98),"verwiesen",IF(COUNTIF($H$98:$H$98,"nein")+COUNTIF($H$98:$H$98,"entbehrlich")=COUNTA($H$98:$H$98),"nein",IF(COUNTIF($H$98:$H$98,"ja")+COUNTIF($H$98:$H$98,"entbehrlich")+COUNTIF($H$98:$H$98,"verwiesen")=COUNTA($H$98:$H$98),"ja","teilweise")))))) -> Bitte Teilanforderungen ausfüllen | N97: APP.3.2.A18-UA.2; APP.5.3.A2-UA.7; CON.10.A17-UA.1; NET.1.1.A30-UA.1; NET.1.1.A30-UA.2; NET.3.1.A17-UA.1; OPS.1.2.5.A20-UA.2 | O97: subset-of; equivalent-to; intersects-with; subset-of; subset-of; subset-of; subset-of | P97: Volumetrische Angriffe können z.B. durch die Verwendung von Anycast-DNS, Upstream Rate Limiting, On-Premise- oder Cloud-Scrubbing, BGP FlowSpec-Filter, Auto-Null-Routing oder Remotely Triggered Blackholing abgewehrt werden. | Q97: Netze | R97: Konfigurationshistorie | S97: Schutzmaßnahmen gegen volumetrische DoS-Angriffe | T97: G 0.27 – Ressourcenmangel; G 0.40 – Verhinderung von Diensten (Denial of Service); G 0.25 – Ausfall von Geräten oder Systemen | U97: 5 | V97: 0 | W97: 0 | X97: 1 | Y97: 0
A98: ARCH.9.5 | B98: Schutz gegen volumetrische DoS-Angriffe | C98: ARCH.9.5 | D98: Anforderungen bei erhöhtem Schutzbedarf | E98: Architektur für Netze KANN Schutzmaßnahmen gegen volumetrische DoS-Angriffe aktivieren. | H98: unbearbeitet | N98: APP.3.2.A18-UA.2; APP.5.3.A2-UA.7; CON.10.A17-UA.1; NET.1.1.A30-UA.1; NET.1.1.A30-UA.2; NET.3.1.A17-UA.1; OPS.1.2.5.A20-UA.2 | O98: subset-of; equivalent-to; intersects-with; subset-of; subset-of; subset-of; subset-of | P98: Volumetrische Angriffe können z.B. durch die Verwendung von Anycast-DNS, Upstream Rate Limiting, On-Premise- oder Cloud-Scrubbing, BGP FlowSpec-Filter, Auto-Null-Routing oder Remotely Triggered Blackholing abgewehrt werden. | Q98: Netze | R98: Konfigurationshistorie | S98: Schutzmaßnahmen gegen volumetrische DoS-Angriffe | T98: G 0.27 – Ressourcenmangel; G 0.40 – Verhinderung von Diensten (Denial of Service); G 0.25 – Ausfall von Geräten oder Systemen | U98: 5 | V98: 0 | W98: 0 | X98: 1 | Y98: 0

Sheet Dashboard
B2: Status Bearbeitung | C2: Anzahl
B3: Relevante Praktiken | C3: =COUNTIF(Praktiken!$C$5:$C$24,"Ja") -> 1
B4: Abgeschlossene Praktiken | C4: =COUNTIFS(Praktiken!$C$5:$C$24,"Ja",Praktiken!$G$5:$G$24,1) -> 0
B5: Begonnene Praktiken | C5: =COUNTIFS(Praktiken!$C$5:$C$24,"Ja",Praktiken!$G$5:$G$24,">0",Praktiken!$G$5:$G$24,"<1") -> 1
B7: Status Umsetzung | C7: Anzahl
B8: Teilanforderungen: ja | C8: =SUMIFS(Praktiken!$H$5:$H$24,Praktiken!$C$5:$C$24,"Ja") -> 1
B9: Teilanforderungen: nein | C9: =SUMIFS(Praktiken!$I$5:$I$24,Praktiken!$C$5:$C$24,"Ja") -> 0
B10: Teilanforderungen: teilweise | C10: =SUMIFS(Praktiken!$J$5:$J$24,Praktiken!$C$5:$C$24,"Ja") -> 0
B11: Teilanforderungen: entbehrlich | C11: =SUMIFS(Praktiken!$K$5:$K$24,Praktiken!$C$5:$C$24,"Ja") -> 0
B12: Teilanforderungen: verwiesen | C12: =SUMIFS(Praktiken!$L$5:$L$24,Praktiken!$C$5:$C$24,"Ja") -> 0
B13: Teilanforderungen: zu klären | C13: =SUMIFS(Praktiken!$M$5:$M$24,Praktiken!$C$5:$C$24,"Ja") -> 0
B14: Teilanforderungen: unbearbeitet | C14: =SUMIFS(Praktiken!$N$5:$N$24,Praktiken!$C$5:$C$24,"Ja") -> 56
B16: Erreichte Punkte je Schutzziel | C16: Punkte
B17: Vertraulichkeit | C17: =SUMIFS(Praktiken!$O$5:$O$24,Praktiken!$C$5:$C$24,"Ja") -> 2
B18: Integrität | C18: =SUMIFS(Praktiken!$P$5:$P$24,Praktiken!$C$5:$C$24,"Ja") -> 2
B19: Verfügbarkeit | C19: =SUMIFS(Praktiken!$Q$5:$Q$24,Praktiken!$C$5:$C$24,"Ja") -> 1
B20: Authentizität | C20: =SUMIFS(Praktiken!$R$5:$R$24,Praktiken!$C$5:$C$24,"Ja") -> 1
B23: Punkte = Summe der Schutzzielwerte (0–2) aller Teilanforderungen mit Status "ja". Entbehrliche und verwiesene Anforderungen zählen nicht mit.

Sheet Praktiken
A4: Praktik | B4: Titel | C4: Relevanz | D4: Zielobjekt | E4: Begründung | F4: Umsetzungsstand (%) | G4: Bearbeitungsstand (%) | H4: ja | I4: nein | J4: teilweise | K4: entbehrlich | L4: verwiesen | M4: zu klären | N4: unbearbeitet | O4: Punkte Vertraulichkeit | P4: Punkte Integrität | Q4: Punkte Verfügbarkeit | R4: Punkte Authentizität | S4: Zuständig | T4: Kommentar
A5: ARCH | B5: Architektur | F5: =IF($C5="Ja",IFERROR((COUNTIFS(ARCH!$C$7:$C$98,"<>",ARCH!$H$7:$H$98,"ja")+COUNTIFS(ARCH!$C$7:$C$98,"<>",ARCH!$H$7:$H$98,"entbehrlich")+COUNTIFS(ARCH!$C$7:$C$98,"<>",ARCH!$H$7:$H$98,"verwiesen"))/COUNTA(ARCH!$C$7:$C$98),0),"") | G5: =IF($C5="Ja",IFERROR((COUNTA(ARCH!$C$7:$C$98)-COUNTIFS(ARCH!$C$7:$C$98,"<>",ARCH!$H$7:$H$98,"unbearbeitet"))/COUNTA(ARCH!$C$7:$C$98),0),"") | H5: =IF($C5="Ja",COUNTIFS(ARCH!$C$7:$C$98,"<>",ARCH!$H$7:$H$98,"ja"),"") | I5: =IF($C5="Ja",COUNTIFS(ARCH!$C$7:$C$98,"<>",ARCH!$H$7:$H$98,"nein"),"") | J5: =IF($C5="Ja",COUNTIFS(ARCH!$C$7:$C$98,"<>",ARCH!$H$7:$H$98,"teilweise"),"") | K5: =IF($C5="Ja",COUNTIFS(ARCH!$C$7:$C$98,"<>",ARCH!$H$7:$H$98,"entbehrlich"),"") | L5: =IF($C5="Ja",COUNTIFS(ARCH!$C$7:$C$98,"<>",ARCH!$H$7:$H$98,"verwiesen"),"") | M5: =IF($C5="Ja",COUNTIFS(ARCH!$C$7:$C$98,"<>",ARCH!$H$7:$H$98,"zu klären"),"") | N5: =IF($C5="Ja",COUNTIFS(ARCH!$C$7:$C$98,"<>",ARCH!$H$7:$H$98,"unbearbeitet"),"") | O5: =IF($C5="Ja",SUMIFS(ARCH!$V$7:$V$98,ARCH!$C$7:$C$98,"<>",ARCH!$H$7:$H$98,"ja"),"") | P5: =IF($C5="Ja",SUMIFS(ARCH!$W$7:$W$98,ARCH!$C$7:$C$98,"<>",ARCH!$H$7:$H$98,"ja"),"") | Q5: =IF($C5="Ja",SUMIFS(ARCH!$X$7:$X$98,ARCH!$C$7:$C$98,"<>",ARCH!$H$7:$H$98,"ja"),"") | R5: =IF($C5="Ja",SUMIFS(ARCH!$Y$7:$Y$98,ARCH!$C$7:$C$98,"<>",ARCH!$H$7:$H$98,"ja"),"")
A6: ASST | B6: Informationen und Assets | C6: Ja | F6: =IF($C6="Ja",IFERROR((COUNTIFS(ASST!$C$7:$C$107,"<>",ASST!$H$7:$H$107,"ja")+COUNTIFS(ASST!$C$7:$C$107,"<>",ASST!$H$7:$H$107,"entbehrlich")+COUNTIFS(ASST!$C$7:$C$107,"<>",ASST!$H$7:$H$107,"verwiesen"))/COUNTA(ASST!$C$7:$C$107),0),"") -> 0.01754386 | G6: =IF($C6="Ja",IFERROR((COUNTA(ASST!$C$7:$C$107)-COUNTIFS(ASST!$C$7:$C$107,"<>",ASST!$H$7:$H$107,"unbearbeitet"))/COUNTA(ASST!$C$7:$C$107),0),"") -> 0.01754386 | H6: =IF($C6="Ja",COUNTIFS(ASST!$C$7:$C$107,"<>",ASST!$H$7:$H$107,"ja"),"") -> 1 | I6: =IF($C6="Ja",COUNTIFS(ASST!$C$7:$C$107,"<>",ASST!$H$7:$H$107,"nein"),"") -> 0 | J6: =IF($C6="Ja",COUNTIFS(ASST!$C$7:$C$107,"<>",ASST!$H$7:$H$107,"teilweise"),"") -> 0 | K6: =IF($C6="Ja",COUNTIFS(ASST!$C$7:$C$107,"<>",ASST!$H$7:$H$107,"entbehrlich"),"") -> 0 | L6: =IF($C6="Ja",COUNTIFS(ASST!$C$7:$C$107,"<>",ASST!$H$7:$H$107,"verwiesen"),"") -> 0 | M6: =IF($C6="Ja",COUNTIFS(ASST!$C$7:$C$107,"<>",ASST!$H$7:$H$107,"zu klären"),"") -> 0 | N6: =IF($C6="Ja",COUNTIFS(ASST!$C$7:$C$107,"<>",ASST!$H$7:$H$107,"unbearbeitet"),"") -> 56 | O6: =IF($C6="Ja",SUMIFS(ASST!$V$7:$V$107,ASST!$C$7:$C$107,"<>",ASST!$H$7:$H$107,"ja"),"") -> 2 | P6: =IF($C6="Ja",SUMIFS(ASST!$W$7:$W$107,ASST!$C$7:$C$107,"<>",ASST!$H$7:$H$107,"ja"),"") -> 2 | Q6: =IF($C6="Ja",SUMIFS(ASST!$X$7:$X$107,ASST!$C$7:$C$107,"<>",ASST!$H$7:$H$107,"ja"),"") -> 1 | R6: =IF($C6="Ja",SUMIFS(ASST!$Y$7:$Y$107,ASST!$C$7:$C$107,"<>",ASST!$H$7:$H$107,"ja"),"") -> 1
A7: BER | B7: Berechtigung | F7: =IF($C7="Ja",IFERROR((COUNTIFS(BER!$C$7:$C$176,"<>",BER!$H$7:$H$176,"ja")+COUNTIFS(BER!$C$7:$C$176,"<>",BER!$H$7:$H$176,"entbehrlich")+COUNTIFS(BER!$C$7:$C$176,"<>",BER!$H$7:$H$176,"verwiesen"))/COUNTA(BER!$C$7:$C$176),0),"") | G7: =IF($C7="Ja",IFERROR((COUNTA(BER!$C$7:$C$176)-COUNTIFS(BER!$C$7:$C$176,"<>",BER!$H$7:$H$176,"unbearbeitet"))/COUNTA(BER!$C$7:$C$176),0),"") | H7: =IF($C7="Ja",COUNTIFS(BER!$C$7:$C$176,"<>",BER!$H$7:$H$176,"ja"),"") | I7: =IF($C7="Ja",COUNTIFS(BER!$C$7:$C$176,"<>",BER!$H$7:$H$176,"nein"),"") | J7: =IF($C7="Ja",COUNTIFS(BER!$C$7:$C$176,"<>",BER!$H$7:$H$176,"teilweise"),"") | K7: =IF($C7="Ja",COUNTIFS(BER!$C$7:$C$176,"<>",BER!$H$7:$H$176,"entbehrlich"),"") | L7: =IF($C7="Ja",COUNTIFS(BER!$C$7:$C$176,"<>",BER!$H$7:$H$176,"verwiesen"),"") | M7: =IF($C7="Ja",COUNTIFS(BER!$C$7:$C$176,"<>",BER!$H$7:$H$176,"zu klären"),"") | N7: =IF($C7="Ja",COUNTIFS(BER!$C$7:$C$176,"<>",BER!$H$7:$H$176,"unbearbeitet"),"") | O7: =IF($C7="Ja",SUMIFS(BER!$V$7:$V$176,BER!$C$7:$C$176,"<>",BER!$H$7:$H$176,"ja"),"") | P7: =IF($C7="Ja",SUMIFS(BER!$W$7:$W$176,BER!$C$7:$C$176,"<>",BER!$H$7:$H$176,"ja"),"") | Q7: =IF($C7="Ja",SUMIFS(BER!$X$7:$X$176,BER!$C$7:$C$176,"<>",BER!$H$7:$H$176,"ja"),"") | R7: =IF($C7="Ja",SUMIFS(BER!$Y$7:$Y$176,BER!$C$7:$C$176,"<>",BER!$H$7:$H$176,"ja"),"")
A8: BES | B8: Beschaffungsmanagement | F8: =IF($C8="Ja",IFERROR((COUNTIFS(BES!$C$7:$C$168,"<>",BES!$H$7:$H$168,"ja")+COUNTIFS(BES!$C$7:$C$168,"<>",BES!$H$7:$H$168,"entbehrlich")+COUNTIFS(BES!$C$7:$C$168,"<>",BES!$H$7:$H$168,"verwiesen"))/COUNTA(BES!$C$7:$C$168),0),"") | G8: =IF($C8="Ja",IFERROR((COUNTA(BES!$C$7:$C$168)-COUNTIFS(BES!$C$7:$C$168,"<>",BES!$H$7:$H$168,"unbearbeitet"))/COUNTA(BES!$C$7:$C$168),0),"") | H8: =IF($C8="Ja",COUNTIFS(BES!$C$7:$C$168,"<>",BES!$H$7:$H$168,"ja"),"") | I8: =IF($C8="Ja",COUNTIFS(BES!$C$7:$C$168,"<>",BES!$H$7:$H$168,"nein"),"") | J8: =IF($C8="Ja",COUNTIFS(BES!$C$7:$C$168,"<>",BES!$H$7:$H$168,"teilweise"),"") | K8: =IF($C8="Ja",COUNTIFS(BES!$C$7:$C$168,"<>",BES!$H$7:$H$168,"entbehrlich"),"") | L8: =IF($C8="Ja",COUNTIFS(BES!$C$7:$C$168,"<>",BES!$H$7:$H$168,"verwiesen"),"") | M8: =IF($C8="Ja",COUNTIFS(BES!$C$7:$C$168,"<>",BES!$H$7:$H$168,"zu klären"),"") | N8: =IF($C8="Ja",COUNTIFS(BES!$C$7:$C$168,"<>",BES!$H$7:$H$168,"unbearbeitet"),"") | O8: =IF($C8="Ja",SUMIFS(BES!$V$7:$V$168,BES!$C$7:$C$168,"<>",BES!$H$7:$H$168,"ja"),"") | P8: =IF($C8="Ja",SUMIFS(BES!$W$7:$W$168,BES!$C$7:$C$168,"<>",BES!$H$7:$H$168,"ja"),"") | Q8: =IF($C8="Ja",SUMIFS(BES!$X$7:$X$168,BES!$C$7:$C$168,"<>",BES!$H$7:$H$168,"ja"),"") | R8: =IF($C8="Ja",SUMIFS(BES!$Y$7:$Y$168,BES!$C$7:$C$168,"<>",BES!$H$7:$H$168,"ja"),"")
A9: DET | B9: Detektion | F9: =IF($C9="Ja",IFERROR((COUNTIFS(DET!$C$7:$C$129,"<>",DET!$H$7:$H$129,"ja")+COUNTIFS(DET!$C$7:$C$129,"<>",DET!$H$7:$H$129,"entbehrlich")+COUNTIFS(DET!$C$7:$C$129,"<>",DET!$H$7:$H$129,"verwiesen"))/COUNTA(DET!$C$7:$C$129),0),"") | G9: =IF($C9="Ja",IFERROR((COUNTA(DET!$C$7:$C$129)-COUNTIFS(DET!$C$7:$C$129,"<>",DET!$H$7:$H$129,"unbearbeitet"))/COUNTA(DET!$C$7:$C$129),0),"") | H9: =IF($C9="Ja",COUNTIFS(DET!$C$7:$C$129,"<>",DET!$H$7:$H$129,"ja"),"") | I9: =IF($C9="Ja",COUNTIFS(DET!$C$7:$C$129,"<>",DET!$H$7:$H$129,"nein"),"") | J9: =IF($C9="Ja",COUNTIFS(DET!$C$7:$C$129,"<>",DET!$H$7:$H$129,"teilweise"),"") | K9: =IF($C9="Ja",COUNTIFS(DET!$C$7:$C$129,"<>",DET!$H$7:$H$129,"entbehrlich"),"") | L9: =IF($C9="Ja",COUNTIFS(DET!$C$7:$C$129,"<>",DET!$H$7:$H$129,"verwiesen"),"") | M9: =IF($C9="Ja",COUNTIFS(DET!$C$7:$C$129,"<>",DET!$H$7:$H$129,"zu klären"),"") | N9: =IF($C9="Ja",COUNTIFS(DET!$C$7:$C$129,"<>",DET!$H$7:$H$129,"unbearbeitet"),"") | O9: =IF($C9="Ja",SUMIFS(DET!$V$7:$V$129,DET!$C$7:$C$129,"<>",DET!$H$7:$H$129,"ja"),"") | P9: =IF($C9="Ja",SUMIFS(DET!$W$7:$W$129,DET!$C$7:$C$129,"<>",DET!$H$7:$H$129,"ja"),"") | Q9: =IF($C9="Ja",SUMIFS(DET!$X$7:$X$129,DET!$C$7:$C$129,"<>",DET!$H$7:$H$129,"ja"),"") | R9: =IF($C9="Ja",SUMIFS(DET!$Y$7:$Y$129,DET!$C$7:$C$129,"<>",DET!$H$7:$H$129,"ja"),"")
A10: DEV | B10: Entwicklung | F10: =IF($C10="Ja",IFERROR((COUNTIFS(DEV!$C$7:$C$68,"<>",DEV!$H$7:$H$68,"ja")+COUNTIFS(DEV!$C$7:$C$68,"<>",DEV!$H$7:$H$68,"entbehrlich")+COUNTIFS(DEV!$C$7:$C$68,"<>",DEV!$H$7:$H$68,"verwiesen"))/COUNTA(DEV!$C$7:$C$68),0),"") | G10: =IF($C10="Ja",IFERROR((COUNTA(DEV!$C$7:$C$68)-COUNTIFS(DEV!$C$7:$C$68,"<>",DEV!$H$7:$H$68,"unbearbeitet"))/COUNTA(DEV!$C$7:$C$68),0),"") | H10: =IF($C10="Ja",COUNTIFS(DEV!$C$7:$C$68,"<>",DEV!$H$7:$H$68,"ja"),"") | I10: =IF($C10="Ja",COUNTIFS(DEV!$C$7:$C$68,"<>",DEV!$H$7:$H$68,"nein"),"") | J10: =IF($C10="Ja",COUNTIFS(DEV!$C$7:$C$68,"<>",DEV!$H$7:$H$68,"teilweise"),"") | K10: =IF($C10="Ja",COUNTIFS(DEV!$C$7:$C$68,"<>",DEV!$H$7:$H$68,"entbehrlich"),"") | L10: =IF($C10="Ja",COUNTIFS(DEV!$C$7:$C$68,"<>",DEV!$H$7:$H$68,"verwiesen"),"") | M10: =IF($C10="Ja",COUNTIFS(DEV!$C$7:$C$68,"<>",DEV!$H$7:$H$68,"zu klären"),"") | N10: =IF($C10="Ja",COUNTIFS(DEV!$C$7:$C$68,"<>",DEV!$H$7:$H$68,"unbearbeitet"),"") | O10: =IF($C10="Ja",SUMIFS(DEV!$V$7:$V$68,DEV!$C$7:$C$68,"<>",DEV!$H$7:$H$68,"ja"),"") | P10: =IF($C10="Ja",SUMIFS(DEV!$W$7:$W$68,DEV!$C$7:$C$68,"<>",DEV!$H$7:$H$68,"ja"),"") | Q10: =IF($C10="Ja",SUMIFS(DEV!$X$7:$X$68,DEV!$C$7:$C$68,"<>",DEV!$H$7:$H$68,"ja"),"") | R10: =IF($C10="Ja",SUMIFS(DEV!$Y$7:$Y$68,DEV!$C$7:$C$68,"<>",DEV!$H$7:$H$68,"ja"),"")
A11: DLS | B11: Dienstleistersteuerung | F11: =IF($C11="Ja",IFERROR((COUNTIFS(DLS!$C$7:$C$35,"<>",DLS!$H$7:$H$35,"ja")+COUNTIFS(DLS!$C$7:$C$35,"<>",DLS!$H$7:$H$35,"entbehrlich")+COUNTIFS(DLS!$C$7:$C$35,"<>",DLS!$H$7:$H$35,"verwiesen"))/COUNTA(DLS!$C$7:$C$35),0),"") | G11: =IF($C11="Ja",IFERROR((COUNTA(DLS!$C$7:$C$35)-COUNTIFS(DLS!$C$7:$C$35,"<>",DLS!$H$7:$H$35,"unbearbeitet"))/COUNTA(DLS!$C$7:$C$35),0),"") | H11: =IF($C11="Ja",COUNTIFS(DLS!$C$7:$C$35,"<>",DLS!$H$7:$H$35,"ja"),"") | I11: =IF($C11="Ja",COUNTIFS(DLS!$C$7:$C$35,"<>",DLS!$H$7:$H$35,"nein"),"") | J11: =IF($C11="Ja",COUNTIFS(DLS!$C$7:$C$35,"<>",DLS!$H$7:$H$35,"teilweise"),"") | K11: =IF($C11="Ja",COUNTIFS(DLS!$C$7:$C$35,"<>",DLS!$H$7:$H$35,"entbehrlich"),"") | L11: =IF($C11="Ja",COUNTIFS(DLS!$C$7:$C$35,"<>",DLS!$H$7:$H$35,"verwiesen"),"") | M11: =IF($C11="Ja",COUNTIFS(DLS!$C$7:$C$35,"<>",DLS!$H$7:$H$35,"zu klären"),"") | N11: =IF($C11="Ja",COUNTIFS(DLS!$C$7:$C$35,"<>",DLS!$H$7:$H$35,"unbearbeitet"),"") | O11: =IF($C11="Ja",SUMIFS(DLS!$V$7:$V$35,DLS!$C$7:$C$35,"<>",DLS!$H$7:$H$35,"ja"),"") | P11: =IF($C11="Ja",SUMIFS(DLS!$W$7:$W$35,DLS!$C$7:$C$35,"<>",DLS!$H$7:$H$35,"ja"),"") | Q11: =IF($C11="Ja",SUMIFS(DLS!$X$7:$X$35,DLS!$C$7:$C$35,"<>",DLS!$H$7:$H$35,"ja"),"") | R11: =IF($C11="Ja",SUMIFS(DLS!$Y$7:$Y$35,DLS!$C$7:$C$35,"<>",DLS!$H$7:$H$35,"ja"),"")
A12: GC | B12: Governance und Compliance | F12: =IF($C12="Ja",IFERROR((COUNTIFS(GC!$C$7:$C$50,"<>",GC!$H$7:$H$50,"ja")+COUNTIFS(GC!$C$7:$C$50,"<>",GC!$H$7:$H$50,"entbehrlich")+COUNTIFS(GC!$C$7:$C$50,"<>",GC!$H$7:$H$50,"verwiesen"))/COUNTA(GC!$C$7:$C$50),0),"") | G12: =IF($C12="Ja",IFERROR((COUNTA(GC!$C$7:$C$50)-COUNTIFS(GC!$C$7:$C$50,"<>",GC!$H$7:$H$50,"unbearbeitet"))/COUNTA(GC!$C$7:$C$50),0),"") | H12: =IF($C12="Ja",COUNTIFS(GC!$C$7:$C$50,"<>",GC!$H$7:$H$50,"ja"),"") | I12: =IF($C12="Ja",COUNTIFS(GC!$C$7:$C$50,"<>",GC!$H$7:$H$50,"nein"),"") | J12: =IF($C12="Ja",COUNTIFS(GC!$C$7:$C$50,"<>",GC!$H$7:$H$50,"teilweise"),"") | K12: =IF($C12="Ja",COUNTIFS(GC!$C$7:$C$50,"<>",GC!$H$7:$H$50,"entbehrlich"),"") | L12: =IF($C12="Ja",COUNTIFS(GC!$C$7:$C$50,"<>",GC!$H$7:$H$50,"verwiesen"),"") | M12: =IF($C12="Ja",COUNTIFS(GC!$C$7:$C$50,"<>",GC!$H$7:$H$50,"zu klären"),"") | N12: =IF($C12="Ja",COUNTIFS(GC!$C$7:$C$50,"<>",GC!$H$7:$H$50,"unbearbeitet"),"") | O12: =IF($C12="Ja",SUMIFS(GC!$V$7:$V$50,GC!$C$7:$C$50,"<>",GC!$H$7:$H$50,"ja"),"") | P12: =IF($C12="Ja",SUMIFS(GC!$W$7:$W$50,GC!$C$7:$C$50,"<>",GC!$H$7:$H$50,"ja"),"") | Q12: =IF($C12="Ja",SUMIFS(GC!$X$7:$X$50,GC!$C$7:$C$50,"<>",GC!$H$7:$H$50,"ja"),"") | R12: =IF($C12="Ja",SUMIFS(GC!$Y$7:$Y$50,GC!$C$7:$C$50,"<>",GC!$H$7:$H$50,"ja"),"")
A13: GEB | B13: Gebäudemanagement | F13: =IF($C13="Ja",IFERROR((COUNTIFS(GEB!$C$7:$C$126,"<>",GEB!$H$7:$H$126,"ja")+COUNTIFS(GEB!$C$7:$C$126,"<>",GEB!$H$7:$H$126,"entbehrlich")+COUNTIFS(GEB!$C$7:$C$126,"<>",GEB!$H$7:$H$126,"verwiesen"))/COUNTA(GEB!$C$7:$C$126),0),"") | G13: =IF($C13="Ja",IFERROR((COUNTA(GEB!$C$7:$C$126)-COUNTIFS(GEB!$C$7:$C$126,"<>",GEB!$H$7:$H$126,"unbearbeitet"))/COUNTA(GEB!$C$7:$C$126),0),"") | H13: =IF($C13="Ja",COUNTIFS(GEB!$C$7:$C$126,"<>",GEB!$H$7:$H$126,"ja"),"") | I13: =IF($C13="Ja",COUNTIFS(GEB!$C$7:$C$126,"<>",GEB!$H$7:$H$126,"nein"),"") | J13: =IF($C13="Ja",COUNTIFS(GEB!$C$7:$C$126,"<>",GEB!$H$7:$H$126,"teilweise"),"") | K13: =IF($C13="Ja",COUNTIFS(GEB!$C$7:$C$126,"<>",GEB!$H$7:$H$126,"entbehrlich"),"") | L13: =IF($C13="Ja",COUNTIFS(GEB!$C$7:$C$126,"<>",GEB!$H$7:$H$126,"verwiesen"),"") | M13: =IF($C13="Ja",COUNTIFS(GEB!$C$7:$C$126,"<>",GEB!$H$7:$H$126,"zu klären"),"") | N13: =IF($C13="Ja",COUNTIFS(GEB!$C$7:$C$126,"<>",GEB!$H$7:$H$126,"unbearbeitet"),"") | O13: =IF($C13="Ja",SUMIFS(GEB!$V$7:$V$126,GEB!$C$7:$C$126,"<>",GEB!$H$7:$H$126,"ja"),"") | P13: =IF($C13="Ja",SUMIFS(GEB!$W$7:$W$126,GEB!$C$7:$C$126,"<>",GEB!$H$7:$H$126,"ja"),"") | Q13: =IF($C13="Ja",SUMIFS(GEB!$X$7:$X$126,GEB!$C$7:$C$126,"<>",GEB!$H$7:$H$126,"ja"),"") | R13: =IF($C13="Ja",SUMIFS(GEB!$Y$7:$Y$126,GEB!$C$7:$C$126,"<>",GEB!$H$7:$H$126,"ja"),"")
A14: KONF | B14: Konfiguration | F14: =IF($C14="Ja",IFERROR((COUNTIFS(KONF!$C$7:$C$275,"<>",KONF!$H$7:$H$275,"ja")+COUNTIFS(KONF!$C$7:$C$275,"<>",KONF!$H$7:$H$275,"entbehrlich")+COUNTIFS(KONF!$C$7:$C$275,"<>",KONF!$H$7:$H$275,"verwiesen"))/COUNTA(KONF!$C$7:$C$275),0),"") | G14: =IF($C14="Ja",IFERROR((COUNTA(KONF!$C$7:$C$275)-COUNTIFS(KONF!$C$7:$C$275,"<>",KONF!$H$7:$H$275,"unbearbeitet"))/COUNTA(KONF!$C$7:$C$275),0),"") | H14: =IF($C14="Ja",COUNTIFS(KONF!$C$7:$C$275,"<>",KONF!$H$7:$H$275,"ja"),"") | I14: =IF($C14="Ja",COUNTIFS(KONF!$C$7:$C$275,"<>",KONF!$H$7:$H$275,"nein"),"") | J14: =IF($C14="Ja",COUNTIFS(KONF!$C$7:$C$275,"<>",KONF!$H$7:$H$275,"teilweise"),"") | K14: =IF($C14="Ja",COUNTIFS(KONF!$C$7:$C$275,"<>",KONF!$H$7:$H$275,"entbehrlich"),"") | L14: =IF($C14="Ja",COUNTIFS(KONF!$C$7:$C$275,"<>",KONF!$H$7:$H$275,"verwiesen"),"") | M14: =IF($C14="Ja",COUNTIFS(KONF!$C$7:$C$275,"<>",KONF!$H$7:$H$275,"zu klären"),"") | N14: =IF($C14="Ja",COUNTIFS(KONF!$C$7:$C$275,"<>",KONF!$H$7:$H$275,"unbearbeitet"),"") | O14: =IF($C14="Ja",SUMIFS(KONF!$V$7:$V$275,KONF!$C$7:$C$275,"<>",KONF!$H$7:$H$275,"ja"),"") | P14: =IF($C14="Ja",SUMIFS(KONF!$W$7:$W$275,KONF!$C$7:$C$275,"<>",KONF!$H$7:$H$275,"ja"),"") | Q14: =IF($C14="Ja",SUMIFS(KONF!$X$7:$X$275,KONF!$C$7:$C$275,"<>",KONF!$H$7:$H$275,"ja"),"") | R14: =IF($C14="Ja",SUMIFS(KONF!$Y$7:$Y$275,KONF!$C$7:$C$275,"<>",KONF!$H$7:$H$275,"ja"),"")
A15: NOT | B15: Notfallplanung | F15: =IF($C15="Ja",IFERROR((COUNTIFS(NOT!$C$7:$C$68,"<>",NOT!$H$7:$H$68,"ja")+COUNTIFS(NOT!$C$7:$C$68,"<>",NOT!$H$7:$H$68,"entbehrlich")+COUNTIFS(NOT!$C$7:$C$68,"<>",NOT!$H$7:$H$68,"verwiesen"))/COUNTA(NOT!$C$7:$C$68),0),"") | G15: =IF($C15="Ja",IFERROR((COUNTA(NOT!$C$7:$C$68)-COUNTIFS(NOT!$C$7:$C$68,"<>",NOT!$H$7:$H$68,"unbearbeitet"))/COUNTA(NOT!$C$7:$C$68),0),"") | H15: =IF($C15="Ja",COUNTIFS(NOT!$C$7:$C$68,"<>",NOT!$H$7:$H$68,"ja"),"") | I15: =IF($C15="Ja",COUNTIFS(NOT!$C$7:$C$68,"<>",NOT!$H$7:$H$68,"nein"),"") | J15: =IF($C15="Ja",COUNTIFS(NOT!$C$7:$C$68,"<>",NOT!$H$7:$H$68,"teilweise"),"") | K15: =IF($C15="Ja",COUNTIFS(NOT!$C$7:$C$68,"<>",NOT!$H$7:$H$68,"entbehrlich"),"") | L15: =IF($C15="Ja",COUNTIFS(NOT!$C$7:$C$68,"<>",NOT!$H$7:$H$68,"verwiesen"),"") | M15: =IF($C15="Ja",COUNTIFS(NOT!$C$7:$C$68,"<>",NOT!$H$7:$H$68,"zu klären"),"") | N15: =IF($C15="Ja",COUNTIFS(NOT!$C$7:$C$68,"<>",NOT!$H$7:$H$68,"unbearbeitet"),"") | O15: =IF($C15="Ja",SUMIFS(NOT!$V$7:$V$68,NOT!$C$7:$C$68,"<>",NOT!$H$7:$H$68,"ja"),"") | P15: =IF($C15="Ja",SUMIFS(NOT!$W$7:$W$68,NOT!$C$7:$C$68,"<>",NOT!$H$7:$H$68,"ja"),"") | Q15: =IF($C15="Ja",SUMIFS(NOT!$X$7:$X$68,NOT!$C$7:$C$68,"<>",NOT!$H$7:$H$68,"ja"),"") | R15: =IF($C15="Ja",SUMIFS(NOT!$Y$7:$Y$68,NOT!$C$7:$C$68,"<>",NOT!$H$7:$H$68,"ja"),"")
A16: PERF | B16: Monitoring-Evaluation | F16: =IF($C16="Ja",IFERROR((COUNTIFS(PERF!$C$7:$C$36,"<>",PERF!$H$7:$H$36,"ja")+COUNTIFS(PERF!$C$7:$C$36,"<>",PERF!$H$7:$H$36,"entbehrlich")+COUNTIFS(PERF!$C$7:$C$36,"<>",PERF!$H$7:$H$36,"verwiesen"))/COUNTA(PERF!$C$7:$C$36),0),"") | G16: =IF($C16="Ja",IFERROR((COUNTA(PERF!$C$7:$C$36)-COUNTIFS(PERF!$C$7:$C$36,"<>",PERF!$H$7:$H$36,"unbearbeitet"))/COUNTA(PERF!$C$7:$C$36),0),"") | H16: =IF($C16="Ja",COUNTIFS(PERF!$C$7:$C$36,"<>",PERF!$H$7:$H$36,"ja"),"") | I16: =IF($C16="Ja",COUNTIFS(PERF!$C$7:$C$36,"<>",PERF!$H$7:$H$36,"nein"),"") | J16: =IF($C16="Ja",COUNTIFS(PERF!$C$7:$C$36,"<>",PERF!$H$7:$H$36,"teilweise"),"") | K16: =IF($C16="Ja",COUNTIFS(PERF!$C$7:$C$36,"<>",PERF!$H$7:$H$36,"entbehrlich"),"") | L16: =IF($C16="Ja",COUNTIFS(PERF!$C$7:$C$36,"<>",PERF!$H$7:$H$36,"verwiesen"),"") | M16: =IF($C16="Ja",COUNTIFS(PERF!$C$7:$C$36,"<>",PERF!$H$7:$H$36,"zu klären"),"") | N16: =IF($C16="Ja",COUNTIFS(PERF!$C$7:$C$36,"<>",PERF!$H$7:$H$36,"unbearbeitet"),"") | O16: =IF($C16="Ja",SUMIFS(PERF!$V$7:$V$36,PERF!$C$7:$C$36,"<>",PERF!$H$7:$H$36,"ja"),"") | P16: =IF($C16="Ja",SUMIFS(PERF!$W$7:$W$36,PERF!$C$7:$C$36,"<>",PERF!$H$7:$H$36,"ja"),"") | Q16: =IF($C16="Ja",SUMIFS(PERF!$X$7:$X$36,PERF!$C$7:$C$36,"<>",PERF!$H$7:$H$36,"ja"),"") | R16: =IF($C16="Ja",SUMIFS(PERF!$Y$7:$Y$36,PERF!$C$7:$C$36,"<>",PERF!$H$7:$H$36,"ja"),"")
A17: PERS | B17: Personal | F17: =IF($C17="Ja",IFERROR((COUNTIFS(PERS!$C$7:$C$54,"<>",PERS!$H$7:$H$54,"ja")+COUNTIFS(PERS!$C$7:$C$54,"<>",PERS!$H$7:$H$54,"entbehrlich")+COUNTIFS(PERS!$C$7:$C$54,"<>",PERS!$H$7:$H$54,"verwiesen"))/COUNTA(PERS!$C$7:$C$54),0),"") | G17: =IF($C17="Ja",IFERROR((COUNTA(PERS!$C$7:$C$54)-COUNTIFS(PERS!$C$7:$C$54,"<>",PERS!$H$7:$H$54,"unbearbeitet"))/COUNTA(PERS!$C$7:$C$54),0),"") | H17: =IF($C17="Ja",COUNTIFS(PERS!$C$7:$C$54,"<>",PERS!$H$7:$H$54,"ja"),"") | I17: =IF($C17="Ja",COUNTIFS(PERS!$C$7:$C$54,"<>",PERS!$H$7:$H$54,"nein"),"") | J17: =IF($C17="Ja",COUNTIFS(PERS!$C$7:$C$54,"<>",PERS!$H$7:$H$54,"teilweise"),"") | K17: =IF($C17="Ja",COUNTIFS(PERS!$C$7:$C$54,"<>",PERS!$H$7:$H$54,"entbehrlich"),"") | L17: =IF($C17="Ja",COUNTIFS(PERS!$C$7:$C$54,"<>",PERS!$H$7:$H$54,"verwiesen"),"") | M17: =IF($C17="Ja",COUNTIFS(PERS!$C$7:$C$54,"<>",PERS!$H$7:$H$54,"zu klären"),"") | N17: =IF($C17="Ja",COUNTIFS(PERS!$C$7:$C$54,"<>",PERS!$H$7:$H$54,"unbearbeitet"),"") | O17: =IF($C17="Ja",SUMIFS(PERS!$V$7:$V$54,PERS!$C$7:$C$54,"<>",PERS!$H$7:$H$54,"ja"),"") | P17: =IF($C17="Ja",SUMIFS(PERS!$W$7:$W$54,PERS!$C$7:$C$54,"<>",PERS!$H$7:$H$54,"ja"),"") | Q17: =IF($C17="Ja",SUMIFS(PERS!$X$7:$X$54,PERS!$C$7:$C$54,"<>",PERS!$H$7:$H$54,"ja"),"") | R17: =IF($C17="Ja",SUMIFS(PERS!$Y$7:$Y$54,PERS!$C$7:$C$54,"<>",PERS!$H$7:$H$54,"ja"),"")
A18: REA | B18: Sicherheitsvorfallsbehandlung | F18: =IF($C18="Ja",IFERROR((COUNTIFS(REA!$C$7:$C$38,"<>",REA!$H$7:$H$38,"ja")+COUNTIFS(REA!$C$7:$C$38,"<>",REA!$H$7:$H$38,"entbehrlich")+COUNTIFS(REA!$C$7:$C$38,"<>",REA!$H$7:$H$38,"verwiesen"))/COUNTA(REA!$C$7:$C$38),0),"") | G18: =IF($C18="Ja",IFERROR((COUNTA(REA!$C$7:$C$38)-COUNTIFS(REA!$C$7:$C$38,"<>",REA!$H$7:$H$38,"unbearbeitet"))/COUNTA(REA!$C$7:$C$38),0),"") | H18: =IF($C18="Ja",COUNTIFS(REA!$C$7:$C$38,"<>",REA!$H$7:$H$38,"ja"),"") | I18: =IF($C18="Ja",COUNTIFS(REA!$C$7:$C$38,"<>",REA!$H$7:$H$38,"nein"),"") | J18: =IF($C18="Ja",COUNTIFS(REA!$C$7:$C$38,"<>",REA!$H$7:$H$38,"teilweise"),"") | K18: =IF($C18="Ja",COUNTIFS(REA!$C$7:$C$38,"<>",REA!$H$7:$H$38,"entbehrlich"),"") | L18: =IF($C18="Ja",COUNTIFS(REA!$C$7:$C$38,"<>",REA!$H$7:$H$38,"verwiesen"),"") | M18: =IF($C18="Ja",COUNTIFS(REA!$C$7:$C$38,"<>",REA!$H$7:$H$38,"zu klären"),"") | N18: =IF($C18="Ja",COUNTIFS(REA!$C$7:$C$38,"<>",REA!$H$7:$H$38,"unbearbeitet"),"") | O18: =IF($C18="Ja",SUMIFS(REA!$V$7:$V$38,REA!$C$7:$C$38,"<>",REA!$H$7:$H$38,"ja"),"") | P18: =IF($C18="Ja",SUMIFS(REA!$W$7:$W$38,REA!$C$7:$C$38,"<>",REA!$H$7:$H$38,"ja"),"") | Q18: =IF($C18="Ja",SUMIFS(REA!$X$7:$X$38,REA!$C$7:$C$38,"<>",REA!$H$7:$H$38,"ja"),"") | R18: =IF($C18="Ja",SUMIFS(REA!$Y$7:$Y$38,REA!$C$7:$C$38,"<>",REA!$H$7:$H$38,"ja"),"")
A19: RISK | B19: Risikomanagement | F19: =IF($C19="Ja",IFERROR((COUNTIFS(RISK!$C$7:$C$14,"<>",RISK!$H$7:$H$14,"ja")+COUNTIFS(RISK!$C$7:$C$14,"<>",RISK!$H$7:$H$14,"entbehrlich")+COUNTIFS(RISK!$C$7:$C$14,"<>",RISK!$H$7:$H$14,"verwiesen"))/COUNTA(RISK!$C$7:$C$14),0),"") | G19: =IF($C19="Ja",IFERROR((COUNTA(RISK!$C$7:$C$14)-COUNTIFS(RISK!$C$7:$C$14,"<>",RISK!$H$7:$H$14,"unbearbeitet"))/COUNTA(RISK!$C$7:$C$14),0),"") | H19: =IF($C19="Ja",COUNTIFS(RISK!$C$7:$C$14,"<>",RISK!$H$7:$H$14,"ja"),"") | I19: =IF($C19="Ja",COUNTIFS(RISK!$C$7:$C$14,"<>",RISK!$H$7:$H$14,"nein"),"") | J19: =IF($C19="Ja",COUNTIFS(RISK!$C$7:$C$14,"<>",RISK!$H$7:$H$14,"teilweise"),"") | K19: =IF($C19="Ja",COUNTIFS(RISK!$C$7:$C$14,"<>",RISK!$H$7:$H$14,"entbehrlich"),"") | L19: =IF($C19="Ja",COUNTIFS(RISK!$C$7:$C$14,"<>",RISK!$H$7:$H$14,"verwiesen"),"") | M19: =IF($C19="Ja",COUNTIFS(RISK!$C$7:$C$14,"<>",RISK!$H$7:$H$14,"zu klären"),"") | N19: =IF($C19="Ja",COUNTIFS(RISK!$C$7:$C$14,"<>",RISK!$H$7:$H$14,"unbearbeitet"),"") | O19: =IF($C19="Ja",SUMIFS(RISK!$V$7:$V$14,RISK!$C$7:$C$14,"<>",RISK!$H$7:$H$14,"ja"),"") | P19: =IF($C19="Ja",SUMIFS(RISK!$W$7:$W$14,RISK!$C$7:$C$14,"<>",RISK!$H$7:$H$14,"ja"),"") | Q19: =IF($C19="Ja",SUMIFS(RISK!$X$7:$X$14,RISK!$C$7:$C$14,"<>",RISK!$H$7:$H$14,"ja"),"") | R19: =IF($C19="Ja",SUMIFS(RISK!$Y$7:$Y$14,RISK!$C$7:$C$14,"<>",RISK!$H$7:$H$14,"ja"),"")
A20: SENS | B20: Sensibilisierung | F20: =IF($C20="Ja",IFERROR((COUNTIFS(SENS!$C$7:$C$168,"<>",SENS!$H$7:$H$168,"ja")+COUNTIFS(SENS!$C$7:$C$168,"<>",SENS!$H$7:$H$168,"entbehrlich")+COUNTIFS(SENS!$C$7:$C$168,"<>",SENS!$H$7:$H$168,"verwiesen"))/COUNTA(SENS!$C$7:$C$168),0),"") | G20: =IF($C20="Ja",IFERROR((COUNTA(SENS!$C$7:$C$168)-COUNTIFS(SENS!$C$7:$C$168,"<>",SENS!$H$7:$H$168,"unbearbeitet"))/COUNTA(SENS!$C$7:$C$168),0),"") | H20: =IF($C20="Ja",COUNTIFS(SENS!$C$7:$C$168,"<>",SENS!$H$7:$H$168,"ja"),"") | I20: =IF($C20="Ja",COUNTIFS(SENS!$C$7:$C$168,"<>",SENS!$H$7:$H$168,"nein"),"") | J20: =IF($C20="Ja",COUNTIFS(SENS!$C$7:$C$168,"<>",SENS!$H$7:$H$168,"teilweise"),"") | K20: =IF($C20="Ja",COUNTIFS(SENS!$C$7:$C$168,"<>",SENS!$H$7:$H$168,"entbehrlich"),"") | L20: =IF($C20="Ja",COUNTIFS(SENS!$C$7:$C$168,"<>",SENS!$H$7:$H$168,"verwiesen"),"") | M20: =IF($C20="Ja",COUNTIFS(SENS!$C$7:$C$168,"<>",SENS!$H$7:$H$168,"zu klären"),"") | N20: =IF($C20="Ja",COUNTIFS(SENS!$C$7:$C$168,"<>",SENS!$H$7:$H$168,"unbearbeitet"),"") | O20: =IF($C20="Ja",SUMIFS(SENS!$V$7:$V$168,SENS!$C$7:$C$168,"<>",SENS!$H$7:$H$168,"ja"),"") | P20: =IF($C20="Ja",SUMIFS(SENS!$W$7:$W$168,SENS!$C$7:$C$168,"<>",SENS!$H$7:$H$168,"ja"),"") | Q20: =IF($C20="Ja",SUMIFS(SENS!$X$7:$X$168,SENS!$C$7:$C$168,"<>",SENS!$H$7:$H$168,"ja"),"") | R20: =IF($C20="Ja",SUMIFS(SENS!$Y$7:$Y$168,SENS!$C$7:$C$168,"<>",SENS!$H$7:$H$168,"ja"),"")
A21: STM | B21: Strukturmodellierung | F21: =IF($C21="Ja",IFERROR((COUNTIFS(STM!$C$7:$C$25,"<>",STM!$H$7:$H$25,"ja")+COUNTIFS(STM!$C$7:$C$25,"<>",STM!$H$7:$H$25,"entbehrlich")+COUNTIFS(STM!$C$7:$C$25,"<>",STM!$H$7:$H$25,"verwiesen"))/COUNTA(STM!$C$7:$C$25),0),"") | G21: =IF($C21="Ja",IFERROR((COUNTA(STM!$C$7:$C$25)-COUNTIFS(STM!$C$7:$C$25,"<>",STM!$H$7:$H$25,"unbearbeitet"))/COUNTA(STM!$C$7:$C$25),0),"") | H21: =IF($C21="Ja",COUNTIFS(STM!$C$7:$C$25,"<>",STM!$H$7:$H$25,"ja"),"") | I21: =IF($C21="Ja",COUNTIFS(STM!$C$7:$C$25,"<>",STM!$H$7:$H$25,"nein"),"") | J21: =IF($C21="Ja",COUNTIFS(STM!$C$7:$C$25,"<>",STM!$H$7:$H$25,"teilweise"),"") | K21: =IF($C21="Ja",COUNTIFS(STM!$C$7:$C$25,"<>",STM!$H$7:$H$25,"entbehrlich"),"") | L21: =IF($C21="Ja",COUNTIFS(STM!$C$7:$C$25,"<>",STM!$H$7:$H$25,"verwiesen"),"") | M21: =IF($C21="Ja",COUNTIFS(STM!$C$7:$C$25,"<>",STM!$H$7:$H$25,"zu klären"),"") | N21: =IF($C21="Ja",COUNTIFS(STM!$C$7:$C$25,"<>",STM!$H$7:$H$25,"unbearbeitet"),"") | O21: =IF($C21="Ja",SUMIFS(STM!$V$7:$V$25,STM!$C$7:$C$25,"<>",STM!$H$7:$H$25,"ja"),"") | P21: =IF($C21="Ja",SUMIFS(STM!$W$7:$W$25,STM!$C$7:$C$25,"<>",STM!$H$7:$H$25,"ja"),"") | Q21: =IF($C21="Ja",SUMIFS(STM!$X$7:$X$25,STM!$C$7:$C$25,"<>",STM!$H$7:$H$25,"ja"),"") | R21: =IF($C21="Ja",SUMIFS(STM!$Y$7:$Y$25,STM!$C$7:$C$25,"<>",STM!$H$7:$H$25,"ja"),"")
A22: TEST | B22: Änderungen und Tests | F22: =IF($C22="Ja",IFERROR((COUNTIFS(TEST!$C$7:$C$57,"<>",TEST!$H$7:$H$57,"ja")+COUNTIFS(TEST!$C$7:$C$57,"<>",TEST!$H$7:$H$57,"entbehrlich")+COUNTIFS(TEST!$C$7:$C$57,"<>",TEST!$H$7:$H$57,"verwiesen"))/COUNTA(TEST!$C$7:$C$57),0),"") | G22: =IF($C22="Ja",IFERROR((COUNTA(TEST!$C$7:$C$57)-COUNTIFS(TEST!$C$7:$C$57,"<>",TEST!$H$7:$H$57,"unbearbeitet"))/COUNTA(TEST!$C$7:$C$57),0),"") | H22: =IF($C22="Ja",COUNTIFS(TEST!$C$7:$C$57,"<>",TEST!$H$7:$H$57,"ja"),"") | I22: =IF($C22="Ja",COUNTIFS(TEST!$C$7:$C$57,"<>",TEST!$H$7:$H$57,"nein"),"") | J22: =IF($C22="Ja",COUNTIFS(TEST!$C$7:$C$57,"<>",TEST!$H$7:$H$57,"teilweise"),"") | K22: =IF($C22="Ja",COUNTIFS(TEST!$C$7:$C$57,"<>",TEST!$H$7:$H$57,"entbehrlich"),"") | L22: =IF($C22="Ja",COUNTIFS(TEST!$C$7:$C$57,"<>",TEST!$H$7:$H$57,"verwiesen"),"") | M22: =IF($C22="Ja",COUNTIFS(TEST!$C$7:$C$57,"<>",TEST!$H$7:$H$57,"zu klären"),"") | N22: =IF($C22="Ja",COUNTIFS(TEST!$C$7:$C$57,"<>",TEST!$H$7:$H$57,"unbearbeitet"),"") | O22: =IF($C22="Ja",SUMIFS(TEST!$V$7:$V$57,TEST!$C$7:$C$57,"<>",TEST!$H$7:$H$57,"ja"),"") | P22: =IF($C22="Ja",SUMIFS(TEST!$W$7:$W$57,TEST!$C$7:$C$57,"<>",TEST!$H$7:$H$57,"ja"),"") | Q22: =IF($C22="Ja",SUMIFS(TEST!$X$7:$X$57,TEST!$C$7:$C$57,"<>",TEST!$H$7:$H$57,"ja"),"") | R22: =IF($C22="Ja",SUMIFS(TEST!$Y$7:$Y$57,TEST!$C$7:$C$57,"<>",TEST!$H$7:$H$57,"ja"),"")
A23: UMS | B23: Umsetzung | F23: =IF($C23="Ja",IFERROR((COUNTIFS(UMS!$C$7:$C$28,"<>",UMS!$H$7:$H$28,"ja")+COUNTIFS(UMS!$C$7:$C$28,"<>",UMS!$H$7:$H$28,"entbehrlich")+COUNTIFS(UMS!$C$7:$C$28,"<>",UMS!$H$7:$H$28,"verwiesen"))/COUNTA(UMS!$C$7:$C$28),0),"") | G23: =IF($C23="Ja",IFERROR((COUNTA(UMS!$C$7:$C$28)-COUNTIFS(UMS!$C$7:$C$28,"<>",UMS!$H$7:$H$28,"unbearbeitet"))/COUNTA(UMS!$C$7:$C$28),0),"") | H23: =IF($C23="Ja",COUNTIFS(UMS!$C$7:$C$28,"<>",UMS!$H$7:$H$28,"ja"),"") | I23: =IF($C23="Ja",COUNTIFS(UMS!$C$7:$C$28,"<>",UMS!$H$7:$H$28,"nein"),"") | J23: =IF($C23="Ja",COUNTIFS(UMS!$C$7:$C$28,"<>",UMS!$H$7:$H$28,"teilweise"),"") | K23: =IF($C23="Ja",COUNTIFS(UMS!$C$7:$C$28,"<>",UMS!$H$7:$H$28,"entbehrlich"),"") | L23: =IF($C23="Ja",COUNTIFS(UMS!$C$7:$C$28,"<>",UMS!$H$7:$H$28,"verwiesen"),"") | M23: =IF($C23="Ja",COUNTIFS(UMS!$C$7:$C$28,"<>",UMS!$H$7:$H$28,"zu klären"),"") | N23: =IF($C23="Ja",COUNTIFS(UMS!$C$7:$C$28,"<>",UMS!$H$7:$H$28,"unbearbeitet"),"") | O23: =IF($C23="Ja",SUMIFS(UMS!$V$7:$V$28,UMS!$C$7:$C$28,"<>",UMS!$H$7:$H$28,"ja"),"") | P23: =IF($C23="Ja",SUMIFS(UMS!$W$7:$W$28,UMS!$C$7:$C$28,"<>",UMS!$H$7:$H$28,"ja"),"") | Q23: =IF($C23="Ja",SUMIFS(UMS!$X$7:$X$28,UMS!$C$7:$C$28,"<>",UMS!$H$7:$H$28,"ja"),"") | R23: =IF($C23="Ja",SUMIFS(UMS!$Y$7:$Y$28,UMS!$C$7:$C$28,"<>",UMS!$H$7:$H$28,"ja"),"")
A24: VRB | B24: Verbesserung | F24: =IF($C24="Ja",IFERROR((COUNTIFS(VRB!$C$7:$C$26,"<>",VRB!$H$7:$H$26,"ja")+COUNTIFS(VRB!$C$7:$C$26,"<>",VRB!$H$7:$H$26,"entbehrlich")+COUNTIFS(VRB!$C$7:$C$26,"<>",VRB!$H$7:$H$26,"verwiesen"))/COUNTA(VRB!$C$7:$C$26),0),"") | G24: =IF($C24="Ja",IFERROR((COUNTA(VRB!$C$7:$C$26)-COUNTIFS(VRB!$C$7:$C$26,"<>",VRB!$H$7:$H$26,"unbearbeitet"))/COUNTA(VRB!$C$7:$C$26),0),"") | H24: =IF($C24="Ja",COUNTIFS(VRB!$C$7:$C$26,"<>",VRB!$H$7:$H$26,"ja"),"") | I24: =IF($C24="Ja",COUNTIFS(VRB!$C$7:$C$26,"<>",VRB!$H$7:$H$26,"nein"),"") | J24: =IF($C24="Ja",COUNTIFS(VRB!$C$7:$C$26,"<>",VRB!$H$7:$H$26,"teilweise"),"") | K24: =IF($C24="Ja",COUNTIFS(VRB!$C$7:$C$26,"<>",VRB!$H$7:$H$26,"entbehrlich"),"") | L24: =IF($C24="Ja",COUNTIFS(VRB!$C$7:$C$26,"<>",VRB!$H$7:$H$26,"verwiesen"),"") | M24: =IF($C24="Ja",COUNTIFS(VRB!$C$7:$C$26,"<>",VRB!$H$7:$H$26,"zu klären"),"") | N24: =IF($C24="Ja",COUNTIFS(VRB!$C$7:$C$26,"<>",VRB!$H$7:$H$26,"unbearbeitet"),"") | O24: =IF($C24="Ja",SUMIFS(VRB!$V$7:$V$26,VRB!$C$7:$C$26,"<>",VRB!$H$7:$H$26,"ja"),"") | P24: =IF($C24="Ja",SUMIFS(VRB!$W$7:$W$26,VRB!$C$7:$C$26,"<>",VRB!$H$7:$H$26,"ja"),"") | Q24: =IF($C24="Ja",SUMIFS(VRB!$X$7:$X$26,VRB!$C$7:$C$26,"<>",VRB!$H$7:$H$26,"ja"),"") | R24: =IF($C24="Ja",SUMIFS(VRB!$Y$7:$Y$26,VRB!$C$7:$C$26,"<>",VRB!$H$7:$H$26,"ja"),"")
B27: Nur Praktiken mit Relevanz = "Ja" werden im Dashboard gezählt. Die Zähler beziehen sich auf Teilanforderungen, nicht auf Sammelzeilen.

Sheet ASST
A1: Einstufung gemäß Vorgaben der Sicherheitskonzeption
A3: ASST | B3: Informationen und Assets
A4: Zielobjekte | B4: =IF(Praktiken!D6="","",Praktiken!D6)
A5: Zuständig | B5: =IF(Praktiken!S6="","",Praktiken!S6)
A6: Anforderung | B6: Beschreibung | C6: Teilanforderung | D6: Schutz | E6: Anforderungstext | F6: Umsetzung | G6: Nachweis | H6: Status | I6: Maßnahme | J6: Befragte Person | K6: Prüfende Person | L6: Datum der Prüfung | M6: Schwerpunkt (Schutzziel) | N6: Alte Anforderung (IT-GS 2023) | O6: Beziehung (IT-GS 2023) | P6: Erläuterung | Q6: Zielobjekt-Kategorien | R6: Dokumentation | S6: Ergebnis | T6: Gefährdungen | U6: Aufwand | V6: Vertraulichkeit | W6: Integrität | X6: Verfügbarkeit | Y6: Authentizität
A7: ASST.1.1 | B7: Verfahren und Regelungen | D7: Basis-Anforderungen | E7: Gesamt: | H7: =IF(OR(COUNTBLANK($H$8:$H$10)>0,COUNTIF($H$8:$H$10,"unbearbeitet")=COUNTA($H$8:$H$10)),"Bitte Teilanforderungen ausfüllen",IF(COUNTIF($H$8:$H$10,"zu klären")>0,"zu klären",IF(COUNTIF($H$8:$H$10,"entbehrlich")=COUNTA($H$8:$H$10),"entbehrlich",IF(COUNTIF($H$8:$H$10,"verwiesen")=COUNTA($H$8:$H$10),"verwiesen",IF(COUNTIF($H$8:$H$10,"nein")+COUNTIF($H$8:$H$10,"entbehrlich")=COUNTA($H$8:$H$10),"nein",IF(COUNTIF($H$8:$H$10,"ja")+COUNTIF($H$8:$H$10,"entbehrlich")+COUNTIF($H$8:$H$10,"verwiesen")=COUNTA($H$8:$H$10),"ja","teilweise")))))) -> teilweise | M7: Vertraulichkeit | P7: Informationsmanagement ist der systematische Umgang mit Informationen während ihres gesamten Lebenszyklus, einschließlich von Regelungen, Prozessen und technischen Verfahren zur Erhebung, Verarbeitung, Speicherung, sowie Löschung und Vernichtung. Dazu gehören z.B. Schutzbedarf, Verarbeitung in den Geschäftsprozessen, Aufbewahrungs- und Löschfristen. Die bei der Festlegung des Verfahrens im Einzelnen zu berücksichtigenden Inhalte ergeben sich aus den Anforderungen dieser Praktik. | R7: IT-Betriebskonzept | S7: Verfahren und Regelungen zum Management von Informationen und damit verbundener Assets | T7: G 0.18 – Fehlplanung oder fehlende Anpassung; G 0.19 – Offenlegung schützenswerter Informationen | U7: 0 | V7: 2 | W7: 1 | X7: 1 | Y7: 0
A8: ASST.1.1 | B8: Verfahren und Regelungen | C8: ASST.1.1.1 | D8: Basis-Anforderungen | E8: Informationen und Assets MUSS die Verfahren und Regelungen dokumentieren. | H8: ja | M8: Vertraulichkeit, Integrität | P8: Ohne eine Dokumentation könnte die Einhaltung der Verfahren und Regelungen von der Tagesform oder dem individuellen Wissen einzelner Mitarbeiter abhängen, was zu inkonsistenten Entscheidungen und Fehlern führen könnte; insbesondere beim Ausscheiden eines langjährigen Administrators könnte wertvolles prozessuales Wissen verloren gehen. Eine klare Dokumentation sichert die Verbindlichkeit und Wiederholbarkeit und dient als unverzichtbare Grundlage für die Einarbeitung neuer Kollegen, für die Durchführung von Audits und zur einheitlichen Anwendung der Regeln in der gesamten Institution. Die Dokumentation kann in einem eigenständigen Dokument als Richtlinie erfolgen, aber auch als Abschnitt in einem bereits bestehenden Dokument oder über die digital strukturiere Erfassung von Maßnahmen zur Umsetzung der Anforderungen, etwa über eine Software zum Management der Informationssicherheit. Sinnvoll ist es Ort und Struktur der Dokumentation an der jeweiligen Zielgruppe, d.h. den für das Management und die Umsetzung verantwortlichen Personen oder Rollen, auszurichten. | R8: IT-Betriebskonzept | S8: die Verfahren und Regelungen | T8: G 0.18 – Fehlplanung oder fehlende Anpassung; G 0.37 – Abstreiten von Handlungen | U8: 0 | V8: 2 | W8: 2 | X8: 1 | Y8: 1
